Workbook

Sheet FPT Digital Retail JSC | Cash F
A1: FPT Digital Retail JSC | Cash Flow 11-Oct-2023 12:01
A3: Cash Flow
A4: Industry - Annual Standardised in Millions of Vietnamese Dong
B5: 2016 | C5: 2017 | D5: 2018 | E5: 2019 | F5: 2019 | G5: 2020 | H5: 2021 | I5: 2022 | J5: 2023F | K5: 2024F | L5: 2025F | M5: 2026F | N5: 2027F | O5: 2028F
A6: Earnings Quality Score | B6: N/A | C6: N/A | D6: 2 | E6: -- | F6: 17 | G6: 89 | H6: 10 | I6: 12
A7: Period End Date | B7: 31-Dec-2016 | C7: 31-Dec-2017 | D7: 31-Dec-2018 | E7: 31-Dec-2019 | F7: 31-Dec-2019 | G7: 31-Dec-2020 | H7: 31-Dec-2021 | I7: 31-Dec-2022 | J7: 31-Dec-2018 | K7: 31-Dec-2019 | L7: 31-Dec-2019 | M7: 31-Dec-2020 | N7: 31-Dec-2021 | O7: 31-Dec-2022
A8: Period Length | B8: 12 Months | C8: 12 Months | D8: 12 Months | E8: 12 Months | F8: 12 Months | G8: 12 Months | H8: 12 Months | I8: 12 Months | J8: 12 Months | K8: 12 Months | L8: 12 Months | M8: 12 Months | N8: 12 Months | O8: 12 Months
A9: Update Type | B9: Updated | C9: Updated | D9: Updated | E9: Updated | F9: Restated | G9: Updated | H9: Updated | I9: Updated | J9: Updated | K9: Updated | L9: Restated | M9: Updated | N9: Updated | O9: Updated
A10: Statement Date | B10: 31-Dec-2017 | C10: 31-Dec-2017 | D10: 31-Dec-2018 | E10: 31-Dec-2019 | F10: 31-Dec-2020 | G10: 31-Dec-2020 | H10: 31-Dec-2021 | I10: 31-Dec-2022 | J10: 31-Dec-2018 | K10: 31-Dec-2019 | L10: 31-Dec-2020 | M10: 31-Dec-2020 | N10: 31-Dec-2021 | O10: 31-Dec-2022
A11: Reporting Unit | B11: Thousands | C11: Thousands | D11: Thousands | E11: Thousands | F11: Thousands | G11: Thousands | H11: Thousands | I11: Thousands | J11: Thousands | K11: Thousands | L11: Thousands | M11: Thousands | N11: Thousands | O11: Thousands
A12: Update Date | B12: 30-Oct-2020 | C12: 23-Nov-2022 | D12: 06-Jun-2022 | E12: 06-Jun-2023 | F12: 06-Jun-2023 | G12: 06-Jun-2023 | H12: 06-Jun-2023 | I12: 08-Jun-2023 | J12: 06-Jun-2022 | K12: 06-Jun-2023 | L12: 06-Jun-2023 | M12: 06-Jun-2023 | N12: 06-Jun-2023 | O12: 08-Jun-2023
A13: Reporting Currency | B13: Vietnamese Dong | C13: Vietnamese Dong | D13: Vietnamese Dong | E13: Vietnamese Dong | F13: Vietnamese Dong | G13: Vietnamese Dong | H13: Vietnamese Dong | I13: Vietnamese Dong | J13: Vietnamese Dong | K13: Vietnamese Dong | L13: Vietnamese Dong | M13: Vietnamese Dong | N13: Vietnamese Dong | O13: Vietnamese Dong
A14: Source | B14: ARS | C14: ARS | D14: ARS | E14: ARS | F14: ARS | G14: ARS | H14: ARS | I14: ARS | J14: ARS | K14: ARS | L14: ARS | M14: ARS | N14: ARS | O14: ARS
A15: Source Date | B15: 27-Apr-2018 | C15: 27-Apr-2018 | D15: 16-Apr-2019 | E15: 31-Mar-2020 | F15: 31-Mar-2021 | G15: 31-Mar-2021 | H15: 14-Mar-2022 | I15: 27-Mar-2023 | J15: 16-Apr-2019 | K15: 31-Mar-2020 | L15: 31-Mar-2021 | M15: 31-Mar-2021 | N15: 14-Mar-2022 | O15: 27-Mar-2023
A16: Original Announcement Date | B16: 10-Apr-2018 03:48 | C16: 27-Apr-2018 05:00 | D16: 21-Jan-2019 11:01 | E16: 22-Jan-2020 14:59 | F16: 01-Feb-2021 06:43 | G16: 01-Feb-2021 06:43 | H16: 07-Feb-2022 15:18 | I16: 31-Jan-2023 20:37 | J16: 21-Jan-2019 11:01 | K16: 22-Jan-2020 14:59 | L16: 01-Feb-2021 06:43 | M16: 01-Feb-2021 06:43 | N16: 07-Feb-2022 15:18 | O16: 31-Jan-2023 20:37
A17: Complete Statement | B17: Complete | C17: Complete | D17: Complete | E17: Complete | F17: Complete | G17: Complete | H17: Complete | I17: Complete | J17: Complete | K17: Complete | L17: Complete | M17: Complete | N17: Complete | O17: Complete
A18: Flash Update | B18: No | C18: No | D18: No | E18: No | F18: No | G18: No | H18: No | I18: No | J18: No | K18: No | L18: No | M18: No | N18: No | O18: No
... A22: Accounting Standard | B22: Vietnamese Accounting Standards | C22: Vietnamese Accounting Standards | D22: Vietnamese Accounting Standards | E22: Vietnamese Accounting Standards | F22: Vietnamese Accounting Standards | G22: Vietnamese Accounting Standards | H22: Vietnamese Accounting Standards | I22: Vietnamese Accounting Standards | J22: Vietnamese Accounting Standards | K22: Vietnamese Accounting Standards | L22: Vietnamese Accounting Standards | M22: Vietnamese Accounting Standards | N22: Vietnamese Accounting Standards | O22: Vietnamese Accounting Standards
A23: Cash Flow-Operating Activities (VND Millions)
A24: Net Income/Starting Line | B24: 259383 | C24: 363074 | D24: 434775 | E24: 278003 | F24: 278003 | G24: 28427 | H24: 554140 | I24: 485623
A25: Depreciation/Depletion | B25: 1705 | C25: 498 | D25: 781 | E25: 837 | F25: 837 | G25: 1372 | H25: 3811 | I25: 115286
A26: Depreciation | B26: 1705 | C26: 498 | D26: 781 | E26: 837 | F26: 837 | G26: 1372 | H26: 3811 | I26: 115286
A27: Amortization | B27: -- | C27: 586 | D27: -- | E27: -- | F27: -- | G27: -- | H27: -- | I27: --
A28: Amortization of Intangibles | B28: -- | C28: 586 | D28: -- | E28: -- | F28: -- | G28: -- | H28: -- | I28: --
A29: Deferred Taxes | B29: -- | C29: -- | D29: -- | E29: -- | F29: -- | G29: -- | H29: -- | I29: --
A30: Non-Cash Items | B30: 36188 | C30: 19667 | D30: 86821 | E30: 91276 | F30: 91276 | G30: 92129 | H30: -60641 | I30: 79146
A31: Unusual Items | B31: -54495 | C31: -34483 | D31: -20946 | E31: -61193 | F31: -61193 | G31: -55871 | H31: -169344 | I31: -147854
A32: Other Non-Cash Items | B32: 90683 | C32: 54150 | D32: 107767 | E32: 152469 | F32: 152469 | G32: 148000 | H32: 108703 | I32: 227000
A33: Changes in Working Capital | B33: -56446 | C33: -204966 | D33: -1909113 | E33: -478312 | F33: -495767 | G33: 1396404 | H33: -1971663 | I33: -2187748 | J33: =I33*(1+J34) -> -1144435.4 | K33: =J33*(1+K34) -> -676930.99 | L33: =K33*(1+L34) -> -394718.79 | M33: =L33*(1+M34) -> -227153.47 | N33: =M33*(1+N34) -> -141451.99 | O33: =N33*(1+O34) -> -85123.534
D34: =D33/('FPT Digital Retail JSC | Income'!E23-'FPT Digital Retail JSC | Income'!D23) -> -0.8872085 | E34: =E33/('FPT Digital Retail JSC | Income'!F23-'FPT Digital Retail JSC | Income'!E23) -> -0.35811848 | F34: =F33/('FPT Digital Retail JSC | Income'!F23-'FPT Digital Retail JSC | Income'!E23) -> -0.37118727 | G34: =G33/('FPT Digital Retail JSC | Income'!G23-'FPT Digital Retail JSC | Income'!F23) -> -0.70792069 | H34: =H33/('FPT Digital Retail JSC | Income'!H23-'FPT Digital Retail JSC | Income'!G23) -> -0.25169489 | I34: =I33/('FPT Digital Retail JSC | Income'!I23-'FPT Digital Retail JSC | Income'!H23) -> -0.28520319 | J34: =AVERAGE(D34:I34) -> -0.47688884 | K34: =AVERAGE(E34:J34) -> -0.40850223 | L34: =AVERAGE(F34:K34) -> -0.41689952 | M34: =AVERAGE(G34:L34) -> -0.42451822 | N34: =AVERAGE(H34:M34) -> -0.37728448 | O34: =AVERAGE(I34:N34) -> -0.39821608
A35: Changes in Working Capital | B35: -56446 | C35: -204966 | D35: =SUM(D36,D39,D40,D42) -> -1709917 | E35: =SUM(E36,E39,E40,E42) -> -259588 | F35: =SUM(F36,F39,F40,F42) -> 1279781 | G35: =SUM(G36,G39,G40,G42) -> -1552472 | H35: =SUM(H36,H39,H40,H42) -> -3292417 | I35: =SUM(I36,I39,I40,I42) -> -3172437 | J35: =SUM(J36,J39,J40,J42) -> -1856662.9 | K35: =SUM(K36,K39,K40,K42) -> -1158338.2 | ... O35: =SUM(O36,O39,O40,O42) -> 8964987.8
A36: Accounts Receivable | B36: -289037 | C36: -432257 | D36: -60063 | E36: 131186 | F36: 113731 | G36: -79330 | H36: 51734 | I36: -93023 | J36: =I36*(1+J38) -> -90625.774 | K36: =J36*(1+K38) -> -87505.502 | L36: =K36*(1+L38) -> -84879.653 | M36: =L36*(1+M38) -> -83112.702 | N36: =M36*(1+N38) -> -81651.265 | O36: =N36*(1+O38) -> -80066.108
A37: Accounts Receivable | D37: ='FPT Digital Retail JSC | BS'!D27-'FPT Digital Retail JSC | BS'!C27 -> -74823 | E37: ='FPT Digital Retail JSC | BS'!E27-'FPT Digital Retail JSC | BS'!D27 -> 40076 | F37: ='FPT Digital Retail JSC | BS'!E27-'FPT Digital Retail JSC | BS'!D27 -> 40076 | G37: ='FPT Digital Retail JSC | BS'!F27-'FPT Digital Retail JSC | BS'!E27 -> -145516 | H37: ='FPT Digital Retail JSC | BS'!G27-'FPT Digital Retail JSC | BS'!F27 -> -41622 | I37: ='FPT Digital Retail JSC | BS'!H27-'FPT Digital Retail JSC | BS'!G27 -> 9502 | J37: ='FPT Digital Retail JSC | BS'!H27-'FPT Digital Retail JSC | BS'!I27 -> -253885.41 | K37: ='FPT Digital Retail JSC | BS'!I27-'FPT Digital Retail JSC | BS'!J27 -> 21535.212 | L37: ='FPT Digital Retail JSC | BS'!J27-'FPT Digital Retail JSC | BS'!K27 -> 46423.236 | M37: ='FPT Digital Retail JSC | BS'!K27-'FPT Digital Retail JSC | BS'!L27 -> -5331.9931 | N37: ='FPT Digital Retail JSC | BS'!L27-'FPT Digital Retail JSC | BS'!M27 -> -43604.398 | O37: ='FPT Digital Retail JSC | BS'!M27-'FPT Digital Retail JSC | BS'!N27 -> -65726.922
A38: % sales change | D38: =-D36/('FPT Digital Retail JSC | Income'!D23-'FPT Digital Retail JSC | Income'!C23) -> 0.026189957 | E38: =-E36/('FPT Digital Retail JSC | Income'!E23-'FPT Digital Retail JSC | Income'!D23) -> -0.060965136 | F38: =-F36/('FPT Digital Retail JSC | Income'!F23-'FPT Digital Retail JSC | Income'!E23) -> -0.085151895 | G38: =-G36/('FPT Digital Retail JSC | Income'!G23-'FPT Digital Retail JSC | Income'!F23) -> -0.040217121 | H38: =-H36/('FPT Digital Retail JSC | Income'!H23-'FPT Digital Retail JSC | Income'!G23) -> -0.0066041628 | I38: =-I36/('FPT Digital Retail JSC | Income'!I23-'FPT Digital Retail JSC | Income'!H23) -> 0.012126834 | J38: =AVERAGE(D38:I38) -> -0.025770254 | K38: =AVERAGE(E38:J38) -> -0.034430289 | L38: =AVERAGE(F38:K38) -> -0.030007815 | M38: =AVERAGE(G38:L38) -> -0.020817135 | N38: =AVERAGE(H38:M38) -> -0.017583804 | O38: =AVERAGE(I38:N38) -> -0.019413744
A39: Inventories | B39: -756654 | C39: 256198 | D39: ='FPT Digital Retail JSC | BS'!C37-'FPT Digital Retail JSC | BS'!D37 -> -782741 | E39: ='FPT Digital Retail JSC | BS'!D37-'FPT Digital Retail JSC | BS'!E37 -> -877323 | F39: ='FPT Digital Retail JSC | BS'!D37-'FPT Digital Retail JSC | BS'!F37 -> 679501 | G39: ='FPT Digital Retail JSC | BS'!E37-'FPT Digital Retail JSC | BS'!G37 -> -1546817 | H39: ='FPT Digital Retail JSC | BS'!F37-'FPT Digital Retail JSC | BS'!H37 -> -4657110 | I39: ='FPT Digital Retail JSC | BS'!G37-'FPT Digital Retail JSC | BS'!I37 -> -2889466 | J39: ='FPT Digital Retail JSC | BS'!H37-'FPT Digital Retail JSC | BS'!J37 -> -1740389.7 | K39: ='FPT Digital Retail JSC | BS'!I37-'FPT Digital Retail JSC | BS'!K37 -> -1041312.9 | L39: ='FPT Digital Retail JSC | BS'!J37-'FPT Digital Retail JSC | BS'!L37 -> -798277.72 | M39: ='FPT Digital Retail JSC | BS'!K37-'FPT Digital Retail JSC | BS'!M37 -> -330881.28 | ... O39: ='FPT Digital Retail JSC | BS'!M37-'FPT Digital Retail JSC | BS'!O37 -> 9192019.2
A40: Prepaid Expenses | B40: -9167 | C40: -9282 | D40: -17223 | E40: -68023 | F40: -68023 | G40: 8228 | H40: -40582 | I40: -226194 | J40: =AVERAGE(D40:I40) -> -68636.167 | K40: =AVERAGE(E40:I40) -> -78918.8 | L40: =AVERAGE(F40:I40) -> -81642.75 | M40: =AVERAGE(G40:I40) -> -86182.667 | N40: =AVERAGE(H40:I40) -> -133388 | O40: =AVERAGE(I40:I40) -> -226194
A41: Accounts Payable | B41: 1117290 | C41: 126774 | D41: ='FPT Digital Retail JSC | BS'!D75 -> -793137 | E41: ='FPT Digital Retail JSC | BS'!E75 -> 581630 | F41: ='FPT Digital Retail JSC | BS'!F75 -> -72732 | G41: ='FPT Digital Retail JSC | BS'!G75 -> 1120953 | H41: ='FPT Digital Retail JSC | BS'!H75 -> -28387 | I41: ='FPT Digital Retail JSC | BS'!I75 -> 896119.51 | J41: ='FPT Digital Retail JSC | BS'!I75 -> 896119.51 | K41: ='FPT Digital Retail JSC | BS'!J75 -> 26129.336 | L41: ='FPT Digital Retail JSC | BS'!K75 -> 491761.97 | M41: ='FPT Digital Retail JSC | BS'!L75 -> 362047.52 | N41: ='FPT Digital Retail JSC | BS'!M75 -> 292753 | O41: ='FPT Digital Retail JSC | BS'!N75 -> 202628.53
A42: Accounts Payable | B42: 1117290 | C42: 126774 | D42: -849890 | E42: 554572 | F42: 554572 | G42: 65447 | H42: 1353541 | I42: 36246 | J42: =I42*(1+J43) -> 42988.746 | K42: =J42*(1+K43) -> 49399.027 | L42: =K42*(1+L43) -> 56765.18 | M42: =L42*(1+M43) -> 62712.202 | N42: =M42*(1+N43) -> 70724.066 | O42: =N42*(1+O43) -> 79228.688
A43: %/ sales change | D43: =-D42/('FPT Digital Retail JSC | Income'!D23-'FPT Digital Retail JSC | Income'!C23) -> 0.37058726 | F43: =F42/('Revenue breakdown'!C3-'Revenue breakdown'!B3) -> 0.41521535 | G43: =G42/('Revenue breakdown'!D3-'Revenue breakdown'!C3) -> -0.033178998 | H43: =H42/('Revenue breakdown'!E3-'Revenue breakdown'!D3) -> 0.17278782 | I43: =I42/('Revenue breakdown'!F3-'Revenue breakdown'!E3) -> 0.004725167 | J43: =AVERAGE(D43:I43) -> 0.18602732 | K43: =AVERAGE(E43:J43) -> 0.14911533 | L43: =AVERAGE(F43:K43) -> 0.14911533 | M43: =AVERAGE(G43:L43) -> 0.10476533 | N43: =AVERAGE(H43:M43) -> 0.12775605 | O43: =AVERAGE(I43:N43) -> 0.12025075
A44: Other Operating Cash Flow | B44: -118877 | C44: -146398 | D44: -191702 | E44: -216538 | F44: -216538 | G44: -143899 | H44: -213516 | I44: -355188 | J44: =AVERAGE(D44:I44) -> -222896.83 | K44: =AVERAGE(E44:J44) -> -228095.97 | L44: =AVERAGE(F44:K44) -> -230022.3 | M44: =AVERAGE(G44:L44) -> -232269.68 | N44: =AVERAGE(H44:M44) -> -246998.13 | O44: =AVERAGE(I44:N44) -> -252578.49
A45: Cash from Operating Activities | B45: 240830 | C45: 178859 | D45: -1386736 | E45: -108197 | F45: -125651 | G45: 1518333 | H45: -1474353 | I45: -1507692
A46: Cash Flow-Investing Activities (VND Millions)
A47: Capital Expenditures | B47: -95659 | C47: -51705 | D47: =SUM(D51:D52) -> -74 | E47: =SUM(E51:E52) -> -3816 | F47: =SUM(F51:F52) -> -3816 | G47: =SUM(G51:G52) -> -3429 | H47: =SUM(H51:H52) -> -2088 | I47: =SUM(I51:I52) -> -518167 | J47: =SUM(J51:J52) - 242646 -> -359049.1 | K47: =SUM(K51:K52) -> -50511.968 | L47: =SUM(L51:L52) -> -58165.237 | M47: =SUM(M51:M52) -> -77160.293 | N47: =SUM(N51:N52) -> -68362.675 | O47: =SUM(O51:O52) -> -115444.17
A48: %/ sales change | D48: =-D47/('FPT Digital Retail JSC | Income'!C23-'FPT Digital Retail JSC | Income'!B23) -> 6.8182939e-06 | E48: =-E47/('FPT Digital Retail JSC | Income'!D23-'FPT Digital Retail JSC | Income'!C23) -> 0.0016639341 | F48: =-F47/('FPT Digital Retail JSC | Income'!D23-'FPT Digital Retail JSC | Income'!C23) -> 0.0016639341 | G48: =-G47/('FPT Digital Retail JSC | Income'!E23-'FPT Digital Retail JSC | Income'!D23) -> 0.0015935348 | H48: =-H47/('FPT Digital Retail JSC | Income'!F23-'FPT Digital Retail JSC | Income'!E23) -> 0.0015633131 | I48: =-I47/('FPT Digital Retail JSC | Income'!G23-'FPT Digital Retail JSC | Income'!F23) -> -0.26268984
A49: Capital Expenditures | D49: -74 | E49: -3816 | F49: -3816 | G49: -3429 | H49: -2088 | I49: -518167 | J49: =J50*'Revenue breakdown'!G3 -> -90942.792 | K49: =K50*'Revenue breakdown'!H3 -> -113885.94 | L49: =L50*'Revenue breakdown'!I3 -> -141579.85 | M49: =M50*'Revenue breakdown'!J3 -> -176901.71 | N49: =N50*'Revenue breakdown'!K3 -> -219038.25 | O49: =O50*'Revenue breakdown'!L3 -> -276908.71
A50: %/rev | D50: =D49/'Revenue breakdown'!B3 -> -4.8371277e-06 | E50: =E49/'Revenue breakdown'!C3 -> -0.00022941019 | F50: =F49/'Revenue breakdown'!D3 -> -0.00026027498 | G50: =G49/'Revenue breakdown'!E3 -> -0.00015243414 | H50: =H49/'Revenue breakdown'!F3 -> -6.9217456e-05 | I50: =I49/'Revenue breakdown'!G3 -> -0.013499491 | J50: =AVERAGE(D50:I50) -> -0.0023692774 | K50: =AVERAGE(E50:J50) -> -0.0027633508 | L50: =AVERAGE(F50:K50) -> -0.0031856742 | M50: =AVERAGE(G50:L50) -> -0.0036732408 | N50: =AVERAGE(H50:M50) -> -0.0042600419 | O50: =AVERAGE(I50:N50) -> -0.0049585126
A51: FPT Shop | D51: =D56*'Revenue breakdown'!B27 -> -70.056838 | E51: =E56*'Revenue breakdown'!C27 -> -3423.4312 | F51: =F56*'Revenue breakdown'!C27 -> -3423.4312 | G51: =G56*'Revenue breakdown'!D27 -> -2566.3585 | H51: =H56*'Revenue breakdown'!E27 -> -1290.2923 | I51: =I56*'Revenue breakdown'!F27 -> -228039.9 | J51: =-J53*('Revenue breakdown'!G6-'Revenue breakdown'!F6) -> -53109.743 | K51: =-K53*('Revenue breakdown'!H6-'Revenue breakdown'!G6) -> -25737.689 | L51: =-L53*('Revenue breakdown'!I6-'Revenue breakdown'!H6) -> -30380.883 | M51: =-M53*('Revenue breakdown'!J6-'Revenue breakdown'!I6) -> -41729.063 | N51: =-N53*('Revenue breakdown'!K6-'Revenue breakdown'!J6) -> -22557.942 | O51: =-O53*('Revenue breakdown'!L6-'Revenue breakdown'!K6) -> -55652.743
A52: Long Chau | D52: =D56*'Revenue breakdown'!B28 -> -3.9431616 | E52: =E56*'Revenue breakdown'!C28 -> -392.56884 | F52: =F56*'Revenue breakdown'!C28 -> -392.56884 | G52: =G56*'Revenue breakdown'!D28 -> -862.64151 | H52: =H56*'Revenue breakdown'!E28 -> -797.70774 | I52: =I56*'Revenue breakdown'!F28 -> -290127.1 | J52: =-J54*('Revenue breakdown'!G12-'Revenue breakdown'!F12) -> -63293.359 | K52: =-K54*('Revenue breakdown'!H12-'Revenue breakdown'!G12) -> -24774.279 | L52: =-L54*('Revenue breakdown'!I12-'Revenue breakdown'!H12) -> -27784.354 | M52: =-M54*('Revenue breakdown'!J12-'Revenue breakdown'!I12) -> -35431.23 | N52: =-N54*('Revenue breakdown'!K12-'Revenue breakdown'!J12) -> -45804.732 | O52: =-O54*('Revenue breakdown'!L12-'Revenue breakdown'!K12) -> -59791.428
A53: %/ sales change | D53: =-D51/('FPT Digital Retail JSC | Income'!E23-'FPT Digital Retail JSC | Income'!D23)*'Revenue breakdown'!B8 -> 3.1822807e-05 | F53: =-F51/('Revenue breakdown'!C6-'Revenue breakdown'!B6) -> 0.0041505241 | G53: =-G51/('Revenue breakdown'!D6-'Revenue breakdown'!C6) -> -0.00096937032 | H53: =-H51/('Revenue breakdown'!E6-'Revenue breakdown'!D6) -> 0.0002538768 | I53: =-I51/('Revenue breakdown'!F6-'Revenue breakdown'!E6) -> 0.1070235 | J53: =AVERAGE(D53:I53) -> 0.022098071 | K53: =AVERAGE(E53:J53) -> 0.026511321 | L53: =AVERAGE(F53:K53) -> 0.026511321 | M53: =AVERAGE(G53:L53) -> 0.03023812 | N53: =AVERAGE(H53:M53) -> 0.035439369 | O53: =N53*(1+'Revenue breakdown'!L7) -> 0.037377513
A54: %/ sales change | D54: =-D51/('FPT Digital Retail JSC | Income'!E23-'FPT Digital Retail JSC | Income'!D23)*'Revenue breakdown'!B15 -> 7.3420869e-07 | F54: =-F52/('Revenue breakdown'!C12-'Revenue breakdown'!B12) -> 0.002367968 | G54: =-G52/('Revenue breakdown'!D12-'Revenue breakdown'!C12) -> 0.0012684841 | H54: =-H52/('Revenue breakdown'!E12-'Revenue breakdown'!D12) -> 0.0002862915 | I54: =-I52/('Revenue breakdown'!F12-'Revenue breakdown'!E12) -> 0.051635487 | J54: =AVERAGE(D54:I54) -> 0.011111793 | K54: =AVERAGE(E54:J54) -> 0.013334005 | L54: =AVERAGE(F54:K54) -> 0.013334005 | M54: =AVERAGE(G54:L54) -> 0.015161678 | N54: =AVERAGE(H54:M54) -> 0.01747721 | O54: =AVERAGE(I54:N54) -> 0.020342363
A56: Purchase of Fixed Assets | B56: -95659 | C56: -51705 | D56: -74 | E56: -3816 | F56: -3816 | G56: -3429 | H56: -2088 | I56: -518167
A57: Other Investing Cash Flow Items, Total | B57: -231512 | C57: 314986 | D57: -104537 | E57: -643173 | F57: -643173 | G57: -392833 | H57: -1684043 | I57: 2378251
A58: Sale of Fixed Assets | B58: -- | C58: -- | D58: -- | E58: -- | F58: -- | G58: -- | H58: -- | I58: 239
A59: Sale/Maturity of Investment | B59: 115000 | C59: 1045300 | D59: -- | E59: 628647 | F59: 628647 | G59: 1098826 | H59: 11185095 | I59: 9161500
A60: Purchase of Investments | B60: -397500 | C60: -765000 | D60: -124499 | E60: -1321150 | F60: -1321150 | G60: -1549982 | H60: -13013064 | I60: -6942462
A61: Other Investing Cash Flow | B61: 50988 | C61: 34686 | D61: 19962 | E61: 49330 | F61: 49330 | G61: 58324 | H61: 143927 | I61: 158974
A62: Cash from Investing Activities | B62: -327171 | C62: 263281 | D62: -104612 | E62: -646989 | F62: -646989 | G62: -396262 | H62: -1686131 | I62: 1860084
E63: =-E47/'FPT Digital Retail JSC | Income'!E23 -> 0.00024943891 | F63: =-F47/'FPT Digital Retail JSC | Income'!F23 -> 0.00022941019 | G63: =-G47/'FPT Digital Retail JSC | Income'!G23 -> 0.00023387917 | H63: =-H47/'FPT Digital Retail JSC | Income'!H23 -> 9.2820788e-05 | I63: =-I47/'FPT Digital Retail JSC | Income'!I23 -> 0.0171773
A64: Cash Flow-Financing Activities (VND Millions)
A65: Financing Cash Flow Items | B65: -- | C65: -- | D65: -- | E65: -- | F65: -- | G65: -- | H65: -- | I65: --
A66: Total Cash Dividends Paid | B66: -- | C66: -- | D66: -- | E66: -68680 | F66: -68680 | G66: -78982 | H66: -- | I66: -39491
A67: Cash Dividends Paid - Common | B67: -- | C67: -- | D67: -- | E67: -68680 | F67: -68680 | G67: -78982 | H67: -- | I67: -39491
A68: Issuance (Retirement) of Stock, Net | B68: 2030 | C68: 50 | D68: 25000 | E68: -7200 | F68: -7200 | G68: 18232 | H68: 10244 | I68: 11478
A69: Sale/Issuance of Common | B69: 2030 | C69: 180 | D69: 25000 | E69: 6800 | F69: 6800 | G69: 18232 | H69: 10244 | I69: 11478
A70: Repurchase/Retirement of Common | B70: 0 | C70: -130 | D70: -- | E70: -14000 | F70: -14000 | G70: 0 | H70: -- | I70: --
A71: Common Stock, Net | B71: 2030 | C71: 50 | D71: 25000 | E71: -7200 | F71: -7200 | G71: 18232 | H71: 10244 | I71: 11478 | J71: =AVERAGE(D72:I72) -> 823185.17 | K71: =AVERAGE(E72:J72) -> 803476.18 | L71: =AVERAGE(F72:K72) -> 891367.04 | M71: =AVERAGE(G72:L72) -> 978468.09 | N71: =AVERAGE(H72:M72) -> 1388615.7 | O71: =AVERAGE(I72:N72) -> 1173612.5
A72: Issuance (Retirement) of Debt, Net | B72: 753126 | C72: -1261621 | D72: 1776650 | E72: 752337 | F72: 752337 | G72: -1212087 | H72: 3553949 | I72: -684075 | J72: =J74*'Revenue breakdown'!G3 -> 1658396.1 | K72: =K74*'Revenue breakdown'!H3 -> 1279682.1 | L72: =L74*'Revenue breakdown'!I3 -> 1274943.3 | M72: =M74*'Revenue breakdown'!J3 -> 1248798.9 | N72: =N74*'Revenue breakdown'!K3 -> 2263929.6 | O72: =O74*'Revenue breakdown'!L3 -> 1398241.8
A73: %growth | D73: =D72/B72-1 -> 1.3590342 | E73: =E72/C72-1 -> -1.5963257 | F73: =F72/D72-1 -> -0.57654181 | G73: =G72/E72-1 -> -2.6110958 | H73: =H72/F72-1 -> 3.7238791 | I73: =I72/G72-1 -> -0.4356222 | J73: =J75*('FPT Digital Retail JSC | Income'!J23-'FPT Digital Retail JSC | Income'!I23) -> 3722309.3 | K73: =K75*('FPT Digital Retail JSC | Income'!K23-'FPT Digital Retail JSC | Income'!J23) -> 1105503.7 | L73: =L75*('FPT Digital Retail JSC | Income'!L23-'FPT Digital Retail JSC | Income'!K23) -> 1284334.6 | M73: =M75*('FPT Digital Retail JSC | Income'!M23-'FPT Digital Retail JSC | Income'!L23) -> 1375490.7 | N73: =N75*('FPT Digital Retail JSC | Income'!N23-'FPT Digital Retail JSC | Income'!M23) -> 1072732.8 | O73: =O75*('FPT Digital Retail JSC | Income'!O23-'FPT Digital Retail JSC | Income'!N23) -> 1366544.6
A74: %/rev | D74: =D72/'FPT Digital Retail JSC | Income'!E23 -> 0.11613355 | E74: =E72/'FPT Digital Retail JSC | Income'!F23 -> 0.045228977 | F74: =F72/'FPT Digital Retail JSC | Income'!F23 -> 0.045228977 | G74: =G72/'FPT Digital Retail JSC | Income'!G23 -> -0.082671886 | H74: =H72/'FPT Digital Retail JSC | Income'!H23 -> 0.15798867 | I74: =I72/'FPT Digital Retail JSC | Income'!I23 -> -0.02267717 | J74: =AVERAGE(D74:I74) -> 0.043205187 | K74: =AVERAGE(E74:J74) -> 0.031050459 | L74: =AVERAGE(F74:K74) -> 0.028687373 | M74: =AVERAGE(G74:L74) -> 0.025930439 | N74: =AVERAGE(H74:M74) -> 0.044030827 | O74: =AVERAGE(I74:N74) -> 0.025037853
A75: %/sales growth | D75: =D72/('FPT Digital Retail JSC | Income'!E23-'FPT Digital Retail JSC | Income'!D23) -> 0.82564991 | E75: =E72/('FPT Digital Retail JSC | Income'!E23-'FPT Digital Retail JSC | Income'!D23) -> 0.34962822 | F75: =F72/('FPT Digital Retail JSC | Income'!F23-'FPT Digital Retail JSC | Income'!E23) -> 0.5632846 | G75: =G72/('FPT Digital Retail JSC | Income'!G23-'FPT Digital Retail JSC | Income'!F23) -> 0.61447938 | H75: =H72/('FPT Digital Retail JSC | Income'!H23-'FPT Digital Retail JSC | Income'!G23) -> 0.45368342 | I75: =I72/('FPT Digital Retail JSC | Income'!I23-'FPT Digital Retail JSC | Income'!H23) -> -0.08917863 | J75: =AVERAGE(D75:I75) -> 0.45292448 | K75: =AVERAGE(E75:J75) -> 0.39080358 | L75: =AVERAGE(F75:K75) -> 0.39766614 | M75: =AVERAGE(G75:L75) -> 0.37006306 | N75: =AVERAGE(H75:M75) -> 0.32932701 | O75: =AVERAGE(I75:N75) -> 0.30860094
A76: Short Term Debt Issued | B76: 7159276 | C76: 6598116 | D76: 8665290 | E76: 11735834 | F76: 11735834 | G76: 10586373 | H76: 14976649 | I76: 13421853
A77: Short Term Debt Reduction | B77: -6406150 | C77: -7859737 | D77: -6888640 | E77: -10983497 | F77: -10983497 | G77: -11798461 | H77: -11422699 | I77: -14105928
A78: Short Term Debt, Net | B78: 753126 | C78: -1261621 | D78: 1776650 | E78: 752337 | F78: 752337 | G78: -1212087 | H78: 3553949 | I78: -684075
A79: Cash from Financing Activities | B79: 755156 | C79: -1261571 | D79: 1801650 | E79: 676457 | F79: 676457 | G79: -1272837 | H79: 3564193 | I79: -712088 | J79: =J80*'Revenue breakdown'!G3 -> 1583937.4 | K79: =K80*'Revenue breakdown'!H3 -> 1175186.9 | L79: =L80*'Revenue breakdown'!I3 -> 1177268 | M79: =M80*'Revenue breakdown'!J3 -> 1118012.9 | N79: =N80*'Revenue breakdown'!K3 -> 1877459.1 | O79: =O80*'Revenue breakdown'!L3 -> 1279295.2
A80: %/rev | D80: =D79/'Revenue breakdown'!B3 -> 0.11776772 | E80: =E79/'Revenue breakdown'!C3 -> 0.040667225 | F80: =F79/'Revenue breakdown'!D3 -> 0.046138583 | G80: =G79/'Revenue breakdown'!E3 -> -0.056583205 | H80: =H79/'Revenue breakdown'!F3 -> 0.11815343 | I80: =I79/'Revenue breakdown'!G3 -> -0.018551597 | J80: =AVERAGE(D80:I80) -> 0.04126536 | K80: =AVERAGE(E80:J80) -> 0.028514967 | L80: =AVERAGE(F80:K80) -> 0.02648959 | M80: =AVERAGE(G80:L80) -> 0.023214758 | N80: =AVERAGE(H80:M80) -> 0.036514419 | O80: =AVERAGE(I80:N80) -> 0.022907916
A81: Foreign Exchange Effects | B81: -- | C81: -- | D81: -- | E81: -- | F81: 0 | G81: 75 | H81: -5 | I81: 43
A82: Net Change in Cash | B82: 668816 | C82: -819431 | D82: 310302 | E82: -78729 | F82: -96183 | G82: -150691 | H82: 403705 | I82: -359653
A84: Net Cash - Beginning Balance | B84: 788691 | C84: 1457507 | D84: 638076 | E84: 948378 | F84: 948378 | G84: 852195 | H84: 701504 | I84: 1105210
A85: Net Cash - Ending Balance | B85: 1457507 | C85: 638076 | D85: 948378 | E85: 869650 | F85: 852195 | G85: 701504 | H85: 1105210 | I85: 745556
A86: Cash Interest Paid | B86: 71906 | C86: 78610 | D86: 90618 | E86: 133877 | F86: 133877 | G86: 114532 | H86: 120490 | I86: 218990
A87: Cash Taxes Paid | B87: 46971 | C87: 67789 | D87: 92733 | E87: 82149 | F87: 82149 | G87: 23606 | H87: 90641 | I87: 135411
A88: Lease liability Issued, Supplemental | B88: -- | C88: -- | D88: -- | E88: -- | F88: -- | G88: -- | H88: -- | I88: --
A89: Lease liability Reduced, Supplemental | B89: -- | C89: -- | D89: -- | E89: -- | F89: -- | G89: -- | H89: -- | I89: --
A90: Lease liability Net, Supplemental | B90: -- | C90: -- | D90: -- | E90: -- | F90: -- | G90: -- | H90: -- | I90: --
A91: Share Based Payments, Supplemental | B91: -- | C91: -- | D91: -- | E91: -- | F91: -- | G91: -- | H91: -- | I91: --
A92: Tax Payments - Employee Options&Buy Back | B92: -- | C92: -- | D92: -- | E92: -- | F92: -- | G92: -- | H92: -- | I92: --
A93: Net Changes in Working Capital | B93: 62431 | C93: -58568 | D93: -1717411 | E93: -261774 | F93: -279228 | G93: 1540303 | H93: -1758147 | I93: -1832560 | J93: =J94*('FPT Digital Retail JSC | Income'!J23-'FPT Digital Retail JSC | Income'!I23) -> -3250432.5 | K93: =K94*('FPT Digital Retail JSC | Income'!K23-'FPT Digital Retail JSC | Income'!J23) -> -928991.19 | L93: =L94*('FPT Digital Retail JSC | Income'!L23-'FPT Digital Retail JSC | Income'!K23) -> -1171934.5 | M93: =M94*('FPT Digital Retail JSC | Income'!M23-'FPT Digital Retail JSC | Income'!L23) -> -1444010.3 | N93: =N94*('FPT Digital Retail JSC | Income'!N23-'FPT Digital Retail JSC | Income'!M23) -> -1052455.7 | O93: =O94*('FPT Digital Retail JSC | Income'!O23-'FPT Digital Retail JSC | Income'!N23) -> -1503574.9
D94: =D93/('FPT Digital Retail JSC | Income'!E23-'FPT Digital Retail JSC | Income'!D23) -> -0.7981202 | E94: =E93/('FPT Digital Retail JSC | Income'!E23-'FPT Digital Retail JSC | Income'!D23) -> -0.12165237 | F94: =F93/('FPT Digital Retail JSC | Income'!F23-'FPT Digital Retail JSC | Income'!E23) -> -0.20906168 | G94: =G93/('FPT Digital Retail JSC | Income'!G23-'FPT Digital Retail JSC | Income'!F23) -> -0.7808717 | H94: =H93/('FPT Digital Retail JSC | Income'!H23-'FPT Digital Retail JSC | Income'!G23) -> -0.22443826 | I94: =I93/('FPT Digital Retail JSC | Income'!I23-'FPT Digital Retail JSC | Income'!H23) -> -0.23889952 | J94: =AVERAGE(D94:I94) -> -0.39550729 | K94: =AVERAGE(E94:J94) -> -0.32840514 | L94: =AVERAGE(F94:K94) -> -0.36286393 | M94: =AVERAGE(G94:L94) -> -0.38849764 | N94: =AVERAGE(H94:M94) -> -0.32310196 | O94: =AVERAGE(I94:N94) -> -0.33954591
A95: Reported Cash from Operating Activities | B95: -- | C95: -- | D95: -- | E95: -- | F95: -- | G95: -- | H95: -- | I95: --
A96: Reported Cash from Investing Activities | B96: -- | C96: -- | D96: -- | E96: -- | F96: -- | G96: -- | H96: -- | I96: --
A97: Reported Cash from Financing Activities | B97: -- | C97: -- | D97: -- | E97: -- | F97: -- | G97: -- | H97: -- | I97: --
A99: Free Cash Flow | B99: 145171 | C99: 127154 | D99: -1386811 | E99: -112013 | F99: -129467 | G99: 1514904 | H99: -1476441 | I99: -2025859

Sheet FPT Digital Retail JSC | BS
A1: FPT Digital Retail JSC | Balance Sheet 11-Oct-2023 12:01
A3: Balance Sheet | E3: =E32-D32 -> 92247
A4: Industry - Annual Standardised in Millions of Vietnamese Dong
B5: 2016 | C5: 2017 | D5: 2018 | E5: 2019 | F5: 2020 | G5: 2021 | H5: 2022 | I5: 2023F | J5: 2024F | K5: 2025F | L5: 2026F | M5: 2027F | N5: 2028F
A6: Earnings Quality Score | B6: N/A | C6: N/A | D6: 2 | E6: 17 | F6: 89 | G6: 10 | H6: 12
A7: Period End Date | B7: 31-Dec-2016 | C7: 31-Dec-2017 | D7: 31-Dec-2018 | E7: 31-Dec-2019 | F7: 31-Dec-2020 | G7: 31-Dec-2021 | H7: 31-Dec-2022 | I7: 31-Dec-2018 | J7: 31-Dec-2019 | K7: 31-Dec-2019 | L7: 31-Dec-2020 | M7: 31-Dec-2021 | N7: 31-Dec-2022
A8: Update Type | B8: Updated | C8: Updated | D8: Updated | E8: Updated | F8: Updated | G8: Updated | H8: Updated | I8: Updated | J8: Updated | K8: Restated | L8: Updated | M8: Updated | N8: Updated
A9: Statement Date | B9: 31-Dec-2017 | C9: 31-Dec-2017 | D9: 31-Dec-2018 | E9: 31-Dec-2019 | F9: 31-Dec-2020 | G9: 31-Dec-2021 | H9: 31-Dec-2022 | I9: 31-Dec-2018 | J9: 31-Dec-2019 | K9: 31-Dec-2020 | L9: 31-Dec-2020 | M9: 31-Dec-2021 | N9: 31-Dec-2022
A10: Reporting Unit | B10: Thousands | C10: Thousands | D10: Thousands | E10: Thousands | F10: Thousands | G10: Thousands | H10: Thousands | I10: Thousands | J10: Thousands | K10: Thousands | L10: Thousands | M10: Thousands | N10: Thousands
A11: Update Date | B11: 06-Jun-2023 | C11: 06-Jun-2023 | D11: 06-Jun-2023 | E11: 06-Jun-2023 | F11: 06-Jun-2023 | G11: 06-Jun-2023 | H11: 08-Jun-2023 | I11: 06-Jun-2022 | J11: 06-Jun-2023 | K11: 06-Jun-2023 | L11: 06-Jun-2023 | M11: 06-Jun-2023 | N11: 08-Jun-2023
A12: Reporting Currency | B12: Vietnamese Dong | C12: Vietnamese Dong | D12: Vietnamese Dong | E12: Vietnamese Dong | F12: Vietnamese Dong | G12: Vietnamese Dong | H12: Vietnamese Dong | I12: Vietnamese Dong | J12: Vietnamese Dong | K12: Vietnamese Dong | L12: Vietnamese Dong | M12: Vietnamese Dong | N12: Vietnamese Dong
A13: Source | B13: ARS | C13: ARS | D13: ARS | E13: ARS | F13: ARS | G13: ARS | H13: ARS | I13: ARS | J13: ARS | K13: ARS | L13: ARS | M13: ARS | N13: ARS
A14: Source Date | B14: 27-Apr-2018 | C14: 27-Apr-2018 | D14: 16-Apr-2019 | E14: 31-Mar-2020 | F14: 31-Mar-2021 | G14: 14-Mar-2022 | H14: 27-Mar-2023 | I14: 16-Apr-2019 | J14: 31-Mar-2020 | K14: 31-Mar-2021 | L14: 31-Mar-2021 | M14: 14-Mar-2022 | N14: 27-Mar-2023
A15: Original Announcement Date | B15: 10-Apr-2018 03:48 | C15: 27-Apr-2018 05:00 | D15: 21-Jan-2019 11:01 | E15: 22-Jan-2020 14:59 | F15: 01-Feb-2021 06:43 | G15: 07-Feb-2022 15:18 | H15: 31-Jan-2023 20:37 | I15: 21-Jan-2019 11:01 | J15: 22-Jan-2020 14:59 | K15: 01-Feb-2021 06:43 | L15: 01-Feb-2021 06:43 | M15: 07-Feb-2022 15:18 | N15: 31-Jan-2023 20:37
A16: Complete Statement | B16: Complete | C16: Complete | D16: Complete | E16: Complete | F16: Complete | G16: Complete | H16: Complete | I16: Complete | J16: Complete | K16: Complete | L16: Complete | M16: Complete | N16: Complete
A17: Flash Update | B17: No | C17: No | D17: No | E17: No | F17: No | G17: No | H17: No | I17: No | J17: No | K17: No | L17: No | M17: No | N17: No
A18: Consolidated | B18: Yes | C18: Yes | D18: Yes | E18: Yes | F18: Yes | G18: Yes | H18: Yes | I18: Yes | J18: Yes | K18: Yes | L18: Yes | M18: Yes | N18: Yes
... A21: Accounting Standard | B21: Vietnamese Accounting Standards | C21: Vietnamese Accounting Standards | D21: Vietnamese Accounting Standards | E21: Vietnamese Accounting Standards | F21: Vietnamese Accounting Standards | G21: Vietnamese Accounting Standards | H21: Vietnamese Accounting Standards | I21: Vietnamese Accounting Standards | J21: Vietnamese Accounting Standards | K21: Vietnamese Accounting Standards | L21: Vietnamese Accounting Standards | M21: Vietnamese Accounting Standards | N21: Vietnamese Accounting Standards
A22: Assets (VND Millions)
A23: Cash and Short Term Investments | B23: 1457807 | C23: 638076 | D23: 952518 | E23: 1364293 | F23: 1489663 | G23: 2925710 | H23: 1864556
A24: Cash | B24: 409709 | C24: 567217 | D24: 855378 | E24: 415979 | F24: 551504 | G24: 679939 | H24: 450488
A25: Cash & Equivalents | B25: 1047798 | C25: 70859 | D25: 93000 | E25: 453671 | F25: 150000 | G25: 425271 | H25: 295068
A26: Short Term Investments | B26: 300 | C26: 0 | D26: 4140 | E26: 494643 | F26: 788159 | G26: 1820500 | H26: 1119000
A27: Accounts Receivable - Trade, Net | B27: 115139 | C27: 294862 | D27: 220039 | E27: 260115 | F27: 114599 | G27: 72977 | H27: 82479 | I27: =I54*'Revenue breakdown'!G3 -> 336364.41 | J27: =J54*'Revenue breakdown'!H3 -> 314829.2 | K27: =K54*'Revenue breakdown'!I3 -> 268405.96 | L27: =L54*'Revenue breakdown'!J3 -> 273737.96 | M27: =M54*'Revenue breakdown'!K3 -> 317342.36 | N27: =N54*'Revenue breakdown'!L3 -> 383069.28
A28: Accounts Receivable - Trade, Gross | B28: 119330 | C28: 305662 | D28: 237824 | E28: 294575 | F28: 172585 | G28: 80725 | H28: 89623
A29: Provision for Doubtful Accounts | B29: -4191 | C29: -10800 | D29: -17785 | E29: -34459 | F29: -57986 | G29: -7749 | H29: -7143
A30: Total Receivables (excl. note receivables) | D30: =D32-D35 -> 997840 | E30: =E32-E35 -> 888087 | F30: =F32-F35 -> 545692 | G30: =G32-G35 -> 477246 | H30: =H32-H35 -> 603715 | I30: =I31*'Revenue breakdown'!G3 -> 1512827.6 | J30: =J31*'Revenue breakdown'!H3 -> 1533930.6 | K30: =K31*'Revenue breakdown'!I3 -> 1654138 | L30: =L31*'Revenue breakdown'!J3 -> 1792479.9 | M30: =M31*'Revenue breakdown'!K3 -> 1913717.1 | N30: =N31*'Revenue breakdown'!L3 -> 2078532.6
A31: %rev | D31: =D30/'Revenue breakdown'!B3 -> 0.065225399 | E31: =E30/'Revenue breakdown'!C3 -> 0.053389993 | F31: =F30/'Revenue breakdown'!D3 -> 0.037219595 | G31: =G30/'Revenue breakdown'!E3 -> 0.021215685 | H31: =H30/'Revenue breakdown'!F3 -> 0.020013226 | I31: =AVERAGE(D31:H31) -> 0.039412779 | J31: =MEDIAN(E31:I31) -> 0.037219595 | K31: =MEDIAN(F31:J31) -> 0.037219595 | L31: =MEDIAN(G31:K31) -> 0.037219595 | M31: =MEDIAN(H31:L31) -> 0.037219595 | N31: =MEDIAN(I31:M31) -> 0.037219595
A32: Total Receivables, Net | B32: 852723 | C32: 1026478 | D32: 1118199 | E32: 1210446 | F32: 1430692 | G32: 2037246 | H32: 643715 | I32: =I33*'Revenue breakdown'!G3 -> 2667554.2 | J32: =J33*'Revenue breakdown'!H3 -> 2899346.9 | K32: =K33*'Revenue breakdown'!I3 -> 3105052.5 | L32: =L33*'Revenue breakdown'!J3 -> 3097785.2 | M32: =M33*'Revenue breakdown'!K3 -> 3037460.4 | N32: =N33*'Revenue breakdown'!L3 -> 3720529.4
A33: %rev | D33: =D30/'Revenue breakdown'!B3 -> 0.065225399 | E33: =E32/'Revenue breakdown'!C3 -> 0.072769563 | F33: =F32/'Revenue breakdown'!D3 -> 0.09758211 | G33: =G32/'Revenue breakdown'!E3 -> 0.090564549 | H33: =H32/'Revenue breakdown'!F3 -> 0.021339231 | I33: =AVERAGE(D33:H33) -> 0.06949617 | J33: =AVERAGE(E33:I33) -> 0.070350325 | K33: =AVERAGE(F33:J33) -> 0.069866477 | L33: =AVERAGE(G33:K33) -> 0.06432335 | M33: =AVERAGE(H33:L33) -> 0.059075111 | N33: =AVERAGE(I33:M33) -> 0.066622287
A34: %growth | D34: =D32/C32-1 -> 0.089355057 | E34: =E32/D32-1 -> 0.082496049 | F34: =F32/E32-1 -> 0.18195442 | G34: =G32/F32-1 -> 0.42395848 | H34: =H32/G32-1 -> -0.68402687
A35: Notes Receivable - Short Term | B35: 280150 | C35: 0 | D35: 120359 | E35: 322359 | F35: 885000 | G35: 1560000 | H35: 40000
A36: Receivables - Other | B36: 457434 | C36: 731616 | D36: 777800 | E36: 627971 | F36: 431093 | G36: 404269 | H36: 521235
A37: Total Inventory | B37: 1948265 | C37: 1723478 | D37: 2506219 | E37: 3383542 | F37: 1826718 | G37: 4930359 | H37: 6483828 | I37: =SUM(I40,I43) -> 7819825 | J37: =SUM(J40,J43) -> 8224217.7 | K37: =SUM(K40,K43) -> 8861137.9 | L37: =SUM(L40,L43) -> 9022495.4 | M37: =SUM(M40,M43) -> 9192019.2 | N37: =SUM(N40,N43) -> 9649471.5
A38: growth | E38: =E37/D37-1 -> 0.35005839 | F38: =F37/E37-1 -> -0.46011665 | G38: =G37/F37-1 -> 1.6990258 | H38: =H37/G37-1 -> 0.31508233
A39: weighted | D39: =D37/'Revenue breakdown'!B3 -> 0.16382299 | E39: =E37/'Revenue breakdown'!C3 -> 0.2034117 | F39: =F37/'Revenue breakdown'!D3 -> 0.12459355 | G39: =G37/'Revenue breakdown'!E3 -> 0.21917615 | H39: =H37/'Revenue breakdown'!F3 -> 0.21493969 | I39: =I37/'Revenue breakdown'!G3 -> 0.20372516 | J39: =J37/'Revenue breakdown'!H3 -> 0.19955404 | K39: =K37/'Revenue breakdown'!I3 -> 0.19938358 | ... N39: =N37/'Revenue breakdown'!L3 -> 0.17278989
A40: FPT shop inv | D40: =D37*'Revenue breakdown'!B8 -> 2449700.1 | E40: =E37*'Revenue breakdown'!C8 -> 3279642.6 | F40: =F37*'Revenue breakdown'!D8 -> 1678988.7 | G40: =G37*'Revenue breakdown'!E8 -> 4067489.2 | H40: =H37*'Revenue breakdown'!F8 -> 4446850.5 | I40: =I41*'Revenue breakdown'!G9 -> 5144009.4 | J40: =J41*'Revenue breakdown'!H9 -> 5309698 | K40: =K41*'Revenue breakdown'!I9 -> 5676726 | L40: =L41*'Revenue breakdown'!J9 -> 5801236.4 | M40: =M41*'Revenue breakdown'!K9 -> 6048683.4 | N40: =N41*'Revenue breakdown'!L9 -> 6369454.7
A41: FPT shop inv per store | D41: =D40/'Revenue breakdown'!B9 -> 4596.0602 | E41: =E40/'Revenue breakdown'!C9 -> 5530.5945 | F41: =F40/'Revenue breakdown'!D9 -> 2821.8297 | G41: =G40/'Revenue breakdown'!E9 -> 6286.6912 | H41: =H40/'Revenue breakdown'!F9 -> 5657.5707 | I41: =H41*(1+I42) -> 5949.6767 | J41: =I41*(1+J42) -> 5805.5731 | K41: =J41*(1+K42) -> 5885.1402 | L41: =K41*(1+L42) -> 5854.1987 | M41: =L41*(1+M42) -> 5878.9261 | N41: =M41*(1+N42) -> 5875.8876
A42: growth | E42: =(E41-D41)/D41 -> 0.2033338 | F42: =(F41-E41)/E41 -> -0.48977824 | G42: =(G41-F41)/F41 -> 1.2278776 | H42: =(H41-G41)/G41 -> -0.10007181 | I42: =MEDIAN(E42:H42) -> 0.051630995 | J42: =MEDIAN(F42:I42) -> -0.024220406 | K42: =MEDIAN(G42:J42) -> 0.013705294 | L42: =MEDIAN(H42:K42) -> -0.005257556 | M42: =MEDIAN(I42:L42) -> 0.0042238692 | N42: =MEDIAN(J42:M42) -> -0.0005168434
A43: Long Chau shop inv | D43: =D37*'Revenue breakdown'!B15 -> 56518.932 | E43: =E37*'Revenue breakdown'!C15 -> 103899.24 | F43: =F37*'Revenue breakdown'!D15 -> 148370.98 | G43: =G37*'Revenue breakdown'!E15 -> 871704.76 | H43: =H37*'Revenue breakdown'!F15 -> 2062548.8 | I43: =I44*'Revenue breakdown'!G16 -> 2675815.7 | J43: =J44*'Revenue breakdown'!H16 -> 2914519.7 | K43: =K44*'Revenue breakdown'!I16 -> 3184411.9 | L43: =L44*'Revenue breakdown'!J16 -> 3221259 | M43: =M44*'Revenue breakdown'!K16 -> 3143335.8 | N43: =N44*'Revenue breakdown'!L16 -> 3280016.8
A44: Long Chau inv per store | D44: =D43/'Revenue breakdown'!B16 -> 1883.9644 | E44: =E43/'Revenue breakdown'!C16 -> 1527.9299 | F44: =F43/'Revenue breakdown'!D16 -> 741.85492 | G44: =G43/'Revenue breakdown'!E16 -> 2179.2619 | H44: =H43/'Revenue breakdown'!F16 -> 2062.5488 | I44: =AVERAGE(D44:H44) -> 1679.112 | J44: =I44*(1+J45) -> 1532.3365 | K44: =J44*(1+K45) -> 1424.3307 | L44: =K44*(1+L45) -> 1311.8819 | M44: =L44*(1+M45) -> 1202.7589 | N44: =M44*(1+N45) -> 1105.2579
A45: growth | E45: =(E44-D44)/D44 -> -0.18898152 | F45: =(F44-E44)/E44 -> -0.51447059 | G45: =(G44-F44)/F44 -> 1.937585 | H45: =(H44-G44)/G44 -> -0.053556244 | I45: =MEDIAN(E45:H45) -> -0.12126888 | J45: =MEDIAN(F45:I45) -> -0.087412563 | K45: =MEDIAN(G45:J45) -> -0.070484404 | L45: =MEDIAN(H45:K45) -> -0.078948484 | M45: =MEDIAN(I45:L45) -> -0.083180523 | N45: =MEDIAN(J45:M45) -> -0.081064504
A46: Inventories - Finished Goods | B46: 1909828 | C46: 1679782 | D46: 2507175 | E46: 3380942 | F46: 1847193 | G46: 4933953 | H46: 6487575
A47: Inventories - Other | B47: 38437 | C47: 43696 | D47: -956 | E47: 2600 | F47: -20476 | G47: -3594 | H47: -3747
A48: Prepaid Expenses | B48: 149918 | C48: 121298 | D48: 238333 | E48: 214958 | F48: 212927 | G48: 328617 | H48: 334699 | I48: =AVERAGE(C48:H48) -> 241805.33 | J48: =AVERAGE(D48:I48) -> 261889.89 | K48: =AVERAGE(E48:J48) -> 265816.04 | L48: =AVERAGE(F48:K48) -> 274292.38 | M48: =AVERAGE(G48:L48) -> 284519.94 | N48: =AVERAGE(H48:M48) -> 277170.43
A49: Other Current Assets, Total | B49: -- | C49: -- | D49: -- | E49: -- | F49: -- | G49: -- | H49: --
D50: =(D37-C37)/C37 -> 0.45416362 | E50: =(E37-D37)/D37 -> 0.35005839 | F50: =(F37-E37)/E37 -> -0.46011665 | G50: =(G37-F37)/F37 -> 1.6990258 | H50: =(H37-G37)/G37 -> 0.31508233 | M50: =H50/G50-1 -> -0.81455118
A51: Total Current Assets (excluding cash) | C51: =SUM(C27,C32,C37,C48) -> 3166116 | D51: =D30+D37 -> 3504059 | E51: =E30+E37 -> 4271629 | F51: =F30+F37 -> 2372410 | G51: =G30+G37 -> 5407605 | H51: =H30+H37 -> 7087543 | I51: =I30+I37 -> 9332652.6 | J51: =J30+J37 -> 9758148.3 | K51: =K30+K37 -> 10515276 | ... N51: =N30+N37 -> 11728004
A52: Total Current Assets | B52: 4408713 | C52: 3509330 | D52: 4815269 | E52: 6173239 | F52: 4959999 | G52: 10221932 | H52: 9326797
A53: AR Growth | D53: =(D27-C27)/C27 -> -0.25375599 | E53: =(E27-D27)/D27 -> 0.18213135 | F53: =(F27-E27)/E27 -> -0.55942948 | G53: =(G27-F27)/F27 -> -0.36319689 | H53: =(H27-G27)/G27 -> 0.13020541 | I53: =(I27-H27)/H27 -> 3.0781825 | J53: =(J27-I27)/I27 -> -0.064023455 | K53: =(K27-J27)/J27 -> -0.14745531 | ... N53: =(N27-M27)/M27 -> 0.20711677
A54: %/ Rev | B54: =B27/'FPT Digital Retail JSC | Income'!C23 -> 0.010608805 | C54: =C27/'FPT Digital Retail JSC | Income'!D23 -> 0.02242891 | D54: =D27/'Revenue breakdown'!B3 -> 0.014383199 | E54: =E27/'Revenue breakdown'!C3 -> 0.015637587 | F54: =F27/'Revenue breakdown'!D3 -> 0.0078163659 | G54: =G27/'Revenue breakdown'!E3 -> 0.0032441488 | H54: =H27/'Revenue breakdown'!F3 -> 0.002734189 | I54: =AVERAGE(D54:H54) -> 0.008763098 | J54: =AVERAGE(E54:I54) -> 0.0076390778 | K54: =AVERAGE(F54:J54) -> 0.0060393759 | L54: =AVERAGE(G54:K54) -> 0.0056839779 | M54: =AVERAGE(H54:L54) -> 0.0061719437 | N54: =AVERAGE(I54:M54) -> 0.0068594946
A55: Property/Plant/Equipment, Total - Gross | B55: 3898 | C55: 9323 | D55: 9344 | E55: 11191 | F55: 14160 | G55: 29396 | H55: 980978
A56: Buildings - Gross | B56: -- | C56: 4620 | D56: 4620 | E56: 4620 | F56: 4620 | G56: 17239 | H56: 943718
A57: Machinery/Equipment - Gross | B57: -- | C57: 4340 | D57: 4362 | E57: 5988 | F57: 7528 | G57: 10053 | H57: 21092
A58: Construction in Progress - Gross | B58: -- | C58: -- | D58: -- | E58: -- | F58: -- | G58: 91 | H58: 1796
A59: Other Property/Plant/Equipment - Gross | B59: 3898 | C59: 363 | D59: 363 | E59: 583 | F59: 2013 | G59: 2013 | H59: 14372
A60: Property/Plant/Equipment, Total - Net | B60: 561 | C60: 5488 | D60: 5154 | E60: 6615 | F60: 8708 | G60: 16438 | H60: 676924
A61: Accumulated Depreciation, Total | B61: -3337 | C61: -3835 | D61: -4190 | E61: -4576 | F61: -5452 | G61: -12958 | H61: -304054
A62: Goodwill, Net | B62: -- | C62: -- | D62: -- | E62: -- | F62: -- | G62: -- | H62: --
A63: Intangibles, Net | B63: 1135 | C63: 40843 | D63: 40438 | E63: 41956 | F63: 41920 | G63: 155606 | H63: 172142
A64: Intangibles - Gross | B64: 4188 | C64: 44482 | D64: 44482 | E64: 46416 | F64: 46876 | G64: 162788 | H64: 183894
A65: Accumulated Intangible Amortization | B65: -3052 | C65: -3639 | D65: -4044 | E65: -4459 | F65: -4956 | G65: -7181 | H65: -11752
A66: Long Term Investments | B66: -- | C66: -- | D66: -- | E66: -- | F66: -- | G66: -- | H66: --
A67: Note Receivable - Long Term | B67: 66086 | C67: 75677 | D67: 84028 | E67: 105270 | F67: 116400 | G67: 136777 | H67: 170162
A68: Other Long Term Assets, Total | B68: 233904 | C68: 239891 | D68: 222781 | E68: 266693 | F68: 260550 | G68: 255316 | H68: 177772
A69: Deferred Charges | B69: 233904 | C69: 239891 | D69: 222781 | E69: 266693 | F69: 257566 | G69: 254448 | H69: 177767
A70: Defered Income Tax - Long Term Asset | B70: -- | C70: -- | D70: -- | E70: -- | F70: 2985 | G70: 868 | H70: 6
A71: Total Assets | B71: 4710400 | C71: 3871228 | D71: 5167669 | E71: 6593773 | F71: 5387578 | G71: 10786069 | H71: 10523797
E72: =E74-D74 -> 581630
A73: Liabilities (VND Millions)
A74: Accounts Payable | B74: 1427548 | C74: 1499029 | D74: 705892 | E74: 1287522 | F74: 1214790 | G74: 2335743 | H74: 2307356 | I74: =I89*'Revenue breakdown'!G3 -> 3203475.5 | J74: =J89*'Revenue breakdown'!H3 -> 3229604.8 | K74: =K89*'Revenue breakdown'!I3 -> 3721366.8 | L74: =L89*'Revenue breakdown'!J3 -> 4083414.3 | M74: =M89*'Revenue breakdown'!K3 -> 4376167.3 | N74: =N89*'Revenue breakdown'!L3 -> 4578795.9
A75: Changes in AP | D75: =D74-C74 -> -793137 | E75: =E74-D74 -> 581630 | F75: =F74-E74 -> -72732 | G75: =G74-F74 -> 1120953 | H75: =H74-G74 -> -28387 | I75: =I74-H74 -> 896119.51 | J75: =J74-I74 -> 26129.336 | K75: =K74-J74 -> 491761.97 | ... N75: =N74-M74 -> 202628.53
A76: Payable/Accrued | B76: -- | C76: -- | D76: -- | E76: -- | F76: -- | G76: -- | H76: --
A77: Accrued Expenses | B77: 198796 | C77: 247307 | D77: 170569 | E77: 183299 | F77: 238744 | G77: 512496 | H77: 653063 | I77: =I78*'Revenue breakdown'!G3 -> 636292.62 | J77: =J78*'Revenue breakdown'!H3 -> 727921.55 | K77: =K78*'Revenue breakdown'!I3 -> 844010.91 | L77: =L78*'Revenue breakdown'!J3 -> 940674.04 | M77: =M78*'Revenue breakdown'!K3 -> 970874.32 | N77: =N78*'Revenue breakdown'!L3 -> 1023587.5
D78: =D77/'Revenue breakdown'!B3 -> 0.011149514 | E78: =E77/'Revenue breakdown'!C3 -> 0.011019565 | F78: =F77/'Revenue breakdown'!D3 -> 0.016283829 | G78: =G77/'Revenue breakdown'!E3 -> 0.022782702 | H78: =H77/'Revenue breakdown'!F3 -> 0.021649118 | I78: =AVERAGE(D78:H78) -> 0.016576946 | J78: =AVERAGE(E78:I78) -> 0.017662432 | K78: =AVERAGE(F78:J78) -> 0.018991005 | L78: =AVERAGE(G78:K78) -> 0.019532441 | M78: =AVERAGE(H78:L78) -> 0.018882388 | N78: =AVERAGE(I78:M78) -> 0.018329042
A79: Notes Payable/Short Term Debt | B79: 0 | C79: 0 | D79: 2947272 | E79: 3698036 | F79: 2485948 | G79: 6047406 | H79: 5363331
A80: Current Port. of LT Debt/Capital Leases | B80: 2434624 | C80: 1173003 | D80: -- | E80: -- | F80: -- | G80: -- | H80: --
A81: Other Current liabilities, Total | B81: 134201 | C81: 155435 | D81: 185169 | E81: 139274 | F81: 222966 | G81: 211062 | H81: 150624 | I81: =I82*'Revenue breakdown'!G3 -> 384304.39 | J81: =J82*'Revenue breakdown'!H3 -> 395384.44 | K81: =K82*'Revenue breakdown'!I3 -> 437220.23 | L81: =L82*'Revenue breakdown'!J3 -> 422064.95 | M81: =M82*'Revenue breakdown'!K3 -> 444249.13 | N81: =N82*'Revenue breakdown'!L3 -> 523241.97
D82: =D81/'Revenue breakdown'!B3 -> 0.012103866 | E82: =E81/'Revenue breakdown'!C3 -> 0.0083728709 | F82: =F81/'Revenue breakdown'!D3 -> 0.015207671 | G82: =G81/'Revenue breakdown'!E3 -> 0.0093826346 | H82: =H81/'Revenue breakdown'!F3 -> 0.0049932041 | I82: =AVERAGE(D82:H82) -> 0.010012049 | J82: =AVERAGE(E82:I82) -> 0.0095936859 | K82: =AVERAGE(F82:J82) -> 0.0098378489 | L82: =AVERAGE(G82:K82) -> 0.0087638845 | M82: =AVERAGE(H82:L82) -> 0.0086401345 | N82: =AVERAGE(I82:M82) -> 0.0093695206
A83: Customer Advances | B83: 34948 | C83: 13232 | D83: 13918 | E83: 19464 | F83: 28401 | G83: 54212 | H83: 35297
A84: Income Taxes Payable | B84: 21509 | C84: 26435 | D84: 24450 | E84: 9108 | F84: 31620 | G84: 71324 | H84: 3120
A85: Other Current Liabilities | B85: 77745 | C85: 115767 | D85: 146802 | E85: 110702 | F85: 162945 | G85: 85527 | H85: 112206
A86: Total Current Liabilities | B86: 4195169 | C86: 3074774 | D86: 4008902 | E86: 5308130 | F86: 4162448 | G86: 9106708 | H86: 8474375
A87: Total Current Liabities (without debt) | C87: =C74+C77+C81 -> 1901771 | D87: =D74+D77+D81 -> 1061630 | E87: =E74+E77+E81 -> 1610095 | F87: =F74+F77+F81 -> 1676500 | G87: =G74+G77+G81 -> 3059301 | H87: =H74+H77+H81 -> 3111043 | I87: =I74+I77+I81 -> 4224072.5 | J87: =J74+J77+J81 -> 4352910.8 | ... N87: =N74+N77+N81 -> 6125625.3
A88: A/P Growth | C88: =(C74-B74)/B74 -> 0.050072572 | D88: =(D74-C74)/C74 -> -0.5291005 | E88: =(E74-D74)/D74 -> 0.82396457 | F88: =(F74-E74)/E74 -> -0.056489909 | G88: =(G74-F74)/F74 -> 0.92275455 | H88: =(H74-G74)/G74 -> -0.012153306 | I88: =(I74-H74)/H74 -> 0.38837505 | J88: =(J74-I74)/I74 -> 0.0081565586 | ... N88: =(N74-M74)/M74 -> 0.046302738
A89: %/ Rev | C89: =C74/'FPT Digital Retail JSC | Income'!D23 -> 0.11402482 | D89: =D74/'FPT Digital Retail JSC | Income'!E23 -> 0.046141753 | E89: =E74/'FPT Digital Retail JSC | Income'!F23 -> 0.077403216 | F89: =F74/'FPT Digital Retail JSC | Income'!G23 -> 0.082856248 | G89: =G74/'FPT Digital Retail JSC | Income'!H23 -> 0.10383405 | H89: =H74/'FPT Digital Retail JSC | Income'!I23 -> 0.076489134 | I89: =AVERAGE(C89:H89) -> 0.083458204 | J89: =AVERAGE(D89:I89) -> 0.078363768 | K89: =AVERAGE(E89:J89) -> 0.083734104 | L89: =AVERAGE(F89:K89) -> 0.084789252 | M89: =AVERAGE(G89:L89) -> 0.08511142 | N89: =AVERAGE(H89:M89) -> 0.08199098
A90: Total Long Term Debt | B90: 0 | C90: 0 | D90: 0 | E90: 0 | F90: 0 | G90: 0 | H90: 0
A91: Total Debt | B91: 2434624 | C91: 1173003 | D91: 2947272 | E91: 3698036 | F91: 2485948 | G91: 6047406 | H91: 5363331
A92: Deferred Income Tax | B92: -- | C92: -- | D92: -- | E92: 6279 | F92: -- | G92: -- | H92: --
A93: Deferred Income Tax - LT Liability | B93: -- | C93: -- | D93: -- | E93: 6279 | F93: -- | G93: -- | H93: --
A94: Minority Interest | B94: -- | C94: -- | D94: 24984 | E94: 5637 | F94: 11403 | G94: 17066 | H94: 41105
A95: Other Liabilities, Total | B95: -- | C95: -- | D95: -- | E95: -- | F95: -- | G95: 87 | H95: 87
A96: Other Long Term Liabilities | B96: -- | C96: -- | D96: -- | E96: -- | F96: -- | G96: 87 | H96: 87
A97: Total Liabilities | B97: 4195169 | C97: 3074774 | D97: 4033886 | E97: 5320047 | F97: 4173851 | G97: 9123860 | H97: 8515566
A98: Working Cap | C98: =C87+C51 -> 5067887 | D98: =D51-D87 -> 2442429 | E98: =E51-E87 -> 2661534 | F98: =F51-F87 -> 695910 | G98: =G51-G87 -> 2348304 | H98: =H51-H87 -> 3976500 | I98: =I51-I87 -> 5108580.1 | J98: =J51-J87 -> 5405237.5 | K98: =K51-K87 -> 5512678 | ... N98: =N51-N87 -> 5602378.8
A99: Changes in WC | D99: =D98-C98 -> -2625458 | E99: =E98-D98 -> 219105 | F99: =F98-E98 -> -1965624 | G99: =G98-F98 -> 1652394 | H99: =H98-G98 -> 1628196 | I99: =I98-H98 -> 1132080.1 | J99: =J98-I98 -> 296657.38 | K99: =K98-J98 -> 107440.52 | ... N99: =N98-M98 -> 287933.35
A100: Shareholders Equity (VND Millions)
A101: Redeemable Preferred Stock, Total | B101: -- | C101: -- | D101: -- | E101: -- | F101: -- | G101: -- | H101: --
A102: Preferred Stock - Non Redeemable, Net | B102: -- | C102: -- | D102: -- | E102: -- | F102: -- | G102: -- | H102: --
A103: Common Stock, Total | B103: 200000 | C103: 400000 | D103: 680000 | E103: 789818 | F103: 789818 | G103: 789818 | H103: 1184725
...

Sheet FPT Digital Retail JSC | Income
A1: FPT Digital Retail JSC | Income Statement 11-Oct-2023 12:01
A3: Income Statement
A4: Industry - Annual Standardised in Millions of Vietnamese Dong
C5: 2016 | D5: 2017 | E5: 2018 | F5: 2019 | G5: 2020 | H5: 2021 | I5: 2022 | J5: 2023F | K5: 2024F | L5: 2025F | M5: 2026F | N5: 2027F | O5: 2028F
A6: Earnings Quality Score | C6: N/A | D6: N/A | E6: 2 | F6: 17 | G6: 89 | H6: 10 | I6: 12
A7: Period End Date | C7: 31-Dec-2016 | D7: 31-Dec-2017 | E7: 31-Dec-2018 | F7: 31-Dec-2019 | G7: 31-Dec-2020 | H7: 31-Dec-2021 | I7: 31-Dec-2022 | J7: 31-Dec-2018 | K7: 31-Dec-2019 | L7: 31-Dec-2019 | M7: 31-Dec-2020 | N7: 31-Dec-2021 | O7: 31-Dec-2022
A8: Period Length | C8: 12 Months | D8: 12 Months | E8: 12 Months | F8: 12 Months | G8: 12 Months | H8: 12 Months | I8: 12 Months | J8: Updated | K8: Updated | L8: Restated | M8: Updated | N8: Updated | O8: Updated
A9: Update Type | C9: Updated | D9: Updated | E9: Updated | F9: Updated | G9: Updated | H9: Updated | I9: Updated | J9: 31-Dec-2018 | K9: 31-Dec-2019 | L9: 31-Dec-2020 | M9: 31-Dec-2020 | N9: 31-Dec-2021 | O9: 31-Dec-2022
A10: Statement Date | C10: 31-Dec-2017 | D10: 31-Dec-2017 | E10: 31-Dec-2018 | F10: 31-Dec-2019 | G10: 31-Dec-2020 | H10: 31-Dec-2021 | I10: 31-Dec-2022 | J10: Thousands | K10: Thousands | L10: Thousands | M10: Thousands | N10: Thousands | O10: Thousands
A11: Reporting Unit | C11: Thousands | D11: Thousands | E11: Thousands | F11: Thousands | G11: Thousands | H11: Thousands | I11: Thousands | J11: 06-Jun-2022 | K11: 06-Jun-2023 | L11: 06-Jun-2023 | M11: 06-Jun-2023 | N11: 06-Jun-2023 | O11: 08-Jun-2023
A12: Update Date | C12: 06-Jun-2023 | D12: 06-Jun-2023 | E12: 06-Jun-2023 | F12: 06-Jun-2023 | G12: 06-Jun-2023 | H12: 06-Jun-2023 | I12: 08-Jun-2023 | J12: Vietnamese Dong | K12: Vietnamese Dong | L12: Vietnamese Dong | M12: Vietnamese Dong | N12: Vietnamese Dong | O12: Vietnamese Dong
A13: Reporting Currency | C13: Vietnamese Dong | D13: Vietnamese Dong | E13: Vietnamese Dong | F13: Vietnamese Dong | G13: Vietnamese Dong | H13: Vietnamese Dong | I13: Vietnamese Dong | J13: ARS | K13: ARS | L13: ARS | M13: ARS | N13: ARS | O13: ARS
A14: Source | C14: ARS | D14: ARS | E14: ARS | F14: ARS | G14: ARS | H14: ARS | I14: ARS | J14: 16-Apr-2019 | K14: 31-Mar-2020 | L14: 31-Mar-2021 | M14: 31-Mar-2021 | N14: 14-Mar-2022 | O14: 27-Mar-2023
A15: Source Date | C15: 27-Apr-2018 | D15: 27-Apr-2018 | E15: 16-Apr-2019 | F15: 31-Mar-2020 | G15: 31-Mar-2021 | H15: 14-Mar-2022 | I15: 27-Mar-2023 | J15: 21-Jan-2019 11:01 | K15: 22-Jan-2020 14:59 | L15: 01-Feb-2021 06:43 | M15: 01-Feb-2021 06:43 | N15: 07-Feb-2022 15:18 | O15: 31-Jan-2023 20:37
A16: Original Announcement Date | C16: 10-Apr-2018 03:48 | D16: 27-Apr-2018 05:00 | E16: 21-Jan-2019 11:01 | F16: 22-Jan-2020 14:59 | G16: 01-Feb-2021 06:43 | H16: 07-Feb-2022 15:18 | I16: 31-Jan-2023 20:37 | J16: Complete | K16: Complete | L16: Complete | M16: Complete | N16: Complete | O16: Complete
A17: Complete Statement | C17: Complete | D17: Complete | E17: Complete | F17: Complete | G17: Complete | H17: Complete | I17: Complete | J17: No | K17: No | L17: No | M17: No | N17: No | O17: No
A18: Flash Update | C18: No | D18: No | E18: No | F18: No | G18: No | H18: No | I18: No | J18: Yes | K18: Yes | L18: Yes | M18: Yes | N18: Yes | O18: Yes
... A21: Auditor Opinion | C21: Unqualified with Explanation | D21: Unqualified with Explanation | E21: Unqualified with Explanation | F21: Unqualified | G21: Unqualified | H21: Unqualified | I21: Unqualified | J21: Vietnamese Accounting Standards | K21: Vietnamese Accounting Standards | L21: Vietnamese Accounting Standards | M21: Vietnamese Accounting Standards | N21: Vietnamese Accounting Standards | O21: Vietnamese Accounting Standards
A22: Accounting Standard | C22: Vietnamese Accounting Standards | D22: Vietnamese Accounting Standards | E22: Vietnamese Accounting Standards | F22: Vietnamese Accounting Standards | G22: Vietnamese Accounting Standards | H22: Vietnamese Accounting Standards | I22: Vietnamese Accounting Standards
A23: Revenue | C23: 10853155 | D23: 13146515 | E23: 15298335 | F23: 16633960 | G23: 14661417 | H23: 22494961 | I23: 30165801 | J23: ='Revenue breakdown'!G3 -> 38384189 | K23: ='Revenue breakdown'!H3 -> 41212985 | L23: ='Revenue breakdown'!I3 -> 44442666 | M23: ='Revenue breakdown'!J3 -> 48159575 | N23: ='Revenue breakdown'!K3 -> 51416923 | O23: ='Revenue breakdown'!L3 -> 55845117
A24: Gross Revenue | C24: 11722218 | D24: 13795036 | E24: 15889646 | F24: 16988957 | G24: 14799953 | H24: 22619505 | I24: 30276711
A25: Sales Returns and Allowances | C25: -869062 | D25: -648521 | E25: -591311 | F25: -354997 | G25: -138536 | H25: -124544 | I25: -110910
A26: Other Revenue, Total | C26: -- | D26: -- | E26: -- | F26: -- | G26: -- | H26: -- | I26: --
A27: Total Revenue | C27: 10853155 | D27: 13146515 | E27: 15298335 | F27: 16633960 | G27: 14661417 | H27: 22494961 | I27: 30165801 | J27: ='Revenue breakdown'!G3 -> 38384189 | K27: ='Revenue breakdown'!H3 -> 41212985 | L27: ='Revenue breakdown'!I3 -> 44442666 | M27: ='Revenue breakdown'!J3 -> 48159575 | N27: ='Revenue breakdown'!K3 -> 51416923 | O27: ='Revenue breakdown'!L3 -> 55845117
A28: Cost of Revenue, Total | C28: 9442776 | D28: 11330255 | E28: 13254725 | F28: 14522903 | G28: 12620415 | H28: 19343448 | I28: 25462623
A29: Cost of Revenue (COGS) | C29: 9442776 | D29: 11330255 | E29: 13254725 | F29: 14522903 | G29: 12620415 | H29: 19343448 | I29: 25462623 | J29: =J30*'Revenue breakdown'!G3 -> 32399675 | K29: =K30*'Revenue breakdown'!H3 -> 35294455 | L29: =L30*'Revenue breakdown'!I3 -> 37911923 | M29: =M30*'Revenue breakdown'!J3 -> 41008105 | N29: =N30*'Revenue breakdown'!K3 -> 43695406 | O29: =O30*'Revenue breakdown'!L3 -> 47522666
B30: %/rev | E30: =E29/E27 -> 0.86641618 | F30: =F29/F27 -> 0.87308753 | G30: =G29/G27 -> 0.86079095 | H30: =H29/H27 -> 0.85990138 | I30: =I29/I27 -> 0.84408907 | J30: =I30 -> 0.84408907 | K30: =AVERAGE(F30:J30) -> 0.8563916 | L30: =AVERAGE(G30:K30) -> 0.85305241 | M30: =AVERAGE(H30:L30) -> 0.85150471 | N30: =AVERAGE(I30:M30) -> 0.84982537 | O30: =AVERAGE(J30:N30) -> 0.85097263
E31: =(E29-D29)/D29 -> 0.16985231 | F31: =(F29-E29)/E29 -> 0.095677428 | G31: =(G29-F29)/F29 -> -0.13099915 | H31: =(H29-G29)/G29 -> 0.53271093 | I31: =(I29-H29)/H29 -> 0.31634355
A32: Gross Profit | C32: 1410379 | D32: 1816260 | E32: =E27-E29 -> 2043610 | F32: =F27-F29 -> 2111057 | G32: =G27-G29 -> 2041002 | H32: =H27-H29 -> 3151513 | I32: =I27-I29 -> 4703178 | J32: =J27-J29 -> 5984514.5 | K32: =K27-K29 -> 5918530.9 | L32: =L27-L29 -> 6530742.5 | ... O32: =O27-O29 -> 8322450.7
A33: COGS | E33: 13325966 | F33: 14522902 | G33: 12620414 | H33: 19343448 | I33: 25462623
B34: FPT Shop | E34: =E32*'Revenue breakdown'!B8 -> 1997523.6 | F34: =F32*'Revenue breakdown'!C8 -> 2046232.1 | G34: =G32*'Revenue breakdown'!D8 -> 1875943.2 | H34: =H32*'Revenue breakdown'!E8 -> 2599961.8 | I34: =I32*'Revenue breakdown'!F8 -> 3225614.5 | J34: =J35*'Revenue breakdown'!G6 -> 2789753.8 | K34: =K35*'Revenue breakdown'!H6 -> 2860057.5 | L34: =L35*'Revenue breakdown'!I6 -> 2975297.3 | M34: =M35*'Revenue breakdown'!J6 -> 3085391.3 | N34: =N35*'Revenue breakdown'!K6 -> 3161760.6 | O34: =O35*'Revenue breakdown'!L6 -> 3387524.7
B35: %/rev | E35: =E34/E23 -> 0.13057131 | F35: =F34/F23 -> 0.12301533 | G35: =G34/G23 -> 0.12795102 | H35: =H34/H23 -> 0.11557974 | I35: =I34/I23 -> 0.10692952 | J35: =AVERAGE(E35:I35) -> 0.12080938 | K35: =AVERAGE(F35:J35) -> 0.118857 | L35: =AVERAGE(G35:K35) -> 0.11802533 | M35: =AVERAGE(H35:L35) -> 0.11604019 | N35: =AVERAGE(I35:M35) -> 0.11613228 | O35: =AVERAGE(J35:N35) -> 0.11797284
B36: Long Chau | E36: =E32*'Revenue breakdown'!B15 -> 46086.417 | F36: =F32*'Revenue breakdown'!C15 -> 64824.734 | G36: =G32*'Revenue breakdown'!D15 -> 165775.71 | H36: =H32*'Revenue breakdown'!E15 -> 557198.55 | I36: =I32*'Revenue breakdown'!F15 -> 1496112.2 | J36: =J37*'Revenue breakdown'!G12 -> 283155.17 | K36: =K37*'Revenue breakdown'!H12 -> 370737.33 | L36: =L37*'Revenue breakdown'!I12 -> 483947.05 | M36: =M37*'Revenue breakdown'!J12 -> 602516.49 | N36: =N37*'Revenue breakdown'!K12 -> 691022.78 | O36: =O37*'Revenue breakdown'!L12 -> 660862.26
B37: %/rev | E37: =E36/E23 -> 0.003012512 | F37: =F36/F23 -> 0.0038971318 | G37: =G36/G23 -> 0.011306936 | H37: =H36/H23 -> 0.024769927 | I37: =I36/I23 -> 0.049596303 | J37: =AVERAGE(E37:I37) -> 0.018516562 | K37: =AVERAGE(F37:J37) -> 0.021617372 | L37: =AVERAGE(G37:K37) -> 0.02516142 | M37: =AVERAGE(H37:L37) -> 0.027932317 | N37: =AVERAGE(I37:M37) -> 0.028564795 | O37: =AVERAGE(J37:N37) -> 0.024358493
B38: Gross profit margin | E38: =E32/E27 -> 0.13358382 | F38: =F32/F27 -> 0.12691247 | G38: =G32/G27 -> 0.13920905 | H38: =H32/H27 -> 0.14009862 | I38: =I32/I27 -> 0.15591093 | J38: =J32/J27 -> 0.15591093 | K38: =K32/K27 -> 0.1436084 | L38: =L32/L27 -> 0.14694759 | ... O38: =O32/O27 -> 0.14902737
A39: Selling/General/Admin. Expenses, Total | C39: 1180366 | D39: 1454296 | E39: 1583114 | F39: 1768320 | G39: 1935903 | H39: 2656653 | I39: 4146636 | J39: =J42*J23 -> 4961021.4 | K39: =K42*K23 -> 5309552.6 | L39: =L42*L23 -> 5942836.8 | M39: =M42*M23 -> 6379782 | N39: =N42*N23 -> 6913568.8 | O39: =O42*O23 -> 7577439.6
B40: FPT Shop | E40: =E39*'Revenue breakdown'!B8/E23 -> 0.10114908 | F40: =F39*'Revenue breakdown'!C8/F23 -> 0.10304339 | G40: =G39*'Revenue breakdown'!D8/G23 -> 0.12136233 | H40: =H39*'Revenue breakdown'!E8/H23 -> 0.097431066 | I40: =I39*'Revenue breakdown'!F8/I23 -> 0.094276207 | J40: =AVERAGE(E40:I40) -> 0.10345241 | K40: =AVERAGE(F40:J40) -> 0.10391308 | L40: =AVERAGE(G40:K40) -> 0.10408702 | M40: =AVERAGE(H40:L40) -> 0.10063196 | N40: =AVERAGE(I40:M40) -> 0.10127214 | O40: =AVERAGE(J40:N40) -> 0.10267132
B41: Long Chau | E41: =E39*'Revenue breakdown'!B15/'FPT Digital Retail JSC | Income'!E23 -> 0.0023336888 | F41: =F39*'Revenue breakdown'!C15/'FPT Digital Retail JSC | Income'!F23 -> 0.0032644197 | G41: =G39*'Revenue breakdown'!D15/'FPT Digital Retail JSC | Income'!G23 -> 0.010724699 | H41: =H39*'Revenue breakdown'!E15/'FPT Digital Retail JSC | Income'!H23 -> 0.020880479 | I41: =I39*'Revenue breakdown'!F15/'FPT Digital Retail JSC | Income'!I23 -> 0.043727415 | J41: =AVERAGE(E41:I41)*(100%+'Revenue breakdown'!G17) -> 0.025794067 | K41: =AVERAGE(F41:J41)*(100%+'Revenue breakdown'!H17) -> 0.024918948 | L41: =AVERAGE(G41:K41)*(100%+'Revenue breakdown'!I17) -> 0.029632158 | M41: =AVERAGE(H41:L41)*(100%+'Revenue breakdown'!J17) -> 0.031839767 | N41: =AVERAGE(I41:M41)*(100%+'Revenue breakdown'!K17) -> 0.033188822 | O41: =AVERAGE(J41:N41)*(100%+'Revenue breakdown'!L17) -> 0.033015379
B42: %/rev | E42: =E39/E23 -> 0.10348276 | F42: =F39/F23 -> 0.10630782 | G42: =G39/G23 -> 0.13204065 | H42: =H39/H23 -> 0.11809992 | I42: =I39/I23 -> 0.13746149 | J42: =SUM(J40:J41) -> 0.12924648 | K42: =SUM(K40:K41) -> 0.12883203 | L42: =SUM(L40:L41) -> 0.13371918 | M42: =SUM(M40:M41) -> 0.13247173 | N42: =SUM(N40:N41) -> 0.13446096 | O42: =SUM(O40:O41) -> 0.1356867
E43: =E30+E42 -> 0.96989895 | F43: =F30+F42 -> 0.97939535 | G43: =G30+G42 -> 0.99283159 | H43: =H30+H42 -> 0.9780013 | I43: =I30+I42 -> 0.98155056 | J43: =SUM(J42,J30) -> 0.97333555 | K43: =SUM(K42,K30) -> 0.98522363 | L43: =SUM(L42,L30) -> 0.98677159 | M43: =SUM(M42,M30) -> 0.98397643 | N43: =SUM(N42,N30) -> 0.98428633 | O43: =SUM(O42,O30) -> 0.98665933
E44: =E39/E32 -> 0.77466542 | F44: =F39/F32 -> 0.83764673 | G44: =G39/G32 -> 0.94850617 | H44: =H39/H32 -> 0.84297701 | I44: =I39/I32 -> 0.88166682 | J44: =J39/J32 -> 0.82897642 | K44: =K39/K32 -> 0.8971065 | L44: =L39/L32 -> 0.90997873 | ... O44: =O39/O32 -> 0.91048178
A45: Selling/General/Administrative Expense | C45: 653541 | D45: 808222 | E45: 935387 | F45: 984520 | G45: 1049295 | H45: 1101041 | I45: 1842001
A46: Labor & Related Expense | C46: 526826 | D46: 646073 | E46: 647727 | F46: 783800 | G46: 886608 | H46: 1365500 | I46: 1957142
A47: Advertising Expense | C47: -- | D47: -- | E47: -- | F47: -- | G47: -- | H47: 190112 | I47: 347493
A48: Research & Development | C48: -- | D48: -- | E48: -- | F48: -- | G48: -- | H48: -- | I48: --
A49: Depreciation/Amortization | C49: -- | D49: -- | E49: 781 | F49: 837 | G49: 1372 | H49: 3811 | I49: 115286
E50: =E49/'Revenue breakdown'!B3 -> 5.1051307e-05 | F50: =F49/'Revenue breakdown'!C3 -> 5.0318746e-05 | G50: =G49/'Revenue breakdown'!D3 -> 9.3578949e-05 | H50: =H49/'Revenue breakdown'!E3 -> 0.00016941572 | I50: =I49/'Revenue breakdown'!F3 -> 0.003821745
A51: Interest Expense, Net - Operating | C51: 73839 | D51: 78951 | E51: 95671 | F51: 135183 | G51: 113682 | H51: 132229 | I51: 231528
A52: Interest Expense - Operating | C52: 73839 | D52: 78951 | E52: 95671 | F52: 135183 | G52: 113682 | H52: 132229 | I52: 231528
A53: Interest/Investment Income - Operating | C53: -56338 | D53: -32858 | E53: -18853 | F53: -51481 | G53: -37582 | H53: -167854 | I53: -129556
A54: Interest Income - Operating | C54: -54495 | D54: -35206 | E54: -20946 | F54: -61193 | G54: -55871 | H54: -169344 | I54: -147691
A55: Investment Income - Operating | C55: -1842 | D55: 2348 | E55: 2094 | F55: 9712 | G55: 18289 | H55: 1490 | I55: 18135
A56: Interest Expense(Income) - Net Operating | C56: -- | D56: -- | E56: -- | F56: -- | G56: -- | H56: -- | I56: --
A57: Interest Exp.(Inc.),Net-Operating, Total | C57: 17501 | D57: 46093 | E57: 76818 | F57: 83702 | G57: 76101 | H57: -35625 | I57: 101972
A58: Unusual Expense (Income) | C58: -- | D58: -- | E58: -- | F58: -- | G58: -- | H58: -- | I58: --
A59: Other Operating Expenses, Total | C59: -17056 | D59: -18367 | E59: -19111 | F59: -13787 | G59: 14680 | H59: -15711 | I59: -19399
A60: Other Operating Expenses, Total | C60: -17056 | D60: -18367 | E60: -19111 | F60: -13787 | G60: 14680 | H60: -15711 | I60: -19399
A61: Total Operating Expense | C61: 10623588 | D61: 12812276 | E61: 14895546 | F61: 16361137 | G61: 14647098 | H61: 21948766 | I61: 29691833
B62: Changes in Operational Cost | E62: =(E61-D61)/D61 -> 0.16259953 | F62: =(F61-E61)/E61 -> 0.098391224 | G62: =(G61-F61)/F61 -> -0.10476283 | H62: =(H61-G61)/G61 -> 0.49850612 | I62: =(I61-H61)/H61 -> 0.35277915
A63: Operating Income (EBIT) | C63: 229567 | D63: 334239 | E63: 402788 | F63: 272823 | G63: 14319 | H63: 546196 | I63: 473968 | J63: =J66*'Revenue breakdown'!G3 -> 642551.35 | K63: =K66*'Revenue breakdown'!H3 -> 610868.14 | L63: =L66*'Revenue breakdown'!I3 -> 644701.16 | M63: =M66*'Revenue breakdown'!J3 -> 828937 | N63: =N66*'Revenue breakdown'!K3 -> 812315.18 | O63: =O66*'Revenue breakdown'!L3 -> 883240.52
J64: =J23-J29-J39 -> 1023493.1
B65: %growth | E65: =(E63-D63)/D63 -> 0.20508977 | F65: =(F63-E63)/E63 -> -0.32266354 | G65: =(G63-F63)/F63 -> -0.94751542 | H65: =(H63-G63)/G63 -> 37.144843 | I65: =(I63-H63)/H63 -> -0.13223824 | J65: =(J63-I63)/I63 -> 0.35568509 | K65: =(K63-J63)/J63 -> -0.049308443 | L65: =(L63-K63)/K63 -> 0.055385146 | ... O65: =(O63-N63)/N63 -> 0.087312584
B66: %/rev | E66: =E63/'Revenue breakdown'!B3 -> 0.026328878 | F66: =F63/'Revenue breakdown'!C3 -> 0.016401566 | G66: =G63/'Revenue breakdown'!D3 -> 0.00097664503 | H66: =H63/'Revenue breakdown'!E3 -> 0.024280816 | I66: =I63/'Revenue breakdown'!F3 -> 0.015712097 | J66: =AVERAGE(E66:I66) -> 0.016740001 | K66: =AVERAGE(F66:J66) -> 0.014822225 | L66: =AVERAGE(G66:K66) -> 0.014506357 | M66: =AVERAGE(H66:L66) -> 0.017212299 | N66: =AVERAGE(I66:M66) -> 0.015798596 | O66: =AVERAGE(J66:N66) -> 0.015815895
A67: Interest Expense, Net Non-Operating | C67: -- | D67: -- | E67: -- | F67: -- | G67: -- | H67: -- | I67: --
A68: Interest/Invest Income - Non-Operating | C68: -- | D68: -- | E68: -- | F68: -- | G68: -- | H68: -- | I68: --
A69: Interest Income(Exp), Net Non-Operating | C69: -- | D69: -- | E69: -- | F69: -- | G69: -- | H69: -- | I69: --
A70: Interest Inc.(Exp.),Net-Non-Op., Total | C70: -- | D70: -- | E70: -- | F70: -- | G70: -- | H70: -- | I70: --
A71: Gain (Loss) on Sale of Assets | C71: -- | D71: -- | E71: -- | F71: -- | G71: -- | H71: -- | I71: --
A72: Other, Net | C72: 29815 | D72: 28835 | E72: 31987 | F72: 5180 | G72: 14108 | H72: 7945 | I72: 11656
A73: Other Non-Operating Income (Expense) | C73: 29815 | D73: 28835 | E73: 31987 | F73: 5180 | G73: 14108 | H73: 7945 | I73: 11656
A74: Net Income Before Taxes | C74: 259383 | D74: 363074 | E74: 434775 | F74: 278003 | G74: 28427 | H74: 554140 | I74: 485623 | J74: =J76*'Revenue breakdown'!G3 -> 674057.52 | K74: =K76*'Revenue breakdown'!H3 -> 634227.55 | L74: =L76*'Revenue breakdown'!I3 -> 672161.15 | M74: =M76*'Revenue breakdown'!J3 -> 855376.55 | N74: =N76*'Revenue breakdown'!K3 -> 842557.04 | O74: =O76*'Revenue breakdown'!L3 -> 918340.86
E75: =(E74-D74)/D74 -> 0.19748316 | F75: =(F74-E74)/E74 -> -0.36058191 | G75: =(G74-F74)/F74 -> -0.89774571 | H75: =(H74-G74)/G74 -> 18.493439 | I75: =(I74-H74)/H74 -> -0.12364565
B76: %/ rev | E76: =E74/'Revenue breakdown'!B3 -> 0.028419759 | F76: =F74/'Revenue breakdown'!C3 -> 0.016712978 | G76: =G74/'Revenue breakdown'!D3 -> 0.0019388985 | H76: =H74/'Revenue breakdown'!E3 -> 0.024633961 | I76: =I74/'Revenue breakdown'!F3 -> 0.016098462 | J76: =AVERAGE(E76:I76) -> 0.017560812 | K76: =AVERAGE(F76:J76) -> 0.015389022 | L76: =AVERAGE(G76:K76) -> 0.015124231 | M76: =AVERAGE(H76:L76) -> 0.017761298 | N76: =AVERAGE(I76:M76) -> 0.016386765 | O76: =AVERAGE(J76:N76) -> 0.016444426
A77: Provision for Income Taxes | C77: 51877 | D77: 73196 | E77: 87028 | F77: 74155 | G77: 18211 | H77: 110242 | I77: 87549 | J77: =AVERAGE(E77:I77) -> 75437 | K77: =AVERAGE(F77:J77) -> 73118.8 | L77: =AVERAGE(G77:K77) -> 72911.56 | M77: =AVERAGE(H77:L77) -> 83851.672 | N77: =AVERAGE(I77:M77) -> 78573.606 | O77: =AVERAGE(J77:N77) -> 76778.528
A78: Net Income After Taxes | C78: 207506 | D78: 289878 | E78: 347747 | F78: 203847 | G78: 10217 | H78: 443898 | I78: 398074 | J78: =J74-J77 -> 598620.52 | K78: =K74-K77 -> 561108.75 | L78: =L74-L77 -> 599249.59 | M78: =M74-M77 -> 771524.87 | N78: =N74-N77 -> 763983.43 | O78: =O74-O77 -> 841562.34
A79: Minority Interest | C79: -- | D79: -- | E79: 16 | F79: 9168 | G79: 14502 | H79: -166 | I79: -7713
A80: Equity In Affiliates | C80: -- | D80: -- | E80: -- | F80: -- | G80: -- | H80: -- | I80: --
A81: U.S. GAAP Adjustment | C81: -- | D81: -- | E81: -- | F81: -- | G81: -- | H81: -- | I81: --
A82: Net Income Before Extra. Items | C82: 207506 | D82: 289878 | E82: 347763 | F82: 213015 | G82: 24719 | H82: 443732 | I82: 390361
A84: Accounting Change | C84: -- | D84: -- | E84: -- | F84: -- | G84: -- | H84: -- | I84: --
A85: Discontinued Operations | C85: -- | D85: -- | E85: -- | F85: -- | G85: -- | H85: -- | I85: --
A86: Extraordinary Item | C86: -- | D86: -- | E86: -- | F86: -- | G86: -- | H86: -- | I86: --
A87: Tax on Extraordinary Items | C87: -- | D87: -- | E87: -- | F87: -- | G87: -- | H87: -- | I87: --
A88: Total Extraordinary Items | C88: -- | D88: -- | F88: -- | G88: -- | H88: -- | I88: --
A89: Net Income | C89: 207506 | D89: 289878 | E89: 347763 | F89: 213015 | G89: 24719 | H89: 443732 | I89: 390361 | J89: =J94*'Revenue breakdown'!G3 -> 536537.71 | K89: =K94*'Revenue breakdown'!H3 -> 541060.85 | L89: =L94*'Revenue breakdown'!I3 -> 589088.45 | M89: =M94*'Revenue breakdown'!J3 -> 762226.14 | N89: =N94*'Revenue breakdown'!K3 -> 758963 | O89: =O94*'Revenue breakdown'!L3 -> 860684.7
B90: FPT Shop | E90: =E89*'Revenue breakdown'!B8 -> 339920.43 | F90: =F89*'Revenue breakdown'!C8 -> 206473.88 | G90: =G89*'Revenue breakdown'!D8 -> 22719.939 | H90: =H89*'Revenue breakdown'!E8 -> 366073.77 | I90: =I89*'Revenue breakdown'!F8 -> 267724.1 | J90: =I90*(1+J91) -> 271438.92 | K90: =J90*(1+K91) -> 274752.32 | L90: =K90*(1+L91) -> 278073.23 | M90: =L90*(1+M91) -> 282012.73 | N90: =M90*(1+N91) -> 285694.52 | O90: =N90*(1+O91) -> 289430.93
B91: %/rev | E91: =E90/'Revenue breakdown'!B6 -> 0.022219408 | F91: =F90/'Revenue breakdown'!C6 -> 0.012806031 | G91: =G90/'Revenue breakdown'!D6 -> 0.0016859898 | H91: =H90/'Revenue breakdown'!E6 -> 0.01972584 | I91: =I90/'Revenue breakdown'!F6 -> 0.012940515 | J91: =AVERAGE(E91:I91) -> 0.013875557 | K91: =AVERAGE(F91:J91) -> 0.012206786 | L91: =AVERAGE(G91:K91) -> 0.012086938 | M91: =AVERAGE(H91:L91) -> 0.014167127 | N91: =AVERAGE(I91:M91) -> 0.013055385 | O91: =AVERAGE(J91:N91) -> 0.013078358
B92: Long Chau | E92: =E89-E90 -> 7842.5682 | F92: =F89-F90 -> 6541.1155 | G92: =G89-G90 -> 1999.0613 | H92: =H89-H90 -> 77658.225 | I92: =I89-I90 -> 122636.9 | J92: =I92*(1+J93) -> 124342.11 | K92: =J92*(1+K93) -> 125851.51 | L92: =K92*(1+L93) -> 127362.44 | M92: =L92*(1+M93) -> 129154.56 | N92: =M92*(1+N93) -> 130831 | O92: =N92*(1+O93) -> 132534.43
B93: %/rev | E93: =E92/'Revenue breakdown'!B12 -> 0.022732082 | F93: =F92/'Revenue breakdown'!C12 -> 0.012806056 | G93: =G92/'Revenue breakdown'!D12 -> 0.0016786985 | H93: =H92/'Revenue breakdown'!E12 -> 0.019525913 | I93: =I92/'Revenue breakdown'!F12 -> 0.012780079 | J93: =AVERAGE(E93:I93) -> 0.013904565 | K93: =AVERAGE(F93:J93) -> 0.012139062 | L93: =AVERAGE(G93:K93) -> 0.012005664 | M93: =AVERAGE(H93:L93) -> 0.014071057 | N93: =AVERAGE(I93:M93) -> 0.012980085 | O93: =AVERAGE(J93:N93) -> 0.013020087
B94: Net profit margin | E94: =E89/'Revenue breakdown'!B3 -> 0.022732082 | F94: =F89/'Revenue breakdown'!C3 -> 0.012806031 | G94: =G89/'Revenue breakdown'!D3 -> 0.0016859898 | H94: =H89/'Revenue breakdown'!E3 -> 0.01972584 | I94: =I89/'Revenue breakdown'!F3 -> 0.012940515 | J94: =AVERAGE(E94:I94) -> 0.013978091 | K94: =AVERAGE(F94:J94)*(100%+'Revenue breakdown'!H4) -> 0.013128407 | L94: =AVERAGE(G94:K94)*(100%+'Revenue breakdown'!I4) -> 0.013255021 | M94: =AVERAGE(H94:L94)*(100%+'Revenue breakdown'!J4) -> 0.015827094 | N94: =AVERAGE(I94:M94)*(100%+'Revenue breakdown'!K4) -> 0.014760957 | O94: =AVERAGE(J94:N94)*(100%+'Revenue breakdown'!L4) -> 0.015411996
B95: %growth | E95: =(E89-D89)/D89 -> 0.19968745 | F95: =(F89-E89)/E89 -> -0.38747078 | G95: =(G89-F89)/F89 -> -0.88395653 | H95: =(H89-G89)/G89 -> 16.95105 | I95: =(I89-H89)/H89 -> -0.12027755
A96: Preferred Dividends | C96: -- | D96: -- | E96: -- | F96: -- | G96: -- | H96: -- | I96: --
A97: General Partners' Distributions | C97: -- | D97: -- | E97: -- | F97: -- | G97: -- | H97: -- | I97: --
A98: Miscellaneous Earnings Adjustment | C98: -6225 | D98: -8704 | E98: -10434 | F98: -7371 | G98: -3700 | H98: -- | I98: --
A99: Pro Forma Adjustment | C99: -- | D99: -- | E99: -- | F99: -- | G99: -- | H99: -- | I99: --
A100: Interest Adjustment - Primary EPS | C100: -- | D100: -- | E100: -- | F100: -- | G100: -- | H100: -- | I100: --
A101: Total Adjustments to Net Income | C101: -6225 | D101: -8704 | E101: -10434 | F101: -7371 | G101: -3700 | H101: -- | I101: --
A102: Income Available to Com Excl ExtraOrd | C102: 201281 | D102: 281174 | E102: 337329 | F102: 205644 | G102: 21018 | H102: 443732 | I102: 390361
A103: Income Available to Com Incl ExtraOrd | C103: 201281 | D103: 281174 | E103: 337329 | F103: 205644 | G103: 21018 | H103: 443732 | I103: 390361
A104: Basic Weighted Average Shares | C104: 67 | D104: 135 | E104: 135 | F104: 136 | G104: 136 | H104: 136 | I104: 136
...

Sheet App
A1: Income Statement | C1: 2016 | D1: 2017 | E1: 2018 | F1: 2019 | G1: 2020 | H1: 2021 | I1: 2022 | J1: 2023F | K1: 2024F | L1: 2025F | M1: 2026F | N1: 2027F | O1: 2028F
A2: Period End Date | C2: 31-Dec-2016 | D2: 31-Dec-2017 | E2: 31-Dec-2018 | F2: 31-Dec-2019 | G2: 31-Dec-2020 | H2: 31-Dec-2021 | I2: 31-Dec-2022 | J2: 31-Dec-2018 | K2: 31-Dec-2019 | L2: 31-Dec-2019 | M2: 31-Dec-2020 | N2: 31-Dec-2021 | O2: 31-Dec-2022
A3: Period Length | C3: 12 Months | D3: 12 Months | E3: 12 Months | F3: 12 Months | G3: 12 Months | H3: 12 Months | I3: 12 Months | J3: Updated | K3: Updated | L3: Restated | M3: Updated | N3: Updated | O3: Updated
A4: Update Type | C4: Updated | D4: Updated | E4: Updated | F4: Updated | G4: Updated | H4: Updated | I4: Updated | J4: 31-Dec-2018 | K4: 31-Dec-2019 | L4: 31-Dec-2020 | M4: 31-Dec-2020 | N4: 31-Dec-2021 | O4: 31-Dec-2022
A5: Statement Date | C5: 31-Dec-2017 | D5: 31-Dec-2017 | E5: 31-Dec-2018 | F5: 31-Dec-2019 | G5: 31-Dec-2020 | H5: 31-Dec-2021 | I5: 31-Dec-2022 | J5: Thousands | K5: Thousands | L5: Thousands | M5: Thousands | N5: Thousands | O5: Thousands
A6: Reporting Unit | C6: Thousands | D6: Thousands | E6: Thousands | F6: Thousands | G6: Thousands | H6: Thousands | I6: Thousands | J6: 06-Jun-2022 | K6: 06-Jun-2023 | L6: 06-Jun-2023 | M6: 06-Jun-2023 | N6: 06-Jun-2023 | O6: 08-Jun-2023
A7: Update Date | C7: 06-Jun-2023 | D7: 06-Jun-2023 | E7: 06-Jun-2023 | F7: 06-Jun-2023 | G7: 06-Jun-2023 | H7: 06-Jun-2023 | I7: 08-Jun-2023 | J7: Vietnamese Dong | K7: Vietnamese Dong | L7: Vietnamese Dong | M7: Vietnamese Dong | N7: Vietnamese Dong | O7: Vietnamese Dong
A8: Reporting Currency | C8: Vietnamese Dong | D8: Vietnamese Dong | E8: Vietnamese Dong | F8: Vietnamese Dong | G8: Vietnamese Dong | H8: Vietnamese Dong | I8: Vietnamese Dong | J8: ARS | K8: ARS | L8: ARS | M8: ARS | N8: ARS | O8: ARS
A9: Source | C9: ARS | D9: ARS | E9: ARS | F9: ARS | G9: ARS | H9: ARS | I9: ARS | J9: 16-Apr-2019 | K9: 31-Mar-2020 | L9: 31-Mar-2021 | M9: 31-Mar-2021 | N9: 14-Mar-2022 | O9: 27-Mar-2023
A10: Source Date | C10: 27-Apr-2018 | D10: 27-Apr-2018 | E10: 16-Apr-2019 | F10: 31-Mar-2020 | G10: 31-Mar-2021 | H10: 14-Mar-2022 | I10: 27-Mar-2023 | J10: 21-Jan-2019 11:01 | K10: 22-Jan-2020 14:59 | L10: 01-Feb-2021 06:43 | M10: 01-Feb-2021 06:43 | N10: 07-Feb-2022 15:18 | O10: 31-Jan-2023 20:37
A11: Original Announcement Date | C11: 10-Apr-2018 03:48 | D11: 27-Apr-2018 05:00 | E11: 21-Jan-2019 11:01 | F11: 22-Jan-2020 14:59 | G11: 01-Feb-2021 06:43 | H11: 07-Feb-2022 15:18 | I11: 31-Jan-2023 20:37 | J11: Complete | K11: Complete | L11: Complete | M11: Complete | N11: Complete | O11: Complete
A12: Complete Statement | C12: Complete | D12: Complete | E12: Complete | F12: Complete | G12: Complete | H12: Complete | I12: Complete | J12: No | K12: No | L12: No | M12: No | N12: No | O12: No
A13: Flash Update | C13: No | D13: No | E13: No | F13: No | G13: No | H13: No | I13: No | J13: Yes | K13: Yes | L13: Yes | M13: Yes | N13: Yes | O13: Yes
... A16: Auditor Opinion | C16: Unqualified with Explanation | D16: Unqualified with Explanation | E16: Unqualified with Explanation | F16: Unqualified | G16: Unqualified | H16: Unqualified | I16: Unqualified | J16: Vietnamese Accounting Standards | K16: Vietnamese Accounting Standards | L16: Vietnamese Accounting Standards | M16: Vietnamese Accounting Standards | N16: Vietnamese Accounting Standards | O16: Vietnamese Accounting Standards
A17: Accounting Standard | C17: Vietnamese Accounting Standards | D17: Vietnamese Accounting Standards | E17: Vietnamese Accounting Standards | F17: Vietnamese Accounting Standards | G17: Vietnamese Accounting Standards | H17: Vietnamese Accounting Standards | I17: Vietnamese Accounting Standards
A18: Revenue | C18: 10853155 | D18: 13146515 | E18: 15298335 | F18: 16633960 | G18: 14661417 | H18: 22494961 | I18: 30165801 | J18: ='Revenue breakdown'!G3 -> 38384189 | K18: ='Revenue breakdown'!H3 -> 41212985 | L18: ='Revenue breakdown'!I3 -> 44442666 | M18: ='Revenue breakdown'!J3 -> 48159575 | N18: ='Revenue breakdown'!K3 -> 51416923 | O18: ='Revenue breakdown'!L3 -> 55845117
A19: Gross Revenue | C19: 11722218 | D19: 13795036 | E19: 15889646 | F19: 16988957 | G19: 14799953 | H19: 22619505 | I19: 30276711
A20: Sales Returns and Allowances | C20: -869062 | D20: -648521 | E20: -591311 | F20: -354997 | G20: -138536 | H20: -124544 | I20: -110910
A21: Other Revenue, Total | C21: -- | D21: -- | E21: -- | F21: -- | G21: -- | H21: -- | I21: --
A22: Total Revenue | C22: 10853155 | D22: 13146515 | E22: 15298335 | F22: 16633960 | G22: 14661417 | H22: 22494961 | I22: 30165801 | J22: ='Revenue breakdown'!G3 -> 38384189 | K22: ='Revenue breakdown'!H3 -> 41212985 | L22: ='Revenue breakdown'!I3 -> 44442666 | M22: ='Revenue breakdown'!J3 -> 48159575 | N22: ='Revenue breakdown'!K3 -> 51416923 | O22: ='Revenue breakdown'!L3 -> 55845117
A23: Cost of Revenue, Total | C23: 9442776 | D23: 11330255 | E23: 13254725 | F23: 14522903 | G23: 12620415 | H23: 19343448 | I23: 25462623
A24: Cost of Revenue (COGS) | C24: 9442776 | D24: 11330255 | E24: 13254725 | F24: 14522903 | G24: 12620415 | H24: 19343448 | I24: 25462623 | J24: =J25*'Revenue breakdown'!G3 -> 32399675 | K24: =K25*'Revenue breakdown'!H3 -> 35294455 | L24: =L25*'Revenue breakdown'!I3 -> 37911923 | M24: =M25*'Revenue breakdown'!J3 -> 41008105 | N24: =N25*'Revenue breakdown'!K3 -> 43695406 | O24: =O25*'Revenue breakdown'!L3 -> 47522666
B25: %/rev | E25: =E24/E22 -> 0.86641618 | F25: =F24/F22 -> 0.87308753 | G25: =G24/G22 -> 0.86079095 | H25: =H24/H22 -> 0.85990138 | I25: =I24/I22 -> 0.84408907 | J25: =I25 -> 0.84408907 | K25: =AVERAGE(F25:J25) -> 0.8563916 | L25: =AVERAGE(G25:K25) -> 0.85305241 | M25: =AVERAGE(H25:L25) -> 0.85150471 | N25: =AVERAGE(I25:M25) -> 0.84982537 | O25: =AVERAGE(J25:N25) -> 0.85097263
E26: =(E24-D24)/D24 -> 0.16985231 | F26: =(F24-E24)/E24 -> 0.095677428 | G26: =(G24-F24)/F24 -> -0.13099915 | H26: =(H24-G24)/G24 -> 0.53271093 | I26: =(I24-H24)/H24 -> 0.31634355
A27: Gross Profit | C27: 1410379 | D27: 1816260 | E27: =E22-E24 -> 2043610 | F27: =F22-F24 -> 2111057 | G27: =G22-G24 -> 2041002 | H27: =H22-H24 -> 3151513 | I27: =I22-I24 -> 4703178 | J27: =J22-J24 -> 5984514.5 | K27: =K22-K24 -> 5918530.9 | L27: =L22-L24 -> 6530742.5 | ... O27: =O22-O24 -> 8322450.7
A28: COGS | E28: 13325966 | F28: 14522902 | G28: 12620414 | H28: 19343448 | I28: 25462623
B29: FPT Shop | E29: =E27*'Revenue breakdown'!B8 -> 1997523.6 | F29: =F27*'Revenue breakdown'!C8 -> 2046232.1 | G29: =G27*'Revenue breakdown'!D8 -> 1875943.2 | H29: =H27*'Revenue breakdown'!E8 -> 2599961.8 | I29: =I27*'Revenue breakdown'!F8 -> 3225614.5 | J29: =J30*'Revenue breakdown'!G6 -> 2789753.8 | K29: =K30*'Revenue breakdown'!H6 -> 2860057.5 | L29: =L30*'Revenue breakdown'!I6 -> 2975297.3 | M29: =M30*'Revenue breakdown'!J6 -> 3085391.3 | N29: =N30*'Revenue breakdown'!K6 -> 3161760.6 | O29: =O30*'Revenue breakdown'!L6 -> 3387524.7
B30: %/rev | E30: =E29/E18 -> 0.13057131 | F30: =F29/F18 -> 0.12301533 | G30: =G29/G18 -> 0.12795102 | H30: =H29/H18 -> 0.11557974 | I30: =I29/I18 -> 0.10692952 | J30: =AVERAGE(E30:I30) -> 0.12080938 | K30: =AVERAGE(F30:J30) -> 0.118857 | L30: =AVERAGE(G30:K30) -> 0.11802533 | M30: =AVERAGE(H30:L30) -> 0.11604019 | N30: =AVERAGE(I30:M30) -> 0.11613228 | O30: =AVERAGE(J30:N30) -> 0.11797284
B31: Long Chau | E31: =E27*'Revenue breakdown'!B15 -> 46086.417 | F31: =F27*'Revenue breakdown'!C15 -> 64824.734 | G31: =G27*'Revenue breakdown'!D15 -> 165775.71 | H31: =H27*'Revenue breakdown'!E15 -> 557198.55 | I31: =I27*'Revenue breakdown'!F15 -> 1496112.2 | J31: =J32*'Revenue breakdown'!G12 -> 283155.17 | K31: =K32*'Revenue breakdown'!H12 -> 370737.33 | L31: =L32*'Revenue breakdown'!I12 -> 483947.05 | M31: =M32*'Revenue breakdown'!J12 -> 602516.49 | N31: =N32*'Revenue breakdown'!K12 -> 691022.78 | O31: =O32*'Revenue breakdown'!L12 -> 660862.26
B32: %/rev | E32: =E31/E18 -> 0.003012512 | F32: =F31/F18 -> 0.0038971318 | G32: =G31/G18 -> 0.011306936 | H32: =H31/H18 -> 0.024769927 | I32: =I31/I18 -> 0.049596303 | J32: =AVERAGE(E32:I32) -> 0.018516562 | K32: =AVERAGE(F32:J32) -> 0.021617372 | L32: =AVERAGE(G32:K32) -> 0.02516142 | M32: =AVERAGE(H32:L32) -> 0.027932317 | N32: =AVERAGE(I32:M32) -> 0.028564795 | O32: =AVERAGE(J32:N32) -> 0.024358493
B33: Gross profit margin | E33: =E27/E22 -> 0.13358382 | F33: =F27/F22 -> 0.12691247 | G33: =G27/G22 -> 0.13920905 | H33: =H27/H22 -> 0.14009862 | I33: =I27/I22 -> 0.15591093 | J33: =J27/J22 -> 0.15591093 | K33: =K27/K22 -> 0.1436084 | L33: =L27/L22 -> 0.14694759 | ... O33: =O27/O22 -> 0.14902737
A34: Selling/General/Admin. Expenses, Total | C34: 1180366 | D34: 1454296 | E34: 1583114 | F34: 1768320 | G34: 1935903 | H34: 2656653 | I34: 4146636 | J34: =J37*J18 -> 4961021.4 | K34: =K37*K18 -> 5309552.6 | L34: =L37*L18 -> 5942836.8 | M34: =M37*M18 -> 6379782 | N34: =N37*N18 -> 6913568.8 | O34: =O37*O18 -> 7577439.6
B35: FPT Shop | E35: =E34*'Revenue breakdown'!B8/E18 -> 0.10114908 | F35: =F34*'Revenue breakdown'!C8/F18 -> 0.10304339 | G35: =G34*'Revenue breakdown'!D8/G18 -> 0.12136233 | H35: =H34*'Revenue breakdown'!E8/H18 -> 0.097431066 | I35: =I34*'Revenue breakdown'!F8/I18 -> 0.094276207 | J35: =AVERAGE(E35:I35) -> 0.10345241 | K35: =AVERAGE(F35:J35) -> 0.10391308 | L35: =AVERAGE(G35:K35) -> 0.10408702 | M35: =AVERAGE(H35:L35) -> 0.10063196 | N35: =AVERAGE(I35:M35) -> 0.10127214 | O35: =AVERAGE(J35:N35) -> 0.10267132
B36: Long Chau | E36: =E34*'Revenue breakdown'!B15/'FPT Digital Retail JSC | Income'!E23 -> 0.0023336888 | F36: =F34*'Revenue breakdown'!C15/'FPT Digital Retail JSC | Income'!F23 -> 0.0032644197 | G36: =G34*'Revenue breakdown'!D15/'FPT Digital Retail JSC | Income'!G23 -> 0.010724699 | H36: =H34*'Revenue breakdown'!E15/'FPT Digital Retail JSC | Income'!H23 -> 0.020880479 | I36: =I34*'Revenue breakdown'!F15/'FPT Digital Retail JSC | Income'!I23 -> 0.043727415 | J36: =AVERAGE(E36:I36)*(100%+'Revenue breakdown'!G17) -> 0.025794067 | K36: =AVERAGE(F36:J36)*(100%+'Revenue breakdown'!H17) -> 0.024918948 | L36: =AVERAGE(G36:K36)*(100%+'Revenue breakdown'!I17) -> 0.029632158 | M36: =AVERAGE(H36:L36)*(100%+'Revenue breakdown'!J17) -> 0.031839767 | N36: =AVERAGE(I36:M36)*(100%+'Revenue breakdown'!K17) -> 0.033188822 | O36: =AVERAGE(J36:N36)*(100%+'Revenue breakdown'!L17) -> 0.033015379
B37: %/rev | E37: =E34/E18 -> 0.10348276 | F37: =F34/F18 -> 0.10630782 | G37: =G34/G18 -> 0.13204065 | H37: =H34/H18 -> 0.11809992 | I37: =I34/I18 -> 0.13746149 | J37: =SUM(J35:J36) -> 0.12924648 | K37: =SUM(K35:K36) -> 0.12883203 | L37: =SUM(L35:L36) -> 0.13371918 | M37: =SUM(M35:M36) -> 0.13247173 | N37: =SUM(N35:N36) -> 0.13446096 | O37: =SUM(O35:O36) -> 0.1356867
E38: =E25+E37 -> 0.96989895 | F38: =F25+F37 -> 0.97939535 | G38: =G25+G37 -> 0.99283159 | H38: =H25+H37 -> 0.9780013 | I38: =I25+I37 -> 0.98155056 | J38: =SUM(J37,J25) -> 0.97333555 | K38: =SUM(K37,K25) -> 0.98522363 | L38: =SUM(L37,L25) -> 0.98677159 | M38: =SUM(M37,M25) -> 0.98397643 | N38: =SUM(N37,N25) -> 0.98428633 | O38: =SUM(O37,O25) -> 0.98665933
E39: =E34/E27 -> 0.77466542 | F39: =F34/F27 -> 0.83764673 | G39: =G34/G27 -> 0.94850617 | H39: =H34/H27 -> 0.84297701 | I39: =I34/I27 -> 0.88166682 | J39: =J34/J27 -> 0.82897642 | K39: =K34/K27 -> 0.8971065 | L39: =L34/L27 -> 0.90997873 | ... O39: =O34/O27 -> 0.91048178
A40: Selling/General/Administrative Expense | C40: 653541 | D40: 808222 | E40: 935387 | F40: 984520 | G40: 1049295 | H40: 1101041 | I40: 1842001
A41: Labor & Related Expense | C41: 526826 | D41: 646073 | E41: 647727 | F41: 783800 | G41: 886608 | H41: 1365500 | I41: 1957142
A42: Advertising Expense | C42: -- | D42: -- | E42: -- | F42: -- | G42: -- | H42: 190112 | I42: 347493
A43: Research & Development | C43: -- | D43: -- | E43: -- | F43: -- | G43: -- | H43: -- | I43: --
A44: Depreciation/Amortization | C44: -- | D44: -- | E44: 781 | F44: 837 | G44: 1372 | H44: 3811 | I44: 115286 | J44: =J18*J45 -> 146694.58 | K44: =K18*K45 -> 157505.52 | L44: =L18*L45 -> 169848.54 | M44: =M18*M45 -> 184053.62 | N44: =N18*N45 -> 196502.37 | O44: =O18*O45 -> 213425.8
E45: =E44/'Revenue breakdown'!B3 -> 5.1051307e-05 | F45: =F44/'Revenue breakdown'!C3 -> 5.0318746e-05 | G45: =G44/'Revenue breakdown'!D3 -> 9.3578949e-05 | H45: =H44/'Revenue breakdown'!E3 -> 0.00016941572 | I45: =I44/'Revenue breakdown'!F3 -> 0.003821745 | J45: ='Revenue breakdown'!G25 -> 0.003821745 | K45: ='Revenue breakdown'!H25 -> 0.003821745 | L45: ='Revenue breakdown'!I25 -> 0.003821745 | M45: ='Revenue breakdown'!J25 -> 0.003821745 | N45: ='Revenue breakdown'!K25 -> 0.003821745 | O45: ='Revenue breakdown'!L25 -> 0.003821745
A46: Interest Expense, Net - Operating | C46: 73839 | D46: 78951 | E46: 95671 | F46: 135183 | G46: 113682 | H46: 132229 | I46: 231528
A47: Interest Expense - Operating | C47: 73839 | D47: 78951 | E47: 95671 | F47: 135183 | G47: 113682 | H47: 132229 | I47: 231528
A48: Interest/Investment Income - Operating | C48: -56338 | D48: -32858 | E48: -18853 | F48: -51481 | G48: -37582 | H48: -167854 | I48: -129556
A49: Interest Income - Operating | C49: -54495 | D49: -35206 | E49: -20946 | F49: -61193 | G49: -55871 | H49: -169344 | I49: -147691
A50: Investment Income - Operating | C50: -1842 | D50: 2348 | E50: 2094 | F50: 9712 | G50: 18289 | H50: 1490 | I50: 18135
A51: Interest Expense(Income) - Net Operating | C51: -- | D51: -- | E51: -- | F51: -- | G51: -- | H51: -- | I51: --
A52: Interest Exp.(Inc.),Net-Operating, Total | C52: 17501 | D52: 46093 | E52: 76818 | F52: 83702 | G52: 76101 | H52: -35625 | I52: 101972
A53: Unusual Expense (Income) | C53: -- | D53: -- | E53: -- | F53: -- | G53: -- | H53: -- | I53: --
A54: Other Operating Expenses, Total | C54: -17056 | D54: -18367 | E54: -19111 | F54: -13787 | G54: 14680 | H54: -15711 | I54: -19399
A55: Other Operating Expenses, Total | C55: -17056 | D55: -18367 | E55: -19111 | F55: -13787 | G55: 14680 | H55: -15711 | I55: -19399
A56: Total Operating Expense | C56: 10623588 | D56: 12812276 | E56: 14895546 | F56: 16361137 | G56: 14647098 | H56: 21948766 | I56: 29691833
B57: Changes in Operational Cost | E57: =(E56-D56)/D56 -> 0.16259953 | F57: =(F56-E56)/E56 -> 0.098391224 | G57: =(G56-F56)/F56 -> -0.10476283 | H57: =(H56-G56)/G56 -> 0.49850612 | I57: =(I56-H56)/H56 -> 0.35277915
A58: Operating Income (EBIT) | C58: 229567 | D58: 334239 | E58: 402788 | F58: 272823 | G58: 14319 | H58: 546196 | I58: 473968 | J58: =J61*'Revenue breakdown'!G3 -> 642551.35 | K58: =K61*'Revenue breakdown'!H3 -> 610868.14 | L58: =L61*'Revenue breakdown'!I3 -> 644701.16 | M58: =M61*'Revenue breakdown'!J3 -> 828937 | N58: =N61*'Revenue breakdown'!K3 -> 812315.18 | O58: =O61*'Revenue breakdown'!L3 -> 883240.52
B60: %growth | E60: =(E58-D58)/D58 -> 0.20508977 | F60: =(F58-E58)/E58 -> -0.32266354 | G60: =(G58-F58)/F58 -> -0.94751542 | H60: =(H58-G58)/G58 -> 37.144843 | I60: =(I58-H58)/H58 -> -0.13223824 | J60: =(J58-I58)/I58 -> 0.35568509 | K60: =(K58-J58)/J58 -> -0.049308443 | L60: =(L58-K58)/K58 -> 0.055385146 | ... O60: =(O58-N58)/N58 -> 0.087312584
B61: %/rev | E61: =E58/'Revenue breakdown'!B3 -> 0.026328878 | F61: =F58/'Revenue breakdown'!C3 -> 0.016401566 | G61: =G58/'Revenue breakdown'!D3 -> 0.00097664503 | H61: =H58/'Revenue breakdown'!E3 -> 0.024280816 | I61: =I58/'Revenue breakdown'!F3 -> 0.015712097 | J61: =AVERAGE(E61:I61) -> 0.016740001 | K61: =AVERAGE(F61:J61) -> 0.014822225 | L61: =AVERAGE(G61:K61) -> 0.014506357 | M61: =AVERAGE(H61:L61) -> 0.017212299 | N61: =AVERAGE(I61:M61) -> 0.015798596 | O61: =AVERAGE(J61:N61) -> 0.015815895
A62: Interest Expense, Net Non-Operating | C62: -- | D62: -- | E62: -- | F62: -- | G62: -- | H62: -- | I62: --
A63: Interest/Invest Income - Non-Operating | C63: -- | D63: -- | E63: -- | F63: -- | G63: -- | H63: -- | I63: --
A64: Interest Income(Exp), Net Non-Operating | C64: -- | D64: -- | E64: -- | F64: -- | G64: -- | H64: -- | I64: --
A65: Interest Inc.(Exp.),Net-Non-Op., Total | C65: -- | D65: -- | E65: -- | F65: -- | G65: -- | H65: -- | I65: --
A66: Gain (Loss) on Sale of Assets | C66: -- | D66: -- | E66: -- | F66: -- | G66: -- | H66: -- | I66: --
A67: Other, Net | C67: 29815 | D67: 28835 | E67: 31987 | F67: 5180 | G67: 14108 | H67: 7945 | I67: 11656
A68: Other Non-Operating Income (Expense) | C68: 29815 | D68: 28835 | E68: 31987 | F68: 5180 | G68: 14108 | H68: 7945 | I68: 11656
A69: Net Income Before Taxes | C69: 259383 | D69: 363074 | E69: 434775 | F69: 278003 | G69: 28427 | H69: 554140 | I69: 485623 | J69: =J71*'Revenue breakdown'!G3 -> 674057.52 | K69: =K71*'Revenue breakdown'!H3 -> 634227.55 | L69: =L71*'Revenue breakdown'!I3 -> 672161.15 | M69: =M71*'Revenue breakdown'!J3 -> 855376.55 | N69: =N71*'Revenue breakdown'!K3 -> 842557.04 | O69: =O71*'Revenue breakdown'!L3 -> 918340.86
E70: =(E69-D69)/D69 -> 0.19748316 | F70: =(F69-E69)/E69 -> -0.36058191 | G70: =(G69-F69)/F69 -> -0.89774571 | H70: =(H69-G69)/G69 -> 18.493439 | I70: =(I69-H69)/H69 -> -0.12364565
B71: %/ rev | E71: =E69/'Revenue breakdown'!B3 -> 0.028419759 | F71: =F69/'Revenue breakdown'!C3 -> 0.016712978 | G71: =G69/'Revenue breakdown'!D3 -> 0.0019388985 | H71: =H69/'Revenue breakdown'!E3 -> 0.024633961 | I71: =I69/'Revenue breakdown'!F3 -> 0.016098462 | J71: =AVERAGE(E71:I71) -> 0.017560812 | K71: =AVERAGE(F71:J71) -> 0.015389022 | L71: =AVERAGE(G71:K71) -> 0.015124231 | M71: =AVERAGE(H71:L71) -> 0.017761298 | N71: =AVERAGE(I71:M71) -> 0.016386765 | O71: =AVERAGE(J71:N71) -> 0.016444426
A72: Provision for Income Taxes | C72: 51877 | D72: 73196 | E72: 87028 | F72: 74155 | G72: 18211 | H72: 110242 | I72: 87549 | J72: =AVERAGE(E72:I72) -> 75437 | K72: =AVERAGE(F72:J72) -> 73118.8 | L72: =AVERAGE(G72:K72) -> 72911.56 | M72: =AVERAGE(H72:L72) -> 83851.672 | N72: =AVERAGE(I72:M72) -> 78573.606 | O72: =AVERAGE(J72:N72) -> 76778.528
A73: Net Income After Taxes | C73: 207506 | D73: 289878 | E73: 347747 | F73: 203847 | G73: 10217 | H73: 443898 | I73: 398074 | J73: =J69-J72 -> 598620.52 | K73: =K69-K72 -> 561108.75 | L73: =L69-L72 -> 599249.59 | M73: =M69-M72 -> 771524.87 | N73: =N69-N72 -> 763983.43 | O73: =O69-O72 -> 841562.34
A74: Minority Interest | C74: -- | D74: -- | E74: 16 | F74: 9168 | G74: 14502 | H74: -166 | I74: -7713
A75: Equity In Affiliates | C75: -- | D75: -- | E75: -- | F75: -- | G75: -- | H75: -- | I75: --
A76: U.S. GAAP Adjustment | C76: -- | D76: -- | E76: -- | F76: -- | G76: -- | H76: -- | I76: --
A77: Net Income Before Extra. Items | C77: 207506 | D77: 289878 | E77: 347763 | F77: 213015 | G77: 24719 | H77: 443732 | I77: 390361
A79: Accounting Change | C79: -- | D79: -- | E79: -- | F79: -- | G79: -- | H79: -- | I79: --
A80: Discontinued Operations | C80: -- | D80: -- | E80: -- | F80: -- | G80: -- | H80: -- | I80: --
A81: Extraordinary Item | C81: -- | D81: -- | E81: -- | F81: -- | G81: -- | H81: -- | I81: --
A82: Tax on Extraordinary Items | C82: -- | D82: -- | E82: -- | F82: -- | G82: -- | H82: -- | I82: --
A83: Total Extraordinary Items | C83: -- | D83: -- | F83: -- | G83: -- | H83: -- | I83: --
A84: Net Income | C84: 207506 | D84: 289878 | E84: 347763 | F84: 213015 | G84: 24719 | H84: 443732 | I84: 390361 | J84: =J89*'Revenue breakdown'!G3 -> 536537.71 | K84: =K89*'Revenue breakdown'!H3 -> 541060.85 | L84: =L89*'Revenue breakdown'!I3 -> 589088.45 | M84: =M89*'Revenue breakdown'!J3 -> 762226.14 | N84: =N89*'Revenue breakdown'!K3 -> 758963 | O84: =O89*'Revenue breakdown'!L3 -> 860684.7
B85: FPT Shop | E85: =E84*'Revenue breakdown'!B8 -> 339920.43 | F85: =F84*'Revenue breakdown'!C8 -> 206473.88 | G85: =G84*'Revenue breakdown'!D8 -> 22719.939 | H85: =H84*'Revenue breakdown'!E8 -> 366073.77 | I85: =I84*'Revenue breakdown'!F8 -> 267724.1 | J85: =I85*(1+J86) -> 271438.92 | K85: =J85*(1+K86) -> 274752.32 | L85: =K85*(1+L86) -> 278073.23 | M85: =L85*(1+M86) -> 282012.73 | N85: =M85*(1+N86) -> 285694.52 | O85: =N85*(1+O86) -> 289430.93
B86: %/rev | E86: =E85/'Revenue breakdown'!B6 -> 0.022219408 | F86: =F85/'Revenue breakdown'!C6 -> 0.012806031 | G86: =G85/'Revenue breakdown'!D6 -> 0.0016859898 | H86: =H85/'Revenue breakdown'!E6 -> 0.01972584 | I86: =I85/'Revenue breakdown'!F6 -> 0.012940515 | J86: =AVERAGE(E86:I86) -> 0.013875557 | K86: =AVERAGE(F86:J86) -> 0.012206786 | L86: =AVERAGE(G86:K86) -> 0.012086938 | M86: =AVERAGE(H86:L86) -> 0.014167127 | N86: =AVERAGE(I86:M86) -> 0.013055385 | O86: =AVERAGE(J86:N86) -> 0.013078358
B87: Long Chau | E87: =E84-E85 -> 7842.5682 | F87: =F84-F85 -> 6541.1155 | G87: =G84-G85 -> 1999.0613 | H87: =H84-H85 -> 77658.225 | I87: =I84-I85 -> 122636.9 | J87: =I87*(1+J88) -> 124342.11 | K87: =J87*(1+K88) -> 125851.51 | L87: =K87*(1+L88) -> 127362.44 | M87: =L87*(1+M88) -> 129154.56 | N87: =M87*(1+N88) -> 130831 | O87: =N87*(1+O88) -> 132534.43
B88: %/rev | E88: =E87/'Revenue breakdown'!B12 -> 0.022732082 | F88: =F87/'Revenue breakdown'!C12 -> 0.012806056 | G88: =G87/'Revenue breakdown'!D12 -> 0.0016786985 | H88: =H87/'Revenue breakdown'!E12 -> 0.019525913 | I88: =I87/'Revenue breakdown'!F12 -> 0.012780079 | J88: =AVERAGE(E88:I88) -> 0.013904565 | K88: =AVERAGE(F88:J88) -> 0.012139062 | L88: =AVERAGE(G88:K88) -> 0.012005664 | M88: =AVERAGE(H88:L88) -> 0.014071057 | N88: =AVERAGE(I88:M88) -> 0.012980085 | O88: =AVERAGE(J88:N88) -> 0.013020087
B89: Net profit margin | E89: =E84/'Revenue breakdown'!B3 -> 0.022732082 | F89: =F84/'Revenue breakdown'!C3 -> 0.012806031 | G89: =G84/'Revenue breakdown'!D3 -> 0.0016859898 | H89: =H84/'Revenue breakdown'!E3 -> 0.01972584 | I89: =I84/'Revenue breakdown'!F3 -> 0.012940515 | J89: =AVERAGE(E89:I89) -> 0.013978091 | K89: =AVERAGE(F89:J89)*(100%+'Revenue breakdown'!H4) -> 0.013128407 | L89: =AVERAGE(G89:K89)*(100%+'Revenue breakdown'!I4) -> 0.013255021 | M89: =AVERAGE(H89:L89)*(100%+'Revenue breakdown'!J4) -> 0.015827094 | N89: =AVERAGE(I89:M89)*(100%+'Revenue breakdown'!K4) -> 0.014760957 | O89: =AVERAGE(J89:N89)*(100%+'Revenue breakdown'!L4) -> 0.015411996
B90: %growth | E90: =(E84-D84)/D84 -> 0.19968745 | F90: =(F84-E84)/E84 -> -0.38747078 | G90: =(G84-F84)/F84 -> -0.88395653 | H90: =(H84-G84)/G84 -> 16.95105 | I90: =(I84-H84)/H84 -> -0.12027755 | J90: =(J84-I84)/I84 -> 0.37446545 | K90: =(K84-J84)/J84 -> 0.0084302452 | L90: =(L84-K84)/K84 -> 0.088765613 | ... O90: =(O84-N84)/N84 -> 0.13402722
A91: Preferred Dividends | C91: -- | D91: -- | E91: -- | F91: -- | G91: -- | H91: -- | I91: --
A92: General Partners' Distributions | C92: -- | D92: -- | E92: -- | F92: -- | G92: -- | H92: -- | I92: --
A93: Miscellaneous Earnings Adjustment | C93: -6225 | D93: -8704 | E93: -10434 | F93: -7371 | G93: -3700 | H93: -- | I93: --
A94: Pro Forma Adjustment | C94: -- | D94: -- | E94: -- | F94: -- | G94: -- | H94: -- | I94: --
A95: Interest Adjustment - Primary EPS | C95: -- | D95: -- | E95: -- | F95: -- | G95: -- | H95: -- | I95: --
A96: Total Adjustments to Net Income | C96: -6225 | D96: -8704 | E96: -10434 | F96: -7371 | G96: -3700 | H96: -- | I96: --
A97: Income Available to Com Excl ExtraOrd | C97: 201281 | D97: 281174 | E97: 337329 | F97: 205644 | G97: 21018 | H97: 443732 | I97: 390361
A98: Income Available to Com Incl ExtraOrd | C98: 201281 | D98: 281174 | E98: 337329 | F98: 205644 | G98: 21018 | H98: 443732 | I98: 390361
A99: Basic Weighted Average Shares | C99: 67 | D99: 135 | E99: 135 | F99: 136 | G99: 136 | H99: 136 | I99: 136
A100: Basic EPS Excluding Extraordinary Items | C100: 2985.09 | D100: 2084.66 | E100: 2500.73 | F100: 1514.45 | G100: 154.27 | H100: 3256.94 | I100: 2865.19
A101: Basic EPS Including Extraordinary Items | C101: 2985.09 | D101: 2084.66 | E101: 2500.73 | F101: 1514.45 | G101: 154.27 | H101: 3256.94 | I101: 2865.19
A102: Dilution Adjustment | C102: -- | D102: -- | E102: -- | F102: -- | G102: -- | H102: -- | I102: --
A103: Diluted Net Income | C103: 201281 | D103: 281174 | E103: 337329 | F103: 205644 | G103: 21018 | H103: 443732 | I103: 390361
A104: Diluted Weighted Average Shares | C104: 67 | D104: 135 | E104: 135 | F104: 136 | G104: 136 | H104: 136 | I104: 136
...

Sheet BS
A1: Balance Sheet | C1: 2016 | D1: 2018 | E1: 2019 | F1: 2020 | G1: 2021 | H1: 2022 | I1: 2023F | J1: 2024F | K1: 2025F | L1: 2026F | M1: 2027F | N1: 2028F
B2: 2016 | C2: 2017 | D2: 2018 | E2: 2019 | F2: 2020 | G2: 2021 | H2: 2022 | I2: 2023F | J2: 2024F | K2: 2025F | L2: 2026F | M2: 2027F | N2: 2028F
A3: Period End Date | B3: 31-Dec-2016 | C3: 31-Dec-2017 | D3: 31-Dec-2018 | E3: 31-Dec-2019 | F3: 31-Dec-2020 | G3: 31-Dec-2021 | H3: 31-Dec-2022 | I3: 31-Dec-2018 | J3: 31-Dec-2019 | K3: 31-Dec-2019 | L3: 31-Dec-2020 | M3: 31-Dec-2021 | N3: 31-Dec-2022
A4: Update Type | B4: Updated | C4: Updated | D4: Updated | E4: Updated | F4: Updated | G4: Updated | H4: Updated | I4: Updated | J4: Updated | K4: Restated | L4: Updated | M4: Updated | N4: Updated
A5: Statement Date | B5: 31-Dec-2017 | C5: 31-Dec-2017 | D5: 31-Dec-2018 | E5: 31-Dec-2019 | F5: 31-Dec-2020 | G5: 31-Dec-2021 | H5: 31-Dec-2022 | I5: 31-Dec-2018 | J5: 31-Dec-2019 | K5: 31-Dec-2020 | L5: 31-Dec-2020 | M5: 31-Dec-2021 | N5: 31-Dec-2022
A6: Reporting Unit | B6: Thousands | C6: Thousands | D6: Thousands | E6: Thousands | F6: Thousands | G6: Thousands | H6: Thousands | I6: Thousands | J6: Thousands | K6: Thousands | L6: Thousands | M6: Thousands | N6: Thousands
A7: Update Date | B7: 06-Jun-2023 | C7: 06-Jun-2023 | D7: 06-Jun-2023 | E7: 06-Jun-2023 | F7: 06-Jun-2023 | G7: 06-Jun-2023 | H7: 08-Jun-2023 | I7: 06-Jun-2022 | J7: 06-Jun-2023 | K7: 06-Jun-2023 | L7: 06-Jun-2023 | M7: 06-Jun-2023 | N7: 08-Jun-2023
A8: Reporting Currency | B8: Vietnamese Dong | C8: Vietnamese Dong | D8: Vietnamese Dong | E8: Vietnamese Dong | F8: Vietnamese Dong | G8: Vietnamese Dong | H8: Vietnamese Dong | I8: Vietnamese Dong | J8: Vietnamese Dong | K8: Vietnamese Dong | L8: Vietnamese Dong | M8: Vietnamese Dong | N8: Vietnamese Dong
A9: Source | B9: ARS | C9: ARS | D9: ARS | E9: ARS | F9: ARS | G9: ARS | H9: ARS | I9: ARS | J9: ARS | K9: ARS | L9: ARS | M9: ARS | N9: ARS
A10: Source Date | B10: 27-Apr-2018 | C10: 27-Apr-2018 | D10: 16-Apr-2019 | E10: 31-Mar-2020 | F10: 31-Mar-2021 | G10: 14-Mar-2022 | H10: 27-Mar-2023 | I10: 16-Apr-2019 | J10: 31-Mar-2020 | K10: 31-Mar-2021 | L10: 31-Mar-2021 | M10: 14-Mar-2022 | N10: 27-Mar-2023
A11: Original Announcement Date | B11: 10-Apr-2018 03:48 | C11: 27-Apr-2018 05:00 | D11: 21-Jan-2019 11:01 | E11: 22-Jan-2020 14:59 | F11: 01-Feb-2021 06:43 | G11: 07-Feb-2022 15:18 | H11: 31-Jan-2023 20:37 | I11: 21-Jan-2019 11:01 | J11: 22-Jan-2020 14:59 | K11: 01-Feb-2021 06:43 | L11: 01-Feb-2021 06:43 | M11: 07-Feb-2022 15:18 | N11: 31-Jan-2023 20:37
A12: Complete Statement | B12: Complete | C12: Complete | D12: Complete | E12: Complete | F12: Complete | G12: Complete | H12: Complete | I12: Complete | J12: Complete | K12: Complete | L12: Complete | M12: Complete | N12: Complete
A13: Flash Update | B13: No | C13: No | D13: No | E13: No | F13: No | G13: No | H13: No | I13: No | J13: No | K13: No | L13: No | M13: No | N13: No
A14: Consolidated | B14: Yes | C14: Yes | D14: Yes | E14: Yes | F14: Yes | G14: Yes | H14: Yes | I14: Yes | J14: Yes | K14: Yes | L14: Yes | M14: Yes | N14: Yes
... A17: Accounting Standard | B17: Vietnamese Accounting Standards | C17: Vietnamese Accounting Standards | D17: Vietnamese Accounting Standards | E17: Vietnamese Accounting Standards | F17: Vietnamese Accounting Standards | G17: Vietnamese Accounting Standards | H17: Vietnamese Accounting Standards | I17: Vietnamese Accounting Standards | J17: Vietnamese Accounting Standards | K17: Vietnamese Accounting Standards | L17: Vietnamese Accounting Standards | M17: Vietnamese Accounting Standards | N17: Vietnamese Accounting Standards
A18: Assets (VND Millions)
A19: Cash and Short Term Investments | B19: 1457807 | C19: 638076 | D19: 952518 | E19: 1364293 | F19: 1489663 | G19: 2925710 | H19: 1864556
A20: Cash | B20: 409709 | C20: 567217 | D20: 855378 | E20: 415979 | F20: 551504 | G20: 679939 | H20: 450488
A21: Cash & Equivalents | B21: 1047798 | C21: 70859 | D21: 93000 | E21: 453671 | F21: 150000 | G21: 425271 | H21: 295068
A22: Short Term Investments | B22: 300 | C22: 0 | D22: 4140 | E22: 494643 | F22: 788159 | G22: 1820500 | H22: 1119000
A23: Accounts Receivable - Trade, Net | B23: 115139 | C23: 294862 | D23: 220039 | E23: 260115 | F23: 114599 | G23: 72977 | H23: 82479 | I23: =I50*'Revenue breakdown'!G3 -> 336364.41 | J23: =J50*'Revenue breakdown'!H3 -> 314829.2 | K23: =K50*'Revenue breakdown'!I3 -> 268405.96 | L23: =L50*'Revenue breakdown'!J3 -> 273737.96 | M23: =M50*'Revenue breakdown'!K3 -> 317342.36 | N23: =N50*'Revenue breakdown'!L3 -> 383069.28
A24: Accounts Receivable - Trade, Gross | B24: 119330 | C24: 305662 | D24: 237824 | E24: 294575 | F24: 172585 | G24: 80725 | H24: 89623
A25: Provision for Doubtful Accounts | B25: -4191 | C25: -10800 | D25: -17785 | E25: -34459 | F25: -57986 | G25: -7749 | H25: -7143
A26: Total Receivables (excl. note receivables) | D26: =D28-D31 -> 997840 | E26: =E28-E31 -> 888087 | F26: =F28-F31 -> 545692 | G26: =G28-G31 -> 477246 | H26: =H28-H31 -> 603715 | I26: =I27*'Revenue breakdown'!G3 -> 1512827.6 | J26: =J27*'Revenue breakdown'!H3 -> 1533930.6 | K26: =K27*'Revenue breakdown'!I3 -> 1654138 | L26: =L27*'Revenue breakdown'!J3 -> 1792479.9 | M26: =M27*'Revenue breakdown'!K3 -> 1913717.1 | N26: =N27*'Revenue breakdown'!L3 -> 2078532.6
A27: %rev | D27: =D26/'Revenue breakdown'!B3 -> 0.065225399 | E27: =E26/'Revenue breakdown'!C3 -> 0.053389993 | F27: =F26/'Revenue breakdown'!D3 -> 0.037219595 | G27: =G26/'Revenue breakdown'!E3 -> 0.021215685 | H27: =H26/'Revenue breakdown'!F3 -> 0.020013226 | I27: =AVERAGE(D27:H27) -> 0.039412779 | J27: =MEDIAN(E27:I27) -> 0.037219595 | K27: =MEDIAN(F27:J27) -> 0.037219595 | L27: =MEDIAN(G27:K27) -> 0.037219595 | M27: =MEDIAN(H27:L27) -> 0.037219595 | N27: =MEDIAN(I27:M27) -> 0.037219595
A28: Total Receivables, Net | B28: 852723 | C28: 1026478 | D28: 1118199 | E28: 1210446 | F28: 1430692 | G28: 2037246 | H28: 643715 | I28: =I29*'Revenue breakdown'!G3 -> 2667554.2 | J28: =J29*'Revenue breakdown'!H3 -> 2899346.9 | K28: =K29*'Revenue breakdown'!I3 -> 3105052.5 | L28: =L29*'Revenue breakdown'!J3 -> 3097785.2 | M28: =M29*'Revenue breakdown'!K3 -> 3037460.4 | N28: =N29*'Revenue breakdown'!L3 -> 3720529.4
A29: %rev | D29: =D26/'Revenue breakdown'!B3 -> 0.065225399 | E29: =E28/'Revenue breakdown'!C3 -> 0.072769563 | F29: =F28/'Revenue breakdown'!D3 -> 0.09758211 | G29: =G28/'Revenue breakdown'!E3 -> 0.090564549 | H29: =H28/'Revenue breakdown'!F3 -> 0.021339231 | I29: =AVERAGE(D29:H29) -> 0.06949617 | J29: =AVERAGE(E29:I29) -> 0.070350325 | K29: =AVERAGE(F29:J29) -> 0.069866477 | L29: =AVERAGE(G29:K29) -> 0.06432335 | M29: =AVERAGE(H29:L29) -> 0.059075111 | N29: =AVERAGE(I29:M29) -> 0.066622287
A30: %growth | D30: =D28/C28-1 -> 0.089355057 | E30: =E28/D28-1 -> 0.082496049 | F30: =F28/E28-1 -> 0.18195442 | G30: =G28/F28-1 -> 0.42395848 | H30: =H28/G28-1 -> -0.68402687
A31: Notes Receivable - Short Term | B31: 280150 | C31: 0 | D31: 120359 | E31: 322359 | F31: 885000 | G31: 1560000 | H31: 40000
A32: Receivables - Other | B32: 457434 | C32: 731616 | D32: 777800 | E32: 627971 | F32: 431093 | G32: 404269 | H32: 521235
A33: Total Inventory | B33: 1948265 | C33: 1723478 | D33: 2506219 | E33: 3383542 | F33: 1826718 | G33: 4930359 | H33: 6483828 | I33: =SUM(I36,I39) -> 7819825 | J33: =SUM(J36,J39) -> 8224217.7 | K33: =SUM(K36,K39) -> 8861137.9 | L33: =SUM(L36,L39) -> 9022495.4 | M33: =SUM(M36,M39) -> 9192019.2 | N33: =SUM(N36,N39) -> 9649471.5
A34: growth | E34: =E33/D33-1 -> 0.35005839 | F34: =F33/E33-1 -> -0.46011665 | G34: =G33/F33-1 -> 1.6990258 | H34: =H33/G33-1 -> 0.31508233
A35: weighted | D35: =D33/'Revenue breakdown'!B3 -> 0.16382299 | E35: =E33/'Revenue breakdown'!C3 -> 0.2034117 | F35: =F33/'Revenue breakdown'!D3 -> 0.12459355 | G35: =G33/'Revenue breakdown'!E3 -> 0.21917615 | H35: =H33/'Revenue breakdown'!F3 -> 0.21493969 | I35: =I33/'Revenue breakdown'!G3 -> 0.20372516 | J35: =J33/'Revenue breakdown'!H3 -> 0.19955404 | K35: =K33/'Revenue breakdown'!I3 -> 0.19938358 | ... N35: =N33/'Revenue breakdown'!L3 -> 0.17278989
A36: FPT shop inv | D36: =D33*'Revenue breakdown'!B8 -> 2449700.1 | E36: =E33*'Revenue breakdown'!C8 -> 3279642.6 | F36: =F33*'Revenue breakdown'!D8 -> 1678988.7 | G36: =G33*'Revenue breakdown'!E8 -> 4067489.2 | H36: =H33*'Revenue breakdown'!F8 -> 4446850.5 | I36: =I37*'Revenue breakdown'!G9 -> 5144009.4 | J36: =J37*'Revenue breakdown'!H9 -> 5309698 | K36: =K37*'Revenue breakdown'!I9 -> 5676726 | L36: =L37*'Revenue breakdown'!J9 -> 5801236.4 | M36: =M37*'Revenue breakdown'!K9 -> 6048683.4 | N36: =N37*'Revenue breakdown'!L9 -> 6369454.7
A37: FPT shop inv per store | D37: =D36/'Revenue breakdown'!B9 -> 4596.0602 | E37: =E36/'Revenue breakdown'!C9 -> 5530.5945 | F37: =F36/'Revenue breakdown'!D9 -> 2821.8297 | G37: =G36/'Revenue breakdown'!E9 -> 6286.6912 | H37: =H36/'Revenue breakdown'!F9 -> 5657.5707 | I37: =H37*(1+I38) -> 5949.6767 | J37: =I37*(1+J38) -> 5805.5731 | K37: =J37*(1+K38) -> 5885.1402 | L37: =K37*(1+L38) -> 5854.1987 | M37: =L37*(1+M38) -> 5878.9261 | N37: =M37*(1+N38) -> 5875.8876
A38: growth | E38: =(E37-D37)/D37 -> 0.2033338 | F38: =(F37-E37)/E37 -> -0.48977824 | G38: =(G37-F37)/F37 -> 1.2278776 | H38: =(H37-G37)/G37 -> -0.10007181 | I38: =MEDIAN(E38:H38) -> 0.051630995 | J38: =MEDIAN(F38:I38) -> -0.024220406 | K38: =MEDIAN(G38:J38) -> 0.013705294 | L38: =MEDIAN(H38:K38) -> -0.005257556 | M38: =MEDIAN(I38:L38) -> 0.0042238692 | N38: =MEDIAN(J38:M38) -> -0.0005168434
A39: Long Chau shop inv | D39: =D33*'Revenue breakdown'!B15 -> 56518.932 | E39: =E33*'Revenue breakdown'!C15 -> 103899.24 | F39: =F33*'Revenue breakdown'!D15 -> 148370.98 | G39: =G33*'Revenue breakdown'!E15 -> 871704.76 | H39: =H33*'Revenue breakdown'!F15 -> 2062548.8 | I39: =I40*'Revenue breakdown'!G16 -> 2675815.7 | J39: =J40*'Revenue breakdown'!H16 -> 2914519.7 | K39: =K40*'Revenue breakdown'!I16 -> 3184411.9 | L39: =L40*'Revenue breakdown'!J16 -> 3221259 | M39: =M40*'Revenue breakdown'!K16 -> 3143335.8 | N39: =N40*'Revenue breakdown'!L16 -> 3280016.8
A40: Long Chau inv per store | D40: =D39/'Revenue breakdown'!B16 -> 1883.9644 | E40: =E39/'Revenue breakdown'!C16 -> 1527.9299 | F40: =F39/'Revenue breakdown'!D16 -> 741.85492 | G40: =G39/'Revenue breakdown'!E16 -> 2179.2619 | H40: =H39/'Revenue breakdown'!F16 -> 2062.5488 | I40: =AVERAGE(D40:H40) -> 1679.112 | J40: =I40*(1+J41) -> 1532.3365 | K40: =J40*(1+K41) -> 1424.3307 | L40: =K40*(1+L41) -> 1311.8819 | M40: =L40*(1+M41) -> 1202.7589 | N40: =M40*(1+N41) -> 1105.2579
A41: growth | E41: =(E40-D40)/D40 -> -0.18898152 | F41: =(F40-E40)/E40 -> -0.51447059 | G41: =(G40-F40)/F40 -> 1.937585 | H41: =(H40-G40)/G40 -> -0.053556244 | I41: =MEDIAN(E41:H41) -> -0.12126888 | J41: =MEDIAN(F41:I41) -> -0.087412563 | K41: =MEDIAN(G41:J41) -> -0.070484404 | L41: =MEDIAN(H41:K41) -> -0.078948484 | M41: =MEDIAN(I41:L41) -> -0.083180523 | N41: =MEDIAN(J41:M41) -> -0.081064504
A42: Inventories - Finished Goods | B42: 1909828 | C42: 1679782 | D42: 2507175 | E42: 3380942 | F42: 1847193 | G42: 4933953 | H42: 6487575
A43: Inventories - Other | B43: 38437 | C43: 43696 | D43: -956 | E43: 2600 | F43: -20476 | G43: -3594 | H43: -3747
A44: Prepaid Expenses | B44: 149918 | C44: 121298 | D44: 238333 | E44: 214958 | F44: 212927 | G44: 328617 | H44: 334699 | I44: =AVERAGE(C44:H44) -> 241805.33 | J44: =AVERAGE(D44:I44) -> 261889.89 | K44: =AVERAGE(E44:J44) -> 265816.04 | L44: =AVERAGE(F44:K44) -> 274292.38 | M44: =AVERAGE(G44:L44) -> 284519.94 | N44: =AVERAGE(H44:M44) -> 277170.43
A45: Other Current Assets, Total | B45: -- | C45: -- | D45: -- | E45: -- | F45: -- | G45: -- | H45: --
D46: =(D33-C33)/C33 -> 0.45416362 | E46: =(E33-D33)/D33 -> 0.35005839 | F46: =(F33-E33)/E33 -> -0.46011665 | G46: =(G33-F33)/F33 -> 1.6990258 | H46: =(H33-G33)/G33 -> 0.31508233 | M46: =H46/G46-1 -> -0.81455118
A47: Total Current Assets (excluding cash) | C47: =SUM(C23,C28,C33,C44) -> 3166116 | D47: =D26+D33 -> 3504059 | E47: =E26+E33 -> 4271629 | F47: =F26+F33 -> 2372410 | G47: =G26+G33 -> 5407605 | H47: =H26+H33 -> 7087543 | I47: =I26+I33 -> 9332652.6 | J47: =J26+J33 -> 9758148.3 | K47: =K26+K33 -> 10515276 | ... N47: =N26+N33 -> 11728004
A48: Total Current Assets | B48: 4408713 | C48: 3509330 | D48: 4815269 | E48: 6173239 | F48: 4959999 | G48: 10221932 | H48: 9326797
A49: AR Growth | D49: =(D23-C23)/C23 -> -0.25375599 | E49: =(E23-D23)/D23 -> 0.18213135 | F49: =(F23-E23)/E23 -> -0.55942948 | G49: =(G23-F23)/F23 -> -0.36319689 | H49: =(H23-G23)/G23 -> 0.13020541 | I49: =(I23-H23)/H23 -> 3.0781825 | J49: =(J23-I23)/I23 -> -0.064023455 | K49: =(K23-J23)/J23 -> -0.14745531 | ... N49: =(N23-M23)/M23 -> 0.20711677
A50: %/ Rev | B50: =B23/'FPT Digital Retail JSC | Income'!C23 -> 0.010608805 | C50: =C23/'FPT Digital Retail JSC | Income'!D23 -> 0.02242891 | D50: =D23/'Revenue breakdown'!B3 -> 0.014383199 | E50: =E23/'Revenue breakdown'!C3 -> 0.015637587 | F50: =F23/'Revenue breakdown'!D3 -> 0.0078163659 | G50: =G23/'Revenue breakdown'!E3 -> 0.0032441488 | H50: =H23/'Revenue breakdown'!F3 -> 0.002734189 | I50: =AVERAGE(D50:H50) -> 0.008763098 | J50: =AVERAGE(E50:I50) -> 0.0076390778 | K50: =AVERAGE(F50:J50) -> 0.0060393759 | L50: =AVERAGE(G50:K50) -> 0.0056839779 | M50: =AVERAGE(H50:L50) -> 0.0061719437 | N50: =AVERAGE(I50:M50) -> 0.0068594946
A51: Property/Plant/Equipment, Total - Gross | B51: 3898 | C51: 9323 | D51: 9344 | E51: 11191 | F51: 14160 | G51: 29396 | H51: 980978
A52: Buildings - Gross | B52: -- | C52: 4620 | D52: 4620 | E52: 4620 | F52: 4620 | G52: 17239 | H52: 943718
A53: Machinery/Equipment - Gross | B53: -- | C53: 4340 | D53: 4362 | E53: 5988 | F53: 7528 | G53: 10053 | H53: 21092
A54: Construction in Progress - Gross | B54: -- | C54: -- | D54: -- | E54: -- | F54: -- | G54: 91 | H54: 1796
A55: Other Property/Plant/Equipment - Gross | B55: 3898 | C55: 363 | D55: 363 | E55: 583 | F55: 2013 | G55: 2013 | H55: 14372
A56: Property/Plant/Equipment, Total - Net | B56: 561 | C56: 5488 | D56: 5154 | E56: 6615 | F56: 8708 | G56: 16438 | H56: 676924
A57: Accumulated Depreciation, Total | B57: -3337 | C57: -3835 | D57: -4190 | E57: -4576 | F57: -5452 | G57: -12958 | H57: -304054
A58: Goodwill, Net | B58: -- | C58: -- | D58: -- | E58: -- | F58: -- | G58: -- | H58: --
A59: Intangibles, Net | B59: 1135 | C59: 40843 | D59: 40438 | E59: 41956 | F59: 41920 | G59: 155606 | H59: 172142
A60: Intangibles - Gross | B60: 4188 | C60: 44482 | D60: 44482 | E60: 46416 | F60: 46876 | G60: 162788 | H60: 183894
A61: Accumulated Intangible Amortization | B61: -3052 | C61: -3639 | D61: -4044 | E61: -4459 | F61: -4956 | G61: -7181 | H61: -11752
A62: Long Term Investments | B62: -- | C62: -- | D62: -- | E62: -- | F62: -- | G62: -- | H62: --
A63: Note Receivable - Long Term | B63: 66086 | C63: 75677 | D63: 84028 | E63: 105270 | F63: 116400 | G63: 136777 | H63: 170162
A64: Other Long Term Assets, Total | B64: 233904 | C64: 239891 | D64: 222781 | E64: 266693 | F64: 260550 | G64: 255316 | H64: 177772
A65: Deferred Charges | B65: 233904 | C65: 239891 | D65: 222781 | E65: 266693 | F65: 257566 | G65: 254448 | H65: 177767
A66: Defered Income Tax - Long Term Asset | B66: -- | C66: -- | D66: -- | E66: -- | F66: 2985 | G66: 868 | H66: 6
A67: Total Assets | B67: 4710400 | C67: 3871228 | D67: 5167669 | E67: 6593773 | F67: 5387578 | G67: 10786069 | H67: 10523797
E68: =E70-D70 -> 581630
A69: Liabilities (VND Millions)
A70: Accounts Payable | B70: 1427548 | C70: 1499029 | D70: 705892 | E70: 1287522 | F70: 1214790 | G70: 2335743 | H70: 2307356 | I70: =I87*'Revenue breakdown'!G3 -> 3203475.5 | J70: =J87*'Revenue breakdown'!H3 -> 3229604.8 | K70: =K87*'Revenue breakdown'!I3 -> 3721366.8 | L70: =L87*'Revenue breakdown'!J3 -> 4083414.3 | M70: =M87*'Revenue breakdown'!K3 -> 4376167.3 | N70: =N87*'Revenue breakdown'!L3 -> 4578795.9
A71: Changes in AP | D71: =D70-C70 -> -793137 | E71: =E70-D70 -> 581630 | F71: =F70-E70 -> -72732 | G71: =G70-F70 -> 1120953 | H71: =H70-G70 -> -28387 | I71: =I70-H70 -> 896119.51 | J71: =J70-I70 -> 26129.336 | K71: =K70-J70 -> 491761.97 | ... N71: =N70-M70 -> 202628.53
A72: Payable/Accrued | B72: -- | C72: -- | D72: -- | E72: -- | F72: -- | G72: -- | H72: --
A73: A/P Growth | C73: =(C57-B57)/B57 -> 0.14923584 | D73: =D86 -> -0.5291005 | E73: =E86 -> 0.82396457 | F73: =F86 -> -0.056489909 | G73: =G86 -> 0.92275455 | H73: =H86 -> -0.012153306 | I73: =I86 -> 0.38837505 | J73: =J86 -> 0.0081565586 | K73: =K86 -> 0.15226692 | ... N73: =N86 -> 0.046302738
A74: %/ Rev | C74: =C57/'FPT Digital Retail JSC | Income'!D10 -> #VALUE! | D74: =D87 -> 0.046141753 | E74: =E87 -> 0.077403216 | F74: =F87 -> 0.082856248 | G74: =G87 -> 0.10383405 | H74: =H87 -> 0.076489134 | I74: =I87 -> 0.083458204 | J74: =J87 -> 0.078363768 | K74: =K87 -> 0.083734104 | ... N74: =N87 -> 0.08199098
A75: Accrued Expenses | B75: 198796 | C75: 247307 | D75: 170569 | E75: 183299 | F75: 238744 | G75: 512496 | H75: 653063 | I75: =I76*'Revenue breakdown'!G3 -> 636292.62 | J75: =J76*'Revenue breakdown'!H3 -> 727921.55 | K75: =K76*'Revenue breakdown'!I3 -> 844010.91 | L75: =L76*'Revenue breakdown'!J3 -> 940674.04 | M75: =M76*'Revenue breakdown'!K3 -> 970874.32 | N75: =N76*'Revenue breakdown'!L3 -> 1023587.5
A76: weighted | D76: =D75/'Revenue breakdown'!B3 -> 0.011149514 | E76: =E75/'Revenue breakdown'!C3 -> 0.011019565 | F76: =F75/'Revenue breakdown'!D3 -> 0.016283829 | G76: =G75/'Revenue breakdown'!E3 -> 0.022782702 | H76: =H75/'Revenue breakdown'!F3 -> 0.021649118 | I76: =AVERAGE(D76:H76) -> 0.016576946 | J76: =AVERAGE(E76:I76) -> 0.017662432 | K76: =AVERAGE(F76:J76) -> 0.018991005 | L76: =AVERAGE(G76:K76) -> 0.019532441 | M76: =AVERAGE(H76:L76) -> 0.018882388 | N76: =AVERAGE(I76:M76) -> 0.018329042
A77: Notes Payable/Short Term Debt | B77: 0 | C77: 0 | D77: 2947272 | E77: 3698036 | F77: 2485948 | G77: 6047406 | H77: 5363331
A78: Current Port. of LT Debt/Capital Leases | B78: 2434624 | C78: 1173003 | D78: -- | E78: -- | F78: -- | G78: -- | H78: --
A79: Other Current liabilities, Total | B79: 134201 | C79: 155435 | D79: 185169 | E79: 139274 | F79: 222966 | G79: 211062 | H79: 150624 | I79: =I80*'Revenue breakdown'!G3 -> 384304.39 | J79: =J80*'Revenue breakdown'!H3 -> 395384.44 | K79: =K80*'Revenue breakdown'!I3 -> 437220.23 | L79: =L80*'Revenue breakdown'!J3 -> 422064.95 | M79: =M80*'Revenue breakdown'!K3 -> 444249.13 | N79: =N80*'Revenue breakdown'!L3 -> 523241.97
A80: weighted | D80: =D79/'Revenue breakdown'!B3 -> 0.012103866 | E80: =E79/'Revenue breakdown'!C3 -> 0.0083728709 | F80: =F79/'Revenue breakdown'!D3 -> 0.015207671 | G80: =G79/'Revenue breakdown'!E3 -> 0.0093826346 | H80: =H79/'Revenue breakdown'!F3 -> 0.0049932041 | I80: =AVERAGE(D80:H80) -> 0.010012049 | J80: =AVERAGE(E80:I80) -> 0.0095936859 | K80: =AVERAGE(F80:J80) -> 0.0098378489 | L80: =AVERAGE(G80:K80) -> 0.0087638845 | M80: =AVERAGE(H80:L80) -> 0.0086401345 | N80: =AVERAGE(I80:M80) -> 0.0093695206
A81: Customer Advances | B81: 34948 | C81: 13232 | D81: 13918 | E81: 19464 | F81: 28401 | G81: 54212 | H81: 35297
A82: Income Taxes Payable | B82: 21509 | C82: 26435 | D82: 24450 | E82: 9108 | F82: 31620 | G82: 71324 | H82: 3120
A83: Other Current Liabilities | B83: 77745 | C83: 115767 | D83: 146802 | E83: 110702 | F83: 162945 | G83: 85527 | H83: 112206
A84: Total Current Liabilities | B84: 4195169 | C84: 3074774 | D84: 4008902 | E84: 5308130 | F84: 4162448 | G84: 9106708 | H84: 8474375
A85: Total Current Liabities (without debt) | C85: =C70+C75+C79 -> 1901771 | D85: =D70+D75+D79 -> 1061630 | E85: =E70+E75+E79 -> 1610095 | F85: =F70+F75+F79 -> 1676500 | G85: =G70+G75+G79 -> 3059301 | H85: =H70+H75+H79 -> 3111043 | I85: =I70+I75+I79 -> 4224072.5 | J85: =J70+J75+J79 -> 4352910.8 | ... N85: =N70+N75+N79 -> 6125625.3
A86: A/P Growth | C86: =(C70-B70)/B70 -> 0.050072572 | D86: =(D70-C70)/C70 -> -0.5291005 | E86: =(E70-D70)/D70 -> 0.82396457 | F86: =(F70-E70)/E70 -> -0.056489909 | G86: =(G70-F70)/F70 -> 0.92275455 | H86: =(H70-G70)/G70 -> -0.012153306 | I86: =(I70-H70)/H70 -> 0.38837505 | J86: =(J70-I70)/I70 -> 0.0081565586 | ... N86: =(N70-M70)/M70 -> 0.046302738
A87: %/ Rev | C87: =C70/'FPT Digital Retail JSC | Income'!D23 -> 0.11402482 | D87: =D70/'FPT Digital Retail JSC | Income'!E23 -> 0.046141753 | E87: =E70/'FPT Digital Retail JSC | Income'!F23 -> 0.077403216 | F87: =F70/'FPT Digital Retail JSC | Income'!G23 -> 0.082856248 | G87: =G70/'FPT Digital Retail JSC | Income'!H23 -> 0.10383405 | H87: =H70/'FPT Digital Retail JSC | Income'!I23 -> 0.076489134 | I87: =AVERAGE(C87:H87) -> 0.083458204 | J87: =AVERAGE(D87:I87) -> 0.078363768 | K87: =AVERAGE(E87:J87) -> 0.083734104 | L87: =AVERAGE(F87:K87) -> 0.084789252 | M87: =AVERAGE(G87:L87) -> 0.08511142 | N87: =AVERAGE(H87:M87) -> 0.08199098
A88: Total Long Term Debt | B88: 0 | C88: 0 | D88: 0 | E88: 0 | F88: 0 | G88: 0 | H88: 0
A89: Total Debt | B89: 2434624 | C89: 1173003 | D89: 2947272 | E89: 3698036 | F89: 2485948 | G89: 6047406 | H89: 5363331
A90: Deferred Income Tax | B90: -- | C90: -- | D90: -- | E90: 6279 | F90: -- | G90: -- | H90: --
A91: Deferred Income Tax - LT Liability | B91: -- | C91: -- | D91: -- | E91: 6279 | F91: -- | G91: -- | H91: --
A92: Minority Interest | B92: -- | C92: -- | D92: 24984 | E92: 5637 | F92: 11403 | G92: 17066 | H92: 41105
A93: Other Liabilities, Total | B93: -- | C93: -- | D93: -- | E93: -- | F93: -- | G93: 87 | H93: 87
A94: Other Long Term Liabilities | B94: -- | C94: -- | D94: -- | E94: -- | F94: -- | G94: 87 | H94: 87
A95: Total Liabilities | B95: 4195169 | C95: 3074774 | D95: 4033886 | E95: 5320047 | F95: 4173851 | G95: 9123860 | H95: 8515566
A96: Working Cap | C96: =C85+C47 -> 5067887 | D96: =D47-D85 -> 2442429 | E96: =E47-E85 -> 2661534 | F96: =F47-F85 -> 695910 | G96: =G47-G85 -> 2348304 | H96: =H47-H85 -> 3976500 | I96: =I47-I85 -> 5108580.1 | J96: =J47-J85 -> 5405237.5 | K96: =K47-K85 -> 5512678 | ... N96: =N47-N85 -> 5602378.8
A97: Changes in WC | D97: =D96-C96 -> -2625458 | E97: =E96-D96 -> 219105 | F97: =F96-E96 -> -1965624 | G97: =G96-F96 -> 1652394 | H97: =H96-G96 -> 1628196 | I97: =I96-H96 -> 1132080.1 | J97: =J96-I96 -> 296657.38 | K97: =K96-J96 -> 107440.52 | ... N97: =N96-M96 -> 287933.35
A98: Shareholders Equity (VND Millions)
A99: Redeemable Preferred Stock, Total | B99: -- | C99: -- | D99: -- | E99: -- | F99: -- | G99: -- | H99: --
A100: Preferred Stock - Non Redeemable, Net | B100: -- | C100: -- | D100: -- | E100: -- | F100: -- | G100: -- | H100: --
A101: Common Stock, Total | B101: 200000 | C101: 400000 | D101: 680000 | E101: 789818 | F101: 789818 | G101: 789818 | H101: 1184725
A102: Common Stock | B102: 200000 | C102: 400000 | D102: 680000 | E102: 789818 | F102: 789818 | G102: 789818 | H102: 1184725
...

Sheet Exhibit 
A1: Exhibit | B1: FA summary
B2: SUMMARY OF FINANCIALS | Q2: Exhibit | R2: Inventory
B3: mil VND | C3: 2020A | D3: 2021A | E3: 2022A | F3: 2023F | G3: 2024F | H3: 2025F | I3: 2026F | J3: 2027F
B4: Revenue | C4: ='Revenue breakdown'!D3 -> 14661417 | D4: ='Revenue breakdown'!E3 -> 22494961 | E4: ='Revenue breakdown'!F3 -> 30165801 | F4: ='Revenue breakdown'!G3 -> 38384189 | G4: ='Revenue breakdown'!H3 -> 41212985 | H4: ='Revenue breakdown'!I3 -> 44442666 | I4: ='Revenue breakdown'!J3 -> 48159575 | J4: ='Revenue breakdown'!K3 -> 51416923
B5: Net income | C5: ='FPT Digital Retail JSC | Income'!G89 -> 24719 | D5: ='FPT Digital Retail JSC | Income'!H89 -> 443732 | E5: ='FPT Digital Retail JSC | Income'!I89 -> 390361 | F5: ='FPT Digital Retail JSC | Income'!J89 -> 536537.71 | G5: ='FPT Digital Retail JSC | Income'!K89 -> 541060.85 | H5: ='FPT Digital Retail JSC | Income'!L89 -> 589088.45 | I5: ='FPT Digital Retail JSC | Income'!M89 -> 762226.14 | J5: ='FPT Digital Retail JSC | Income'!N89 -> 758963
B6: EBIT | C6: ='FPT Digital Retail JSC | Income'!G63 -> 14319 | D6: ='FPT Digital Retail JSC | Income'!H63 -> 546196 | E6: ='FPT Digital Retail JSC | Income'!I63 -> 473968 | F6: ='FPT Digital Retail JSC | Income'!J63 -> 642551.35 | G6: ='FPT Digital Retail JSC | Income'!K63 -> 610868.14 | H6: ='FPT Digital Retail JSC | Income'!L63 -> 644701.16 | I6: ='FPT Digital Retail JSC | Income'!M63 -> 828937 | J6: ='FPT Digital Retail JSC | Income'!N63 -> 812315.18
B7: Net margin | C7: ='FPT Digital Retail JSC | Income'!G94 -> 0.0016859898 | D7: ='FPT Digital Retail JSC | Income'!H94 -> 0.01972584 | E7: ='FPT Digital Retail JSC | Income'!I94 -> 0.012940515 | F7: ='FPT Digital Retail JSC | Income'!J94 -> 0.013978091 | G7: ='FPT Digital Retail JSC | Income'!K94 -> 0.013128407 | H7: ='FPT Digital Retail JSC | Income'!L94 -> 0.013255021 | I7: ='FPT Digital Retail JSC | Income'!M94 -> 0.015827094 | J7: ='FPT Digital Retail JSC | Income'!N94 -> 0.014760957
B8: Inventory Turnover | C8: ='Key financial ratios'!G48 -> 4.8 | D8: ='Key financial ratios'!H48 -> 5.7 | E8: ='Key financial ratios'!I48 -> 4.5 | F8: ='FPT Digital Retail JSC | Income'!J29/'FPT Digital Retail JSC | BS'!I37 -> 4.1432736 | G8: ='FPT Digital Retail JSC | Income'!K29/'FPT Digital Retail JSC | BS'!J37 -> 4.2915273 | H8: ='FPT Digital Retail JSC | Income'!L29/'FPT Digital Retail JSC | BS'!K37 -> 4.2784486 | I8: ='FPT Digital Retail JSC | Income'!M29/'FPT Digital Retail JSC | BS'!L37 -> 4.5450957 | J8: ='FPT Digital Retail JSC | Income'!N29/'FPT Digital Retail JSC | BS'!M37 -> 4.7536243
B9: Debt-to-equity | C9: ='Key financial ratios'!G41 -> 2.0481954 | D9: ='Key financial ratios'!H41 -> 3.6381764 | E9: ='Key financial ratios'!I41 -> 2.6706743
A11: Exhibit | B11: Market snapshot
B12: Market Snapshot
B13: Date | C13: Dec 8th, 2023
B14: Closing Price | C14: 101,800 VND
B15: Market cap | C15: 137,743bn VND
B16: Shares Out. | C16: 136,24m
B17: Free Float | C17: 0.485 | P17: Exhibit | Q17: A/R | X17: A/R days
B18: 52-wk High | C18: 52,640 VND
B19: 52-wk Low | C19: 106,900 VND
B20: P/E | C20: 20,78x
B21: EPS | C21: 2,865.19
A23: Exhibit | B23: Price movement
P37: Exhibit | Q37: A/P
A40: Exhibit | B40: Ownership structure
B42: Ownership Structure | Y42: Exhibit
B43: FPT Corporation | C43: 46.54% | Y43: Revenue | Z43: 2022 | AA43: 2023F
B44: CTBC Investment Co. Ltd | C44: 5.12% | Z44: ='Revenue breakdown'!F3 -> 30165801 | AA44: =Z44*113% -> 34087355
B45: Nguyen Bach Diep | C45: 0.005 | Y45: Net profit before tax | Z45: ='FPT Digital Retail JSC | Income'!I74 -> 485623 | AA45: =Z45*49% -> 237955.27
B46: Principal Asset Management Co., Ltd | C46: 0.0195
B47: Dragon Capital VietFund Management | C47: 0.0187
B48: Yurie Asset Management Inc. | C48: 0.0178
A50: Exhibit | B50: Revenue Structure
P54: Exhibit
A67: Exhibit | B67: Distribution Channels
B68: =2018 -> 2018 | C68: =B68+1 -> 2019 | D68: =C68+1 -> 2020 | E68: =D68+1 -> 2021 | F68: =E68+1 -> 2022
A69: Offline | B69: =100-B70 -> 84 | C69: =100-C70 -> 76.6 | D69: =100-D70 -> 65 | E69: =100-E70 -> 72 | F69: =100-F70 -> 81
A70: Online | B70: 16 | C70: 23.4 | D70: 35 | E70: 28 | F70: 19
A87: Exhibit | B87: Revenue and growth
A111: Exhibit | B111: Segmented revenue growth
A134: Exhibit | B134: Gross Margin peers | H134: Operating Margin | O134: Net Margin | W134: Fixed Asset Turnover | AD134: Inventory Turnover | AK134: Quick Ratio | AR134: Gap between Quick and Current Ratio | AX134: D/E
A137: FRT | B137: 0.13358382 | C137: 0.12691247 | D137: 0.13920905 | E137: 0.14009862 | F137: 0.15591093 | H137: FRT | I137: ='Peers '!B25 -> 0.026328878 | J137: ='Peers '!C25 -> 0.016401566 | K137: ='Peers '!D25 -> 0.00097664503 | L137: ='Peers '!E25 -> 0.024280816 | M137: ='Peers '!F25 -> 0.015712097 | O137: FRT | P137: ='Peers '!B26 -> 0.023 | Q137: ='Peers '!C26 -> 0.012 | R137: ='Peers '!D26 -> 0.001 | S137: ='Peers '!E26 -> 0.02 | T137: ='Peers '!F26 -> 0.013 | W137: FRT | X137: ='Peers '!I30 -> 2875.09 | Y137: ='Peers '!J30 -> 2826.83 | Z137: ='Peers '!K30 -> 1913.67 | AA137: ='Peers '!L30 -> 1789.13 | AB137: ='Peers '!M30 -> 87.01 | AD137: FRT | AE137: ='Peers '!I29 -> 6.3 | AF137: ='Peers '!J29 -> 4.9 | AG137: ='Peers '!K29 -> 4.8 | AH137: ='Peers '!L29 -> 5.7 | AI137: ='Peers '!M29 -> 4.5 | AK137: FRT | AL137: ='Peers '!P31 -> 0.58 | AM137: ='Peers '!Q31 -> 0.53 | AN137: ='Peers '!R31 -> 0.75 | AO137: ='Peers '!S31 -> 0.58 | AP137: ='Peers '!T31 -> 0.34 | AX137: FRT | AY137: ='Peers '!P33 -> 2.5995027 | AZ137: ='Peers '!Q33 -> 2.9033214 | BA137: ='Peers '!R33 -> 2.0481954 | BB137: ='Peers '!S33 -> 3.6381764 | BC137: ='Peers '!T33 -> 2.6706743
A138: MWG | B138: 0.177 | C138: 0.191 | D138: 0.221 | E138: 0.225 | F138: 0.231 | H138: MWG | I138: ='Peers '!B17 -> 0.044 | J138: ='Peers '!C17 -> 0.049 | K138: ='Peers '!D17 -> 0.05 | L138: ='Peers '!E17 -> 0.053 | M138: ='Peers '!F17 -> 0.049 | O138: MWG | P138: ='Peers '!B18 -> 0.033 | Q138: ='Peers '!C18 -> 0.038 | R138: ='Peers '!D18 -> 0.036 | S138: ='Peers '!E18 -> 0.04 | T138: ='Peers '!F18 -> 0.031 | W138: MWG | X138: ='Peers '!I20 -> 24.6 | Y138: ='Peers '!J20 -> 22.64 | Z138: ='Peers '!K20 -> 16.88 | AA138: ='Peers '!L20 -> 14.43 | AB138: ='Peers '!M20 -> 13.74 | AD138: MWG | AE138: ='Peers '!I19 -> 4.8 | AF138: ='Peers '!J19 -> 3.8 | AG138: ='Peers '!K19 -> 3.7 | AH138: ='Peers '!L19 -> 3.9 | AI138: ='Peers '!M19 -> 3.7 | AK138: MWG | AL138: ='Peers '!P19 -> 0.33 | AM138: ='Peers '!Q19 -> 0.33 | AN138: ='Peers '!R19 -> 0.61 | AO138: ='Peers '!S19 -> 0.54 | AP138: ='Peers '!T19 -> 0.73 | AX138: MWG | AY138: ='Peers '!P21 -> 0.78 | AZ138: ='Peers '!Q21 -> 1.17 | BA138: ='Peers '!R21 -> 1.08 | BB138: ='Peers '!S21 -> 1.21 | BC138: ='Peers '!T21 -> 0.69
A139: DGW | B139: 0.062 | C139: 0.065 | D139: 0.064 | E139: 0.072 | F139: 0.075 | H139: DGW | I139: ='Peers '!B13 -> 0.023 | J139: ='Peers '!C13 -> 0.025 | K139: ='Peers '!D13 -> 0.026 | L139: ='Peers '!E13 -> 0.039 | M139: ='Peers '!F13 -> 0.039 | O139: DGW | P139: ='Peers '!B14 -> 0.018 | Q139: ='Peers '!C14 -> 0.019 | R139: ='Peers '!D14 -> 0.021 | S139: ='Peers '!E14 -> 0.031 | T139: ='Peers '!F14 -> 0.031 | W139: DGW | X139: ='Peers '!I15 -> 241.28 | Y139: ='Peers '!J15 -> 398.35 | Z139: ='Peers '!K15 -> 531.3 | AA139: ='Peers '!L15 -> 678.23 | AB139: ='Peers '!M15 -> 660.47 | AD139: DGW | AE139: ='Peers '!I14 -> 5.1 | AF139: ='Peers '!J14 -> 5.7 | AG139: ='Peers '!K14 -> 10.3 | AH139: ='Peers '!L14 -> 10.5 | AI139: ='Peers '!M14 -> 6.6 | AK139: DGW | AL139: ='Peers '!P13 -> 0.55 | AM139: ='Peers '!Q13 -> 0.57 | AN139: ='Peers '!R13 -> 1.07 | AO139: ='Peers '!S13 -> 0.71 | AP139: ='Peers '!T13 -> 0.65 | AX139: DGW | AY139: ='Peers '!P15 -> 1.09 | AZ139: ='Peers '!Q15 -> 0.67 | BA139: ='Peers '!R15 -> 0.54 | BB139: ='Peers '!S15 -> 0.63 | BC139: ='Peers '!T15 -> 0.82
A140: PET | B140: 0.06 | C140: 0.061 | D140: 0.05 | E140: 0.053 | F140: 0.055 | H140: PET | I140: ='Peers '!B21 -> 0.016 | J140: ='Peers '!C21 -> 0.01 | K140: ='Peers '!D21 -> 0.015 | L140: ='Peers '!E21 -> 0.023 | M140: ='Peers '!F21 -> 0.012 | O140: PET | P140: ='Peers '!B22 -> 0.012 | Q140: ='Peers '!C22 -> 0.013 | R140: ='Peers '!D22 -> 0.01 | S140: ='Peers '!E22 -> 0.018 | T140: ='Peers '!F22 -> 0.01 | W140: PET | X140: ='Peers '!I25 -> 67.23 | Y140: ='Peers '!J25 -> 77.62 | Z140: ='Peers '!K25 -> 105.6 | AA140: ='Peers '!L25 -> 139.58 | AB140: ='Peers '!M25 -> 132.04 | AD140: PET | AE140: ='Peers '!I24 -> 11.7 | AF140: ='Peers '!J24 -> 8.8 | AG140: ='Peers '!K24 -> 13.4 | AH140: ='Peers '!L24 -> 14.9 | AI140: ='Peers '!M24 -> 8.6 | AK140: PET | AL140: ='Peers '!P25 -> 0.93 | AM140: ='Peers '!Q25 -> 0.86 | AN140: ='Peers '!R25 -> 0.98 | AO140: ='Peers '!S25 -> 0.9 | AP140: ='Peers '!T25 -> 0.78 | AX140: PET | AY140: ='Peers '!P27 -> 1.28 | AZ140: ='Peers '!Q27 -> 1.01 | BA140: ='Peers '!R27 -> 1.76 | BB140: ='Peers '!S27 -> 2.01 | BC140: ='Peers '!T27 -> 1.91
A141: Peers Median | B141: 0.097791909 | C141: 0.095956237 | D141: 0.10160453 | E141: 0.10604931 | F141: 0.11545546 | H141: Peers Median | I141: ='Peers '!B29 -> 0.024664439 | J141: ='Peers '!C29 -> 0.020700783 | K141: ='Peers '!D29 -> 0.0205 | L141: ='Peers '!E29 -> 0.031640408 | M141: ='Peers '!F29 -> 0.027356049 | O141: Peers Median | P141: ='Peers '!B30 -> 0.0205 | Q141: ='Peers '!C30 -> 0.016 | R141: ='Peers '!D30 -> 0.0155 | S141: ='Peers '!E30 -> 0.0255 | T141: ='Peers '!F30 -> 0.022 | W141: Peers Median | X141: ='Peers '!I35 -> 154.255 | Y141: ='Peers '!J35 -> 237.985 | Z141: ='Peers '!K35 -> 318.45 | AA141: ='Peers '!L35 -> 408.905 | AB141: ='Peers '!M35 -> 109.525 | AD141: Peers Median | AE141: ='Peers '!I34 -> 5.7 | AF141: ='Peers '!J34 -> 5.3 | AG141: ='Peers '!K34 -> 7.55 | AH141: ='Peers '!L34 -> 8.1 | AI141: ='Peers '!M34 -> 5.55 | AK141: Peers Median | AL141: ='Peers '!P37 -> 0.565 | AM141: ='Peers '!Q37 -> 0.55 | AN141: ='Peers '!R37 -> 0.865 | AO141: ='Peers '!S37 -> 0.645 | AP141: ='Peers '!T37 -> 0.69 | AX141: Peers Median | AY141: ='Peers '!P39 -> 1.185 | AZ141: ='Peers '!Q39 -> 1.09 | BA141: ='Peers '!R39 -> 1.42 | BB141: ='Peers '!S39 -> 1.61 | BC141: ='Peers '!T39 -> 1.365
A164: Exhibit | B164: Inventory Turnover vs COGS
L168: Apple | M168: 0.5
L169: Laptop | M169: 0.3
L170: Household Appliances | M170: 0.025
L171: Others | M171: =100%-(SUM(M168:M170)) -> 0.175
A184: Exhibit | B184: GDP Growth
A185: Vietnam | B185: =2020 -> 2020 | C185: =B185+1 -> 2021 | D185: =C185+1 -> 2022 | E185: 2023F
B186: 0.029 | C186: 0.026 | D186: =8% -> 0.08 | E186: =5.7% -> 0.057
A205: Exhibit | B205: Computing and Telephony growth
B206: 2021 | C206: =B206+1 -> 2022 | D206: =C206+1 -> 2023 | E206: =D206+1 -> 2024 | F206: =E206+1 -> 2025 | G206: =F206+1 -> 2026 | H206: =G206+1 -> 2027 | I206: =H206+1 -> 2028
A207: Computing | B207: 4.99 | C207: -3.56 | D207: 1.89 | E207: 0.5 | F207: 4.16 | G207: 3.99 | H207: 3.83 | I207: 3.87
A208: Telephone | B208: 11.14 | C208: -6.62 | D208: 3.1 | E208: -1.76 | F208: 1.35 | G208: 1.33 | H208: 1.3 | I208: 1.35
A229: Exhibit | B229: OTC pharma
A230: Vietnam | B230: -2.13 | C230: 9.2 | D230: 7.57 | E230: 7.71 | F230: 7.38 | G230: 7.34 | H230: 7.13 | I230: 6.65
A250: Exhibit | B250: Vietnam customer brand loyalty
A253: Vietnam | B253: 0.9
A254: India | B254: 0.84
A255: Indonesia | B255: 0.77
A256: China | B256: 0.74
A257: Australia | B257: 0.56
A258: South Korea | B258: 0.55
A259: Japan | B259: 0.27
A279: Exhibit | B279: Engagement
E280: FPT Long Chau | F280: An Khang/ BHX | G280: Pharmacity
D281: Mobile App. Downloads | E281: 19100 | F281: 163 | G281: 1400
D282: Landing page visits | E282: =9.7*1000000 -> 9700000 | F282: =4.7*1000000 -> 4700000 | G282: =2.1*1000000 -> 2100000
A285: Exhibit | B285: Numer of stores - Market share | N285: Number of stores
A287: Long Chau | B287: 1016 | C287: =B287/$B$295 -> 0.37657524
A288: Pharmacity | B288: 937 | C288: =B288/$B$295 -> 0.34729429
A289: An Khang Pharmacy | B289: 524 | C289: =B289/$B$295 -> 0.19421794
A290: Guardian | B290: 109 | C290: =B290/$B$295 -> 0.040400297
A291: Medicare | B291: 85 | C291: =B291/$B$295 -> 0.031504818
A292: SK Pharmacy | B292: 12 | C292: =B292/$B$295 -> 0.0044477391
A293: ECO pharma | B293: 10 | C293: =B293/$B$295 -> 0.0037064492
A294: Matsumoto Kiyoshi | B294: 5 | C294: =B294/$B$295 -> 0.0018532246
A295: Total | B295: 2698
A314: Exhibit | B314: Engagement
B316: FPT Shop | C316: FPT Long Chau | D316: MWG
B317: Tiktok
B318: 771k Followers 44k Likes 9,8M no. of plays 0,72% follow growth | C318: 104k Followers 21k Likes 2,1M no. of plays 19% follow growth | D318: 95k Followers 125 Likes 18k no. of plays 0,42% follow growth
B319: Facebook
B320: 2,6M Followers 2,6M Likes | C320: 1M Followers 949K Likes | D320: 3,9M Followers 3,8M Likes
A322: Exhibit | B322: Interest expenses
A339: Exhibit | B339: Inventory management
E341: 2019 | F341: 2020 | G341: 2021 | H341: 2022
D342: ROA | E342: ='Key financial ratios'!F27 -> 0.047 | F342: ='Key financial ratios'!G27 -> 0.005 | G342: ='Key financial ratios'!H27 -> 0.069 | H342: ='Key financial ratios'!I27 -> 0.046
D343: Inv. Turnover | E343: ='Key financial ratios'!F48 -> 4.9 | F343: ='Key financial ratios'!G48 -> 4.8 | G343: ='Key financial ratios'!H48 -> 5.7 | H343: ='Key financial ratios'!I48 -> 4.5
D344: Avg. Inv. Days | E344: ='Key financial ratios'!F49 -> 74.2 | F344: ='Key financial ratios'!G49 -> 75.6 | G344: ='Key financial ratios'!H49 -> 63.9 | H344: ='Key financial ratios'!I49 -> 82
A346: Exhibit | B346: Inventry growth
A365: Exhibit | B365: Purchase of Fixed Asset
A366: 74 | B366: 3816 | C366: 3429 | D366: 2088 | E366: 518167
A385: Exhibit | B385: ROE
C387: Industry Median | D387: 2018 | E387: 2019 | F387: 2020 | G387: 2021 | H387: 2022
B388: Net Margin | C388: 0.07 | D388: 0.0227 | E388: 0.0128 | F388: 0.0017 | G388: 0.0197 | H388: 0.0129
B389: Asset Turnover | C389: 1.44 | D389: 3.39 | E389: 2.83 | F389: 2.45 | G389: 2.78 | H389: 2.83
B390: Leverage | C390: 2.3 | D390: 4.56 | E390: 5.18 | F390: 4.44 | G390: 6.49 | H390: 5.24
...

Sheet Revenue breakdown
B1: Historical | G1: Forecast
A2: FPT Revenue Breakdown (mil VND) | B2: 2018 | C2: 2019 | D2: 2020 | E2: 2021 | F2: 2022 | G2: 2023F | H2: 2024F | I2: 2025F | J2: 2026F | K2: 2027F | L2: 2028F
A3: Total Revenue | B3: ='FPT Digital Retail JSC | Income'!E23 -> 15298335 | C3: ='FPT Digital Retail JSC | Income'!F23 -> 16633960 | D3: ='FPT Digital Retail JSC | Income'!G23 -> 14661417 | E3: ='FPT Digital Retail JSC | Income'!H23 -> 22494961 | F3: ='FPT Digital Retail JSC | Income'!I23 -> 30165801 | G3: =G6+G12 -> 38384189 | H3: =H6+H12 -> 41212985 | I3: =I6+I12 -> 44442666 | J3: =J6+J12 -> 48159575 | K3: =K6+K12 -> 51416923 | L3: =L6+L12 -> 55845117
A4: %growth | B4: =('FPT Digital Retail JSC | Income'!E23-'FPT Digital Retail JSC | Income'!D23)/'FPT Digital Retail JSC | Income'!D23 -> 0.16367988 | C4: =(C3-B3)/B3 -> 0.087305252 | D4: =(D3-C3)/C3 -> -0.11858529 | E4: =(E3-D3)/D3 -> 0.53429651 | F4: =(F3-E3)/E3 -> 0.34100259 | G4: =(G3-F3)/F3 -> 0.27244058 | H4: =(H3-G3)/G3 -> 0.073696911 | I4: =(I3-H3)/H3 -> 0.078365603 | J4: =(J3-I3)/I3 -> 0.083633797 | ... L4: =(L3-K3)/K3 -> 0.086123264
A6: ICT | B6: 15298357 | C6: 16123176 | D6: 13475727 | E6: 18558083 | F6: 20688829 | G6: =G11*G9 -> 23092195 | H6: =H11*H9 -> 24063013 | I6: =I11*I9 -> 25208972 | J6: =J11*J9 -> 26588987 | K6: =K11*K9 -> 27225509 | L6: =L11*L9 -> 28714446
A7: %growth | C7: =(C6-B6)/B6 -> 0.053915528 | D7: =(D6-C6)/C6 -> -0.16420146 | E7: =(E6-D6)/D6 -> 0.37714893 | F7: =(F6-E6)/E6 -> 0.11481498 | G7: =(G6-F6)/F6 -> 0.11616731 | H7: =(H6-G6)/G6 -> 0.042040994 | I7: =(I6-H6)/H6 -> 0.047623248 | J7: =(J6-I6)/I6 -> 0.054743013 | ... L7: =(L6-K6)/K6 -> 0.054689022
A8: %weight | B8: =100%-B15 -> 0.97744853 | C8: =C6/C3 -> 0.9692927 | D8: =D6/D3 -> 0.91912855 | E8: =E6/E3 -> 0.82498845 | F8: =F6/F3 -> 0.68583722 | G8: =G6/G3 -> 0.60160694 | H8: =H6/H3 -> 0.5838697 | I8: =I6/I3 -> 0.56722457 | J8: =J6/J3 -> 0.55210179 | ... L8: =L6/L3 -> 0.51418007
A9: Number of stores (x) | B9: 533 | C9: 593 | D9: 595 | E9: 647 | F9: 786 | G9: =F9*(1+G10) -> 864.58637 | H9: =G9+50 -> 914.58637 | I9: =H9+50 -> 964.58637 | J9: =I9*(1+J10) -> 990.95311 | K9: =J9*(1+K10) -> 1028.8756 | L9: =K9*(1+L10) -> 1083.9987
A10: %store growth | C10: =(C9-B9)/B9 -> 0.11257036 | D10: =(D9-C9)/C9 -> 0.0033726813 | E10: =(E9-D9)/D9 -> 0.087394958 | F10: =(F9-E9)/E9 -> 0.21483771 | G10: =MEDIAN(C10:F10) -> 0.099982657 | H10: =H9/G9-1 -> 0.057831122 | I10: =I9/H9-1 -> 0.054669522 | J10: =I10*50% -> 0.027334761 | K10: =J10*140% -> 0.038268666 | L10: =K10*140% -> 0.053576132
A11: Rev per store | B11: =B6/B9 -> 28702.358 | C11: =C6/C9 -> 27189.167 | D11: =D6/D9 -> 22648.281 | E11: =E6/E9 -> 28683.281 | F11: =F6/F9 -> 26321.665 | G11: =AVERAGE(B11:F11) -> 26708.951 | H11: =AVERAGE(C11:G11) -> 26310.269 | I11: =AVERAGE(D11:H11) -> 26134.489 | J11: =AVERAGE(E11:I11) -> 26831.731 | K11: =AVERAGE(F11:J11) -> 26461.421 | L11: =AVERAGE(G11:K11) -> 26489.372
A12: Pharmacy | B12: 345000 | C12: 510783 | D12: 1190840 | E12: 3977188 | F12: 9595942 | G12: =G16*G18 -> 15291995 | H12: =H16*H18 -> 17149972 | I12: =I16*I18 -> 19233694 | J12: =J16*J18 -> 21570588 | K12: =K16*K18 -> 24191414 | L12: =L16*L18 -> 27130671
H13: =G12*(1+12.15%) -> 17149972 | I13: =H12*(1+12.15%) -> 19233694 | J13: =I12*(1+12.15%) -> 21570588 | K13: =J12*(1+12.15%) -> 24191414 | L13: =K12*(1+12.15%) -> 27130671
A14: %growth | C14: =(C12-B12)/B12 -> 0.48053043 | D14: =(D12-C12)/C12 -> 1.331401 | E14: =(E12-D12)/D12 -> 2.3398173 | F14: =(F12-E12)/E12 -> 1.4127454 | G14: =(G12-F12)/F12 -> 0.59358974 | H14: =(H12-G12)/G12 -> 0.1215 | I14: =(I12-H12)/H12 -> 0.1215 | J14: =(J12-I12)/I12 -> 0.1215 | ... L14: =(L12-K12)/K12 -> 0.1215
A15: %weight | B15: =B12/B3 -> 0.022551474 | C15: =C12/C3 -> 0.03070724 | D15: =D12/D3 -> 0.081222709 | E15: =E12/E3 -> 0.17680351 | F15: =F12/F3 -> 0.31810665 | G15: =G12/G3 -> 0.39839306 | H15: =H12/H3 -> 0.4161303 | I15: =I12/I3 -> 0.43277543 | ... L15: =L12/L3 -> 0.48581993
A16: Number of stores (x) | B16: 30 | C16: 68 | D16: 200 | E16: 400 | F16: 1000 | G16: =1243*100/78 -> 1593.5897 | H16: =H13/H18 -> 1902.0102 | I16: =I13/I18 -> 2235.7251 | J16: =J13/J18 -> 2455.4488 | K16: =K13/K18 -> 2613.438 | L16: =L13/L18 -> 2967.6485
A17: %store growth | C17: =(C16-B16)/B16 -> 1.2666667 | D17: =(D16-C16)/C16 -> 1.9411765 | E17: =(E16-D16)/D16 -> 1 | F17: =(F16-E16)/E16 -> 1.5 | G17: =(G16-F16)/F16 -> 0.59358974 | H17: =(H16-G16)/G16 -> 0.19353817 | I17: =(I16-H16)/H16 -> 0.17545382 | J17: =(J16-I16)/I16 -> 0.098278493 | ... L17: =(L16-K16)/K16 -> 0.13553431
A18: Rev per store | B18: =B12/B16 -> 11500 | C18: =C12/C16 -> 7511.5147 | D18: =D12/D16 -> 5954.2 | E18: =E12/E16 -> 9942.97 | F18: =F12/F16 -> 9595.942 | G18: =F18 -> 9595.942 | H18: =AVERAGE(B18:G18) -> 9016.7615 | I18: =AVERAGE(C18:H18) -> 8602.8884 | J18: =AVERAGE(D18:I18) -> 8784.784 | K18: =AVERAGE(E18:J18) -> 9256.548 | L18: =AVERAGE(F18:K18) -> 9142.1443
A19: Total weight | B19: =B8+B15 -> 1 | C19: =C8+C15 -> 0.99999994 | D19: =D8+D15 -> 1.0003513 | E19: =E8+E15 -> 1.001792 | F19: =F8+F15 -> 1.0039439 | G19: =G8+G15 -> 1 | H19: =H8+H15 -> 1 | I19: =I8+I15 -> 1 | ... L19: =L8+L15 -> 1
A21: Other (F.studio) | E21: 1247259 | F21: 6980526
A22: %growth
A23: Total no. Of stores | C23: s
A24: OPERATING RATIO & ASSUMPTIONS
A25: D&A Expense | B25: ='FPT Digital Retail JSC | Income'!E49/'FPT Digital Retail JSC | Income'!E23 -> 5.1051307e-05 | C25: ='FPT Digital Retail JSC | Income'!F49/'FPT Digital Retail JSC | Income'!F23 -> 5.0318746e-05 | D25: ='FPT Digital Retail JSC | Income'!G49/'FPT Digital Retail JSC | Income'!G23 -> 9.3578949e-05 | E25: ='FPT Digital Retail JSC | Income'!H49/'FPT Digital Retail JSC | Income'!H23 -> 0.00016941572 | F25: ='FPT Digital Retail JSC | Income'!I49/'FPT Digital Retail JSC | Income'!I23 -> 0.003821745 | G25: 0.003821745 | H25: 0.003821745 | I25: 0.003821745 | J25: 0.003821745 | K25: 0.003821745 | L25: 0.003821745
A26: Total no. Of stores | B26: =B9+B16 -> 563 | C26: =C9+C16 -> 661 | D26: =D9+D16 -> 795 | E26: =E9+E16 -> 1047 | F26: =F9+F16 -> 1786 | G26: =G9+G16 -> 2458.1761 | H26: =H9+H16 -> 2816.5966 | I26: =I9+I16 -> 3200.3115 | ... L26: =L9+L16 -> 4051.6472
A27: FPT Shop weight | B27: =B9/B26 -> 0.94671403 | C27: =C9/C26 -> 0.89712557 | D27: =D9/D26 -> 0.74842767 | E27: =E9/E26 -> 0.61795606 | F27: =F9/F26 -> 0.44008959 | G27: =G9/G26 -> 0.35171864 | H27: =H9/H26 -> 0.3247133 | I27: =I9/I26 -> 0.3014039 | ... L27: =L9/L26 -> 0.26754519
A28: Long Chau weight | B28: =B16/B26 -> 0.053285968 | C28: =C16/C26 -> 0.10287443 | D28: =D16/D26 -> 0.25157233 | E28: =E16/E26 -> 0.38204394 | F28: =F16/F26 -> 0.55991041 | G28: =G16/G26 -> 0.64828136 | H28: =H16/H26 -> 0.6752867 | I28: =I16/I26 -> 0.6985961 | ... L28: =L16/L26 -> 0.73245481
A33: FPT Shop | D33: 70.056838 | E33: 3423.4312 | F33: 3423.4312 | G33: 2566.3585 | H33: 1290.2923 | I33: 228039.9 | J33: 53109.743 | K33: 25737.689 | L33: 30380.883 | M33: 22557.942 | N33: 55652.743
A34: Long Chau | D34: 3.9431616 | E34: 392.56884 | F34: 392.56884 | G34: 862.64151 | H34: 797.70774 | I34: 290127.1 | J34: 63293.359 | K34: 24774.279 | L34: 27784.354 | M34: 45804.732 | N34: 59791.428

Sheet ROE Dupont
A1: Dupont Analysis
A2: ROE | B2: 2018 | C2: 2019 | D2: 2020 | E2: 2021 | F2: 2022
A3: Net Margin | B3: ='FPT Digital Retail JSC | Income'!E89/'FPT Digital Retail JSC | Income'!E23 -> 0.022732082 | C3: ='FPT Digital Retail JSC | Income'!F89/'FPT Digital Retail JSC | Income'!F23 -> 0.012806031 | D3: ='FPT Digital Retail JSC | Income'!G89/'FPT Digital Retail JSC | Income'!G23 -> 0.0016859898 | E3: ='FPT Digital Retail JSC | Income'!H89/'FPT Digital Retail JSC | Income'!H23 -> 0.01972584 | F3: ='FPT Digital Retail JSC | Income'!I89/'FPT Digital Retail JSC | Income'!I23 -> 0.012940515 | G3: Decrease profitability
A4: Asset Turnover | B4: ='Key financial ratios'!E25 -> 3.39 | C4: ='Key financial ratios'!F25 -> 2.83 | D4: ='Key financial ratios'!G25 -> 2.45 | E4: ='Key financial ratios'!H25 -> 2.78 | F4: ='Key financial ratios'!I25 -> 2.83
A5: A/E | B5: ='FPT Digital Retail JSC | BS'!D71/'FPT Digital Retail JSC | BS'!D111 -> 4.5578995 | C5: ='FPT Digital Retail JSC | BS'!E71/'FPT Digital Retail JSC | BS'!E111 -> 5.1767594 | D5: ='FPT Digital Retail JSC | BS'!F71/'FPT Digital Retail JSC | BS'!F111 -> 4.438875 | E5: ='FPT Digital Retail JSC | BS'!G71/'FPT Digital Retail JSC | BS'!G111 -> 6.4890008 | F5: ='FPT Digital Retail JSC | BS'!H71/'FPT Digital Retail JSC | BS'!H111 -> 5.2403319 | G5: Increase leverage
B6: =B3*B4*B5 -> 0.35123974 | C6: =C3*C4*C5 -> 0.18761128 | D6: =D3*D4*D5 -> 0.01833555 | E6: =E3*E4*E5 -> 0.35584275 | F6: =F3*F4*F5 -> 0.19190964
A7: ROE | B7: 0.36 | C7: 0.177 | D7: 0.02 | E7: 0.309 | F7: 0.213
A11: MWG
A12: ROE | B12: 2018 | C12: 2019 | D12: 2020 | E12: 2021 | F12: 2022
A13: Net Margin | B13: ='Peers '!B18 -> 0.033 | C13: ='Peers '!C18 -> 0.038 | D13: ='Peers '!D18 -> 0.036 | E13: ='Peers '!E18 -> 0.04 | F13: ='Peers '!F18 -> 0.031 | G13: giam profitability
A14: Asset Turnover | B14: 3.4 | C14: 2.93 | D14: 2.47 | E14: 2.26 | F14: 2.25 | G14: use assets less effectively
A15: A/E | B15: ='Peers '!P20 -> 3.13 | C15: ='Peers '!Q20 -> 3.44 | D15: ='Peers '!R20 -> 2.98 | E15: ='Peers '!S20 -> 3.09 | F15: ='Peers '!T20 -> 2.33 | G15: Reduce Assets
B16: =B15*B14*B13 -> 0.351186 | C16: =C15*C14*C13 -> 0.3830096 | D16: =D15*D14*D13 -> 0.2649816 | E16: =E15*E14*E13 -> 0.279336 | F16: =F15*F14*F13 -> 0.1625175
A18: DGW
A19: ROE | B19: 2018 | C19: 2019 | D19: 2020 | E19: 2021 | F19: 2022
A20: Net Margin | B20: ='Peers '!B14 -> 0.018 | C20: ='Peers '!C14 -> 0.019 | D20: ='Peers '!D14 -> 0.021 | E20: ='Peers '!E14 -> 0.031 | F20: ='Peers '!F14 -> 0.031 | G20: tang profitability
A21: Asset Turnover | B21: 3.11 | C21: 3.67 | D21: 4.58 | E21: 4.35 | F21: 3.42 | G21: use assets more effectively
A22: A/E | B22: ='Peers '!P14 -> 2.9 | C22: ='Peers '!Q14 -> 2.61 | D22: ='Peers '!R14 -> 2.65 | E22: ='Peers '!S14 -> 3.68 | F22: ='Peers '!T14 -> 2.65 | G22: slight adjust in capital stucture => reduce Assets
B23: =B22*B21*B20 -> 0.162342 | C23: =C22*C21*C20 -> 0.1819953 | D23: =D22*D21*D20 -> 0.254877 | E23: =E22*E21*E20 -> 0.496248 | F23: =F22*F21*F20 -> 0.280953
A25: PET
A26: ROE | B26: 2018 | C26: 2019 | D26: 2020 | E26: 2021 | F26: 2022
A27: Net Margin | B27: ='Peers '!B22 -> 0.012 | C27: ='Peers '!C22 -> 0.013 | D27: ='Peers '!D22 -> 0.01 | E27: ='Peers '!E22 -> 0.018 | F27: ='Peers '!F22 -> 0.01
A28: Asset Turnover | B28: 1.89 | C28: 1.9 | D28: 2.38 | E28: 2.38 | F28: 2
A29: A/E | B29: ='Peers '!P26 -> 3.77 | C29: ='Peers '!Q26 -> 3.29 | D29: ='Peers '!R26 -> 4.1 | E29: ='Peers '!S26 -> 4.68 | F29: ='Peers '!T26 -> 4.67 | G29: increae leverage
B30: =B29*B28*B27 -> 0.0855036 | C30: =C29*C28*C27 -> 0.081263 | D30: =D29*D28*D27 -> 0.09758 | E30: =E29*E28*E27 -> 0.2004912 | F30: =F29*F28*F27 -> 0.0934

Sheet Key financial ratios
A1: FPT Digital Retail JSC | Ratios - Key Metrics 11-Oct-2023 12:01
A3: Ratios - Key Metrics
A4: Industry - Annual Standardised in Millions of Vietnamese Dong
B5: Industry Median | C5: 2016 | D5: 2017 | E5: 2018 | F5: 2019 | G5: 2020 | H5: 2021 | I5: 2022
A6: Earnings Quality Score | B6: 69 | C6: N/A | D6: N/A | E6: 2 | F6: 17 | G6: 89 | H6: 10 | I6: 12
A7: Retail
A8: Same Store Sales | B8: - | C8: - | D8: - | E8: - | F8: - | G8: - | H8: - | I8: -
A9: Inventory per Square Ft (VND) | B9: - | C9: - | D9: - | E9: - | F9: - | G9: - | H9: - | I9: -
A10: Net Sales per Retail Square Ft (VND) | B10: - | C10: - | D10: - | E10: - | F10: - | G10: - | H10: - | I10: -
A11: Operating Expense per Square Ft (VND) | B11: - | C11: - | D11: - | E11: - | F11: - | G11: - | H11: - | I11: -
A12: # Stores | B12: - | C12: - | D12: 473 | E12: 533 | F12: 663 | G12: - | H12: - | I12: -
A13: Rent Exp as % Retail Sales | B13: - | C13: - | D13: - | E13: - | F13: - | G13: - | H13: - | I13: -
A14: Rent Exp per Square Ft (VND) | B14: - | C14: - | D14: - | E14: - | F14: - | G14: - | H14: - | I14: -
A15: Customer Visits | B15: - | C15: - | D15: - | E15: 360325253 | F15: - | G15: - | H15: - | I15: -
A16: Merchandise Margins | B16: - | C16: - | D16: - | E16: - | F16: - | G16: - | H16: - | I16: -
A17: Profitability
A18: Gross Margin | B18: 22.7% | C18: 0.13 | D18: 0.138 | E18: ='FPT Digital Retail JSC | Income'!E32/'FPT Digital Retail JSC | Income'!E23 -> 0.13358382 | F18: ='FPT Digital Retail JSC | Income'!F32/'FPT Digital Retail JSC | Income'!F23 -> 0.12691247 | G18: ='FPT Digital Retail JSC | Income'!G32/'FPT Digital Retail JSC | Income'!G23 -> 0.13920905 | H18: ='FPT Digital Retail JSC | Income'!H32/'FPT Digital Retail JSC | Income'!H23 -> 0.14009862 | I18: ='FPT Digital Retail JSC | Income'!I32/'FPT Digital Retail JSC | Income'!I23 -> 0.15591093 | J18: low compared to industry median
A19: EBITDA Margin | B19: 12.4% | C19: 0.023 | D19: 0.029 | E19: ='FPT Digital Retail JSC | Income'!E197/'FPT Digital Retail JSC | Income'!E23 -> 0.03140126 | F19: ='FPT Digital Retail JSC | Income'!F197/'FPT Digital Retail JSC | Income'!F23 -> 0.02148382 | G19: ='FPT Digital Retail JSC | Income'!G197/'FPT Digital Retail JSC | Income'!G23 -> 0.0062607864 | H19: ='FPT Digital Retail JSC | Income'!H197/'FPT Digital Retail JSC | Income'!H23 -> 0.022866543 | I19: ='FPT Digital Retail JSC | Income'!I197/'FPT Digital Retail JSC | Income'!I23 -> 0.022914227
A20: Operating Margin | B20: 8.2% | C20: 0.021 | D20: 0.025 | E20: ='FPT Digital Retail JSC | Income'!E63/'FPT Digital Retail JSC | Income'!E23 -> 0.026328878 | F20: ='FPT Digital Retail JSC | Income'!F63/'FPT Digital Retail JSC | Income'!F23 -> 0.016401566 | G20: ='FPT Digital Retail JSC | Income'!G63/'FPT Digital Retail JSC | Income'!G23 -> 0.00097664503 | H20: ='FPT Digital Retail JSC | Income'!H63/'FPT Digital Retail JSC | Income'!H23 -> 0.024280816 | I20: ='FPT Digital Retail JSC | Income'!I63/'FPT Digital Retail JSC | Income'!I23 -> 0.015712097
A21: Pretax Margin | B21: 7.6% | C21: 0.024 | D21: 0.028 | E21: 0.028 | F21: 0.017 | G21: 0.002 | H21: 0.025 | I21: 0.016
A22: Effective Tax Rate | B22: 20.3% | C22: 0.2 | D22: 0.202 | E22: 0.2 | F22: 0.267 | G22: 0.641 | H22: 0.199 | I22: 0.18
A23: Net Margin | B23: 7.0% | C23: 0.019 | D23: 0.022 | E23: 0.023 | F23: 0.012 | G23: 0.001 | H23: 0.02 | I23: 0.013
A24: DuPont/Earning Power
A25: Asset Turnover | B25: 1.44 | C25: - | D25: 3.06 | E25: 3.39 | F25: 2.83 | G25: 2.45 | H25: 2.78 | I25: 2.83
A26: x Pretax Margin | B26: 7.6% | C26: 0.024 | D26: 0.028 | E26: 0.028 | F26: 0.017 | G26: 0.002 | H26: 0.025 | I26: w
A27: Pretax ROA | B27: 8.0% | C27: - | D27: 0.085 | E27: 0.096 | F27: 0.047 | G27: 0.005 | H27: 0.069 | I27: 0.046
A28: x Leverage (Assets/Equity) | B28: 2.30 | C28: 9.14 | D28: 4.86 | E28: 4.56 | F28: 5.18 | G28: 4.44 | H28: 6.49 | I28: 5.24
A29: Pretax ROE | B29: 17.8% | C29: - | D29: 0.554 | E29: 0.45 | F29: 0.231 | G29: 0.023 | H29: 0.385 | I29: 0.265
A30: x Tax Complement | B30: 0.80 | C30: 0.8 | D30: 0.8 | E30: 0.8 | F30: 0.77 | G30: 0.87 | H30: 0.8 | I30: 0.8
A31: ROE | B31: 13.7% | C31: - | D31: 0.442 | E31: 0.36 | F31: 0.177 | G31: 0.02 | H31: 0.309 | I31: 0.213 | J31: High => why? => Solvency the highest => Be cautious in the future as the margin or retails is low while the leverage is high due to high multiplier
A32: x Earnings Retention | B32: 0.55 | C32: 1 | D32: 1 | E32: 0.81 | F32: 0.64 | G32: -2.76 | H32: 0.82 | I32: 0.86
A33: Reinvestment Rate | B33: 3.4% | C33: - | D33: 0.429 | E33: 0.283 | F33: 0.109 | G33: -0.047 | H33: 0.254 | I33: 0.182 | J33: not paying the cash out => bigger plan?
A34: Liquidity
A35: Quick Ratio | B35: 1.00 | C35: 0.59 | D35: 0.58 | E35: 0.58 | F35: 0.53 | G35: 0.75 | H35: 0.58 | I35: 0.34 | J35: below industry average
A36: Current Ratio | B36: 1.66 | C36: 1.05 | D36: 1.14 | E36: 1.2 | F36: 1.16 | G36: 1.19 | H36: 1.12 | I36: 1.1
A37: Times Interest Earned | B37: 11.2 | C37: 3.3 | D37: 4.8 | E37: 5 | F37: 2.6 | G37: 0.8 | H37: 3.9 | I37: 2.5
A38: Cash Cycle (Days) | B38: 71.0 | C38: - | D38: 38.2 | E38: 53.6 | F38: 74.7 | G38: 72.2 | H38: 58.5 | I38: 64.9
A39: Leverage
A40: Assets/Equity | B40: 2.30 | C40: 9.14 | D40: 4.86 | E40: ='FPT Digital Retail JSC | BS'!D71/'FPT Digital Retail JSC | BS'!D111 -> 4.5578995 | F40: ='FPT Digital Retail JSC | BS'!E71/'FPT Digital Retail JSC | BS'!E111 -> 5.1767594 | G40: ='FPT Digital Retail JSC | BS'!F71/'FPT Digital Retail JSC | BS'!F111 -> 4.438875 | H40: ='FPT Digital Retail JSC | BS'!G71/'FPT Digital Retail JSC | BS'!G111 -> 6.4890008 | I40: ='FPT Digital Retail JSC | BS'!H71/'FPT Digital Retail JSC | BS'!H111 -> 5.2403319 | J40: high compared to industry median
A41: Debt/Equity | B41: 0.32 | C41: 4.73 | D41: 1.47 | E41: ='FPT Digital Retail JSC | BS'!D91/'FPT Digital Retail JSC | BS'!D111 -> 2.5995027 | F41: ='FPT Digital Retail JSC | BS'!E91/'FPT Digital Retail JSC | BS'!E111 -> 2.9033214 | G41: ='FPT Digital Retail JSC | BS'!F91/'FPT Digital Retail JSC | BS'!F111 -> 2.0481954 | H41: ='FPT Digital Retail JSC | BS'!G91/'FPT Digital Retail JSC | BS'!G111 -> 3.6381764 | I41: ='FPT Digital Retail JSC | BS'!H91/'FPT Digital Retail JSC | BS'!H111 -> 2.6706743 | J41: high debt | K41: =AVERAGE(E41:I41) -> 2.7719741
A42: % LT Debt to Total Capital | B42: 12.4% | C42: 0 | D42: 0 | E42: 0 | F42: 0 | G42: 0 | H42: 0 | I42: 0
A43: (Total Debt - Cash) / EBITDA | B43: 0.51 | C43: - | D43: 1.98 | E43: 2.63 | F43: 6.06 | G43: 18.14 | H43: 4 | I43: 4.79
A44: Operating
A45: A/R Turnover | B45: 13.9 | C45: - | D45: 14 | E45: 14.3 | F45: 14.3 | G45: 11.1 | H45: 13 | I45: 22.5
A46: Avg. A/R Days | B46: 26.6 | C46: - | D46: 26.2 | E46: 25.7 | F46: 25.6 | G46: 33 | H46: 28.2 | I46: 16.3
F47: =F46-E46 -> -0.1 | G47: =G46-F46 -> 7.4 | H47: =H46-G46 -> -4.8 | I47: =I46-H46 -> -11.9
A48: Inv Turnover | B48: 5.3 | C48: - | D48: 6.2 | E48: 6.3 | F48: 4.9 | G48: 4.8 | H48: 5.7 | I48: 4.5
A49: Avg. Inventory Days | B49: 70.5 | C49: - | D49: 59.3 | E49: 58.4 | F49: 74.2 | G49: 75.6 | H49: 63.9 | I49: 82
A50: Avg. A/P Days | B50: 38.6 | C50: - | D50: 47.3 | E50: 30.4 | F50: 25.1 | G50: 36.3 | H50: 33.6 | I50: 33.4
A51: Fixed Asset Turnover | B51: 5.01 | C51: - | D51: 4346.55 | E51: 2875.09 | F51: 2826.83 | G51: 1913.67 | H51: 1789.13 | I51: 87.01
A52: WC / Sales Growth | B52: (0.5%) | C52: - | D52: - | E52: 0.016 | F52: 0.01 | G52: 0.006 | H52: -0.014 | I52: -0.01
A53: Bad Debt Allowance (% of A/R) | B53: 1.6% | C53: 0.005 | D53: 0.011 | E53: 0.016 | F53: 0.028 | G53: 0.041 | H53: 0.004 | I53: 0.011 | J53: FRT is trying to get money back
A54: ROIC | B54: - | C54: - | D54: 0.442 | E54: 0.36 | F54: 0.169 | G54: 0.008 | H54: 0.309 | I54: 0.217
A55: Revenue per Employee (VND) | B55: - | C55: - | D55: VND2,352,843,840.0 | E55: VND2,646,541,746.5 | F55: VND2,580,909,192.7 | G55: VND2,042,406,774.7 | H55: VND2,615,541,120.6 | I55: VND2,360,483,646.2
A57: AP | E57: ='FPT Digital Retail JSC | Income'!E28/'FPT Digital Retail JSC | BS'!D74 -> 18.77727 | F57: ='FPT Digital Retail JSC | Income'!F28/'FPT Digital Retail JSC | BS'!E74 -> 11.279732 | G57: ='FPT Digital Retail JSC | Income'!G28/'FPT Digital Retail JSC | BS'!F74 -> 10.388968 | H57: ='FPT Digital Retail JSC | Income'!H28/'FPT Digital Retail JSC | BS'!G74 -> 8.2814967 | I57: ='FPT Digital Retail JSC | Income'!I28/'FPT Digital Retail JSC | BS'!H74 -> 11.035412

Sheet Model 
A1: FY | B1: 2023 | C1: 2024 | D1: 2025 | E1: 2026 | F1: 2027 | G1: 2028
A2: VND (VND millions)
A3: Net Income | B3: ='FPT Digital Retail JSC | Income'!J89 -> 536537.71 | C3: ='FPT Digital Retail JSC | Income'!K89 -> 541060.85 | D3: ='FPT Digital Retail JSC | Income'!L89 -> 589088.45 | E3: ='FPT Digital Retail JSC | Income'!M89 -> 762226.14 | F3: ='FPT Digital Retail JSC | Income'!N89 -> 758963 | G3: ='FPT Digital Retail JSC | Income'!O89 -> 860684.7
A4: Depreciation Expense | B4: ='Revenue breakdown'!G25*'Revenue breakdown'!G3 -> 146694.58 | C4: ='Revenue breakdown'!H25*'Revenue breakdown'!H3 -> 157505.52 | D4: ='Revenue breakdown'!I25*'Revenue breakdown'!I3 -> 169848.54 | E4: ='Revenue breakdown'!J25*'Revenue breakdown'!J3 -> 184053.62 | F4: ='Revenue breakdown'!K25*'Revenue breakdown'!K3 -> 196502.37 | G4: ='Revenue breakdown'!L25*'Revenue breakdown'!L3 -> 213425.8
A5: Capital Expenditures (negative numbers in the statement means cash outflow) | B5: ='FPT Digital Retail JSC | Cash F'!J47 -> -359049.1 | C5: ='FPT Digital Retail JSC | Cash F'!K47 -> -50511.968 | D5: ='FPT Digital Retail JSC | Cash F'!L47 -> -58165.237 | E5: ='FPT Digital Retail JSC | Cash F'!M47 -> -77160.293 | F5: ='FPT Digital Retail JSC | Cash F'!N47 -> -68362.675 | G5: ='FPT Digital Retail JSC | Cash F'!O47 -> -115444.17 | H5: expected => due to scaling and expanding long chau but not too hype due to the slow down in expansion of ICT
A6: Change in Working Capital (negative numbers in the statement means cash outflow) | B6: =-'FPT Digital Retail JSC | BS'!I99 -> -1132080.1 | C6: =-'FPT Digital Retail JSC | BS'!J99 -> -296657.38 | D6: =-'FPT Digital Retail JSC | BS'!K99 -> -107440.52 | E6: =-'FPT Digital Retail JSC | BS'!L99 -> 143856.05 | F6: =-'FPT Digital Retail JSC | BS'!M99 -> 54376.466 | G6: =-'FPT Digital Retail JSC | BS'!N99 -> -287933.35
A7: Net Borrowing | B7: ='FPT Digital Retail JSC | Cash F'!J73 -> 3722309.3 | C7: ='FPT Digital Retail JSC | Cash F'!K73 -> 1105503.7 | D7: ='FPT Digital Retail JSC | Cash F'!L73 -> 1284334.6 | E7: ='FPT Digital Retail JSC | Cash F'!M73 -> 1375490.7 | F7: ='FPT Digital Retail JSC | Cash F'!N73 -> 1072732.8 | G7: ='FPT Digital Retail JSC | Cash F'!O73 -> 1366544.6
A8: FCFE (FV) | B8: =SUM(B3:B7) -> 2914412.4 | C8: =SUM(C3:C7) -> 1456900.7 | D8: =SUM(D3:D7) -> 1877665.8 | E8: =SUM(E3:E7) -> 2388466.2 | F8: =SUM(F3:F7) -> 2014212 | G8: =SUM(G3:G7) -> 2037277.6
L9: Sensitivity Analysis | N9: Terminal Growth Rate (g)
N10: 0.0575 | O10: 0.0625 | P10: 0.0675 | Q10: 0.0725 | R10: 0.0775
A11: FCFE | C11: 1 | D11: 2 | E11: 3 | F11: 4 | G11: 5 | L11: E(Ri) | M11: 0.1849 | N11: 99432 | O11: 101485 | P11: 103713 | Q11: 106139 | R11: 108790
B12: FY | C12: 2023 | D12: 2024 | E12: 2025 | F12: 2026 | G12: 2027 | H12: 2028 | M12: 0.1949 | N12: 92818 | O12: 94506 | P12: 96325 | Q12: 98294 | R12: 100430 | S12: =R11/P13-1 -> 0.20903302
A13: Step 1: Estimate your Future FCFE | B13: g | C13: =20.49% -> 0.2049 | D13: =20.49% -> 0.2049 | E13: =20.49% -> 0.2049 | F13: =20.49% -> 0.2049 | G13: =20.49% -> 0.2049 | H13: =D28 -> 0.06746 | M13: 0.2049 | N13: 87086 | O13: 88489 | P13: 89981 | Q13: 91612 | R13: 93357 | S13: =P11/O11-1 -> 0.021953983
A14: =B2 -> 0 | B14: FCFE | C14: =B8 -> 2914412.4 | D14: =C8 -> 1456900.7 | E14: =D8 -> 1877665.8 | F14: =E8 -> 2388466.2 | G14: =F8 -> 2014212 | H14: =G8 -> 2037277.6 | M14: 0.2149 | N14: 82067 | O14: 83245 | P14: 84503 | Q14: 85849 | R14: 87292 | S14: =P13/P14-1 -> 0.064826101
A15: PV terminal | H15: =H14/(G13-H13) -> 14823033 | M15: 0.2249 | N15: 77636 | O15: 78633 | P15: 79694 | Q15: 80824 | R15: 82031 | S15: =P13/N15-1 -> 0.15901128
A16: PV 5 years @ 20,49% | B16: DCF | C16: =C14/(1+C13)^C11 -> 2418800.2 | D16: =D14/(1+D13)^D11 -> 1003524.4 | E16: =E14/(1+E13)^E11 -> 1073409.1 | F16: =F14/(1+F13)^F11 -> 1133222.2 | G16: =(H15+G14)/(1+G13)^G11 -> 6630037.7
A17: Intrinsic Value
B18: Intrinsic Value | C18: =(SUM(C16:G16)/136.24) -> 89980.87 | L18: Sensitivity Analysis | N18: P/E
B19: Market Value | C19: =101800 -> 101800 | D19: As 8 Dec 2023 | N19: 0.0575 | O19: 0.0625 | P19: 0.0675 | Q19: 0.0725 | R19: 0.0775
B20: HOLD | L20: EPS | M20: 0.1849 | N20: 99432 | O20: 101485 | P20: 103713 | Q20: 106139 | R20: 108790
A21: FCFE | M21: 0.1949 | N21: 92818 | O21: 94506 | P21: 96325 | Q21: 98294 | R21: 100430
M22: 0.2049 | N22: 87086 | O22: 88489 | P22: 89981 | Q22: 91612 | R22: 93357
B23: gdp | C23: 0.058 | M23: 0.2149 | N23: 82067 | O23: 83245 | P23: 84503 | Q23: 85849 | R23: 87292
B24: infl | C24: 0.034 | M24: 0.2249 | N24: 77636 | O24: 78633 | P24: 79694 | Q24: 80824 | R24: 82031
B25: pharma | C25: 0.073 | D25: =C25*44% -> 0.03212
B26: ict | C26: 0.022 | D26: =SUM(C26:C27)*56% -> 0.0448
B27: household | C27: 0.058 | D27: =SUM(D25:D26) -> 0.07692
D28: =AVERAGE(D27,C23) -> 0.06746 | G28: 0.062
G29: =(1+G28)^10 -> 1.8249256
B30: 1 | C30: 2 | D30: 3 | E30: 4 | G30: =5500000000 -> 5500000000
B31: 2100 | D31: 2740 | E31: 3270 | G31: =G30/G29 -> 3.0138215e+09
B32: 0.09 | C32: 0.09 | D32: 0.09 | E32: 0.09
A33: =SUM(B33:E33) -> 6358.9387 | B33: =B31/((1+B32)^B30) -> 1926.6055 | C33: =C31/((1+C32)^C30) -> 0 | D33: =D31/((1+D32)^D30) -> 2115.7827 | E33: =E31/((1+E32)^E30) -> 2316.5504
A34: =8200 -> 8200 | C34: =A34-A33 -> 1841.0613
C35: =C34*((1+C32)^C30) -> 2187.365

Sheet Peer Valuation
A1: Identifier (GRID_REPORT.RIC) | B1: Company Name | C1: GICS Sector Name | D1: Market Cap (VND) | E1: P/E (Daily Time Series Ratio)
G2: P/E (Daily Time Series Ratio) (0CY) | H2: Forward P/E | I2: ROE (%) | K2: Criteria for peers selection: - Retail in ICT - consumer electronics/Pharma - Listed - Market Cap
A4: FRT.HM | B4: FPT Digital Retail JSC | C4: Consumer Discretionary | D4: 1.3742897e+13 | G4: 20.78 | H4: ='Model '!C19/'Peer Valuation'!B19 -> 25.849501 | I4: ='Key financial ratios'!I31 -> 0.213
A5: MWG.HM | B5: Mobile World Investment Corp | C5: Consumer Discretionary | D5: 6.2157022e+13 | G5: 15.785691 | H5: =40800/798.45 -> 51.099004 | I5: 0.1852 | AA5: Method | AB5: Target Price | AC5: Weight | AD5: Final Target Price
A6: DGW.HM | B6: Digiworld Corp | C6: Information Technology | D6: 8.868144e+12 | G6: 8.8800517 | H6: =53200/2349.5 -> 22.643116 | I6: 0.3277 | AA6: Discounted Cash Flow - FCFE Model | AB6: ='Model '!C18 -> 89980.87 | AC6: 0.7 | AD6: =C26 -> 89738.411
A7: PET.HM | B7: PetroVietnam General Services Corp | C7: Industrials | D7: 2.890941e+12 | G7: 13.39 | H7: =27300/1605.94 -> 16.99939 | I7: 0.0578 | AA7: Relative Multiples - P/E | AB7: =B21 -> 89172.675 | AC7: 0.3
A8: Peer Median | D8: 3.6898761e+13 | G8: =MEDIAN(G5:G7) -> 13.39 | H8: =MEDIAN(H5:H7) -> 22.643116 | I8: =MEDIAN(I4:I7) -> 0.1991
A9: Peer Mean | D9: 33982241223425 | G9: =AVERAGE(G5:G7) -> 12.685247 | H9: =AVERAGE(H5:H7) -> 30.24717 | I9: =AVERAGE(I4:I7) -> 0.195925
A10: 1st Quartile | D10: 2.890941e+12 | G10: 5.9595715
A11: 3rd Quartile | D11: 4.3021976e+13 | G11: 18.476359
A12: Specialty Retail | D12: 3.1902783e+12 | G12: 14.17934
A15: Relative Valuation - in mn VND (Except for forecasted price) | B15: FPT Retail
A16: Profit before tax (F) | B16: ='FPT Digital Retail JSC | Income'!J74 -> 674057.52
A17: Net income (F) | B17: ='FPT Digital Retail JSC | Income'!J89 -> 536537.71
A18: total no. of shares outstanding (A) | B18: =136.24 -> 136.24
A19: EPS (F) | B19: =B17/B18 -> 3938.1805
A20: current P/E (average in the industry) | B20: =H8 -> 22.643116
A21: Forecasted price (in VND) | B21: =B20*B19 -> 89172.675
A23: Method | B23: Weight | C23: Forecasted Price
A24: FCFE | B24: 0.7 | C24: ='Model '!C18*'Peer Valuation'!B24 -> 62986.609
A25: P/E | B25: 0.3 | C25: =B21*B25 -> 26751.803
A26: FINAL PRICE | C26: =SUM(C24:C25) -> 89738.411
C27: =C26/'Model '!C19-1 -> -0.11848319
A29: Consider EV/EBITDA | S29: Sensitivity Analysis | U29: P/E
U30: =V30-0.5 -> 21.64 | V30: =W30-0.5 -> 22.14 | W30: =22.64 -> 22.64 | X30: =W30+0.5 -> 23.14 | Y30: =X30+0.5 -> 23.64
S31: EPS | T31: =T32-500 -> 2938
T32: =T33-500 -> 3438
T33: =3938 -> 3938 | W33: =89173 -> 89173
T34: =T33+500 -> 4438
T35: =T34+500 -> 4938

Sheet CAPM
A1: Exchange Date | B1: VN Index | C1: FRT | D1: VN Index returns | E1: FRT returns
A2: 43220 | B2: 1050.26 | C2: 44455.33
A3: 43251 | B3: 971.25 | C3: 42566.346 | D3: =B3/B4-1 -> 0.010897396 | E3: =C3/C4-1 -> 0.11604938
A4: 43281 | B4: 960.78 | C4: 38140.199 | D4: =B4/B5-1 -> 0.0045901776 | E4: =C4/C5-1 -> 0.082887701
A5: 43312 | B5: 956.39 | C5: 35220.826 | D5: =B5/B6-1 -> -0.033500414 | E5: =C5/C6-1 -> -0.020942408
A6: 43343 | B6: 989.54 | C6: 35974.213 | D6: =B6/B7-1 -> -0.027125343 | E6: =C6/C7-1 -> 0.0039421813
A7: 43373 | B7: 1017.13 | C7: 35832.953 | D7: =B7/B8-1 -> 0.11190913 | E7: =C7/C8-1 -> 0.046767538
A8: 43404 | B8: 914.76 | C8: 34232.006 | D8: =B8/B9-1 -> -0.012713968 | E8: =C8/C9-1 -> -0.004109589
A9: 43434 | B9: 926.54 | C9: 34373.266 | D9: =B9/B10-1 -> 0.038093531 | E9: =C9/C10-1 -> 0.015299026
A10: 43465 | B10: 892.54 | C10: 33855.313 | D10: =B10/B11-1 -> -0.019886894 | E10: =C10/C11-1 -> 0.051169591
A11: 43496 | B11: 910.65 | C11: 32207.279 | D11: =B11/B12-1 -> -0.056780635 | E11: =C11/C12-1 -> 0.11219512
A12: 43524 | B12: 965.47 | C12: 28958.299 | D12: =B12/B13-1 -> -0.015589951 | E12: =C12/C13-1 -> 0.23742455
A13: 43555 | B13: 980.76 | C13: 23402.073 | D13: =B13/B14-1 -> 0.0011432771 | E13: =C13/C14-1 -> -0.029296875
A14: 43585 | B14: 979.64 | C14: 24108.373 | D14: =B14/B15-1 -> 0.020585907 | E14: =C14/C15-1 -> 0.0098619329
... A17: 43677 | B17: 991.66 | C17: 26482.271 | D17: =B17/B18-1 -> 0.0077231063 | E17: =C17/C18-1 -> 0.090909091
A18: 43708 | B18: 984.06 | C18: 24275.415 | D18: =B18/B19-1 -> -0.012543148 | E18: =C18/C19-1 -> -0.028697572 | G18: SUMMARY OUTPUT
A19: 43738 | B19: 996.56 | C19: 24992.643 | D19: =B19/B20-1 -> -0.00226267 | E19: =C19/C20-1 -> 0.10893513
A20: 43769 | B20: 998.82 | C20: 22537.516 | D20: =B20/B21-1 -> 0.028915787 | E20: =C20/C21-1 -> 0.51858736 | G20: Regression Statistics
A21: 43799 | B21: 970.75 | C21: 14841.106 | D21: =B21/B22-1 -> 0.010156193 | E21: =C21/C22-1 -> 0.27790974 | G21: Multiple R | H21: 0.44803808
A22: 43830 | B22: 960.99 | C22: 11613.579 | D22: =B22/B23-1 -> 0.02601909 | E22: =C22/C23-1 -> 0.22740525 | G22: R Square | H22: 0.20073812
A23: 43861 | B23: 936.62 | C23: 9461.8948 | D23: =B23/B24-1 -> 0.061698727 | E23: =C23/C24-1 -> -0.18527316 | G23: Adjusted R Square | H23: 0.18805142
A24: 43890 | B24: 882.19 | C24: 11613.579 | D24: =B24/B25-1 -> 0.33154725 | E24: =C24/C25-1 -> 0.88789238 | G24: Standard Error | H24: 0.19844188
A25: 43921 | B25: 662.53 | C25: 6151.6109 | D25: =B25/B26-1 -> -0.13857576 | E25: =C25/C26-1 -> -0.47529412 | G25: Observations | H25: 65
A26: 43951 | B26: 769.11 | C26: 11723.922 | D26: =B26/B27-1 -> -0.11031036 | E26: =C26/C27-1 -> -0.1889313
A27: 43982 | B27: 864.47 | C27: 14454.906 | D27: =B27/B28-1 -> 0.047702731 | E27: =C27/C28-1 -> 0.19090909 | G27: ANOVA
A28: 44012 | B28: 825.11 | C28: 12137.708 | D28: =B28/B29-1 -> 0.033467353 | E28: =C28/C29-1 -> 0.078431373 | H28: df | I28: SS | J28: MS | K28: F | L28: Significance F
A29: 44043 | B29: 798.39 | C29: 11254.965 | D29: =B29/B30-1 -> -0.094436568 | E29: =C29/C30-1 -> -0.17798629 | G29: Regression | H29: 1 | I29: 0.62308594 | J29: 0.62308594 | K29: 15.822726 | L29: 0.00018216014
A30: 44074 | B30: 881.65 | C30: 13691.943 | D30: =B30/B31-1 -> -0.02602711 | E30: =C30/C31-1 -> -0.0083333334 | G30: Residual | H30: 63 | I30: 2.4808883 | J30: 0.039379179
A31: 44104 | B31: 905.21 | C31: 13807.002 | D31: =B31/B32-1 -> -0.021891579 | E31: =C31/C32-1 -> 0.15107914 | G31: Total | H31: 64 | I31: 3.1039742
A32: 44135 | B32: 925.47 | C32: 11994.833 | D32: =B32/B33-1 -> -0.077371695 | E32: =C32/C33-1 -> -0.12210526
A33: 44165 | B33: 1003.08 | C33: 13663.179 | D33: =B33/B34-1 -> -0.091306041 | E33: =C33/C34-1 -> -0.2578125 | H33: Coefficients | I33: Standard Error | J33: t Stat | K33: P-value | L33: Lower 95% | M33: Upper 95% | N33: Lower 95,0% | O33: Upper 95,0%
A34: 44196 | B34: 1103.87 | C34: 18409.336 | D34: =B34/B35-1 -> 0.044727951 | E34: =C34/C35-1 -> 0.22137405 | G34: Intercept | H34: 0.026354004 | I34: 0.024652285 | J34: 1.0690289 | K34: 0.28913567 | L34: -0.022909656 | M34: 0.075617663 | N34: -0.022909656 | O34: 0.075617663
A35: 44227 | B35: 1056.61 | C35: 15072.644 | D35: =B35/B36-1 -> -0.095732026 | E35: =C35/C36-1 -> -0.064285714 | G35: X Variable 1 | H35: 1.4986275 | I35: 0.37674981 | J35: 3.977779 | K35: 0.00018216014 | L35: 0.74575305 | M35: 2.2515019 | N35: 0.74575305 | O35: 2.2515019
A36: 44255 | B36: 1168.47 | C36: 16108.169 | D36: =B36/B37-1 -> -0.019279192 | E36: =C36/C37-1 -> -0.08045977
A37: 44286 | B37: 1191.44 | C37: 17517.633 | D37: =B37/B38-1 -> -0.038688387 | E37: =C37/C38-1 -> 0.12777778
A38: 44316 | B38: 1239.39 | C38: 15532.877 | D38: =B38/B39-1 -> -0.066759535 | E38: =C38/C39-1 -> 0.084337349 | G38: Adjusted Beta | H38: =2/3*(H35)+1/3 -> 1.3324183
A39: 44347 | B39: 1328.05 | C39: 14324.764 | D39: =B39/B40-1 -> -0.057150971 | E39: =C39/C40-1 -> -0.081180812 | G39: Risk premium | H39: =16%-H40 -> 0.13518
A40: 44377 | B40: 1408.55 | C40: 15590.406 | D40: =B40/B41-1 -> 0.07518797 | E40: =C40/C41-1 -> -0.27636849 | G40: RF (%) | H40: 0.02482 | I40: 10y gov bond
A41: 44408 | B41: 1310.05 | C41: 21544.676 | D41: =B41/B42-1 -> -0.016087482 | E41: =C41/C42-1 -> -0.091019417 | G41: Cost of Equity | H41: =H40+(H38*H39) -> 0.20493631
A42: 44439 | B42: 1331.47 | C42: 23702.02 | D42: =B42/B43-1 -> -0.0078908544 | E42: =C42/C43-1 -> -0.13354364
A43: 44469 | B43: 1342.06 | C43: 27355.122 | D43: =B43/B44-1 -> -0.070769316 | E43: =C43/C44-1 -> -0.087332054
A44: 44500 | B44: 1444.27 | C44: 29972.7 | D44: =B44/B45-1 -> -0.023112199 | E44: =C44/C45-1 -> -0.10172414
A45: 44530 | B45: 1478.44 | C45: 33366.921 | D45: =B45/B46-1 -> -0.013241851 | E45: =C45/C46-1 -> -0.42115768
A46: 44561 | B46: 1498.28 | C46: 57644.232 | D46: =B46/B47-1 -> 0.013063234 | E46: =C46/C47-1 -> 0.14253136
A47: 44592 | B47: 1478.96 | C47: 50453.085 | D47: =B47/B48-1 -> -0.0074959903 | E47: =C47/C48-1 -> -0.28291087
A48: 44620 | B48: 1490.13 | C48: 70358.18 | D48: =B48/B49-1 -> -0.0013537513 | E48: =C48/C49-1 -> -0.18520986
A49: 44651 | B49: 1492.15 | C49: 86351.29 | D49: =B49/B50-1 -> 0.091710565 | E49: =C49/C50-1 -> -0.040894569
A50: 44681 | B50: 1366.8 | C50: 90033.157 | D50: =B50/B51-1 -> 0.057338243 | E50: =C50/C51-1 -> 0.26311542
A51: 44712 | B51: 1292.68 | C51: 71278.646 | D51: =B51/B52-1 -> 0.079392118 | E51: =C51/C52-1 -> -0.094297793
A52: 44742 | B52: 1197.6 | C52: 78699.87 | D52: =B52/B53-1 -> -0.0072368257 | E52: =C52/C53-1 -> 0.26666667
A53: 44773 | B53: 1206.33 | C53: 62131.477 | D53: =B53/B54-1 -> -0.057930043 | E53: =C53/C54-1 -> -0.20879121
... A67: 45199 | B67: 1154.15 | C67: 89000 | D67: =B67/B68-1 -> #DIV/0! | E67: =C67/C68-1 -> #DIV/0!

Sheet Peers 
A1: Identifier | B1: Company Name | C1: Country | D1: Market Capitalization (VND)
A3: FRT.HM | B3: FPT Digital Retail JSC | C3: Vietnam | D3: 1.3742897e+13
A4: MWG.HM | B4: Mobile World Investment Corp | C4: Vietnam | D4: 6.2157022e+13
A5: DGW.HM | B5: Digiworld Corp | C5: Vietnam | D5: 8.868144e+12
A6: PET.HM | B6: PetroVietnam General Services Corp | C6: Vietnam | D6: 2.890941e+12
A9: PROFITABILITY | H9: EFFICIENCY | O9: LIQUIDITY AND SOLVENCY
B10: 2018 | C10: 2019 | D10: 2020 | E10: 2021 | F10: 2022 | I10: 2018 | J10: 2019 | K10: 2020 | L10: 2021 | M10: 2022 | P10: 2018 | Q10: 2019 | R10: 2020 | S10: 2021 | T10: 2022 | V10: DGW
A11: DGW | H11: DGW | O11: DGW | V11: 173211 | W11: 100216 | X11: 198672 | Y11: 391431 | Z11: 212926 | AB11: 2017 | AC11: =AC17 -> 2018 | AD11: =AD17 -> 2019 | AE11: =AE17 -> 2020 | AF11: =AF17 -> 2021 | AG11: =AG17 -> 2022
A12: Gross Margin | B12: 0.062 | C12: 0.065 | D12: 0.064 | E12: 0.072 | F12: 0.075 | H12: AR Turnover | I12: 10.1 | J12: 12.3 | K12: 13.8 | L12: 14.4 | M12: 12.9 | O12: Current Ratio | P12: 1.46 | Q12: 1.55 | R12: 1.5 | S12: 1.32 | T12: 1.49 | V12: 93376 | W12: 67681 | X12: 76420 | Y12: 81065 | Z12: 175767 | AB12: 3.821 | AC12: 5.937 | AD12: 8.488 | AE12: 12.536 | AF12: 20.923 | AG12: 22.028
A13: Operating Margin | B13: 0.023 | C13: 0.025 | D13: 0.026 | E13: 0.039 | F13: 0.039 | H13: AP Turnover | I13: =A40 -> 10.852759 | J13: =B40 -> 12.120099 | K13: =C40 -> 13.316377 | L13: =D40 -> 7.3556466 | M13: =E40 -> 18.199039 | O13: Quick Ratio | P13: 0.55 | Q13: 0.57 | R13: 1.07 | S13: 0.71 | T13: 0.65 | V13: =V11/V12 -> 1.8549842 | W13: =W11/W12 -> 1.480711 | X13: =X11/X12 -> 2.5997383 | Y13: =Y11/Y12 -> 4.8286067 | Z13: =Z11/Z12 -> 1.2114106 | AB13: Growth | AC13: =(AC12-AB12)/AB12 -> 0.55378173 | AD13: =(AD12-AC12)/AC12 -> 0.42967829 | AE13: =(AE12-AD12)/AD12 -> 0.47690858 | AF13: =(AF12-AE12)/AE12 -> 0.66903318 | AG13: =(AG12-AF12)/AF12 -> 0.052812694
A14: Net Margin | B14: 0.018 | C14: 0.019 | D14: 0.021 | E14: 0.031 | F14: 0.031 | H14: Inventory Turnover | I14: 5.1 | J14: 5.7 | K14: 10.3 | L14: 10.5 | M14: 6.6 | O14: A/E | P14: 2.9 | Q14: 2.61 | R14: 2.65 | S14: 3.68 | T14: 2.65
A15: MWG | H15: Fixed Asset Turnover | I15: 241.28 | J15: 398.35 | K15: 531.3 | L15: 678.23 | M15: 660.47 | O15: D/E | P15: 1.09 | Q15: 0.67 | R15: 0.54 | S15: 0.63 | T15: 0.82
A16: Gross Margin | B16: 0.177 | C16: 0.191 | D16: 0.221 | E16: 0.225 | F16: 0.231 | H16: MWG | O16: Interest Coverage Ratio | P16: =V13 -> 1.8549842 | Q16: =W13 -> 1.480711 | R16: =X13 -> 2.5997383 | S16: =Y13 -> 4.8286067 | T16: =Z13 -> 1.2114106 | V16: MWG
A17: Operating Margin | B17: 0.044 | C17: 0.049 | D17: 0.05 | E17: 0.053 | F17: 0.049 | H17: AR Turnover | I17: 36.3 | J17: 49.2 | K17: 54.7 | L17: 48.3 | M17: 42.8 | O17: MWG | V17: 3774182 | W17: 5034683 | X17: 5412530 | Y17: 6465607 | Z17: 6574694 | AB17: 2017 | AC17: =AC22 -> 2018 | AD17: =AD22 -> 2019 | AE17: =AE22 -> 2020 | AF17: =AF22 -> 2021 | AG17: =AG22 -> 2022
A18: Net Margin | B18: 0.033 | C18: 0.038 | D18: 0.036 | E18: 0.04 | F18: 0.031 | H18: AP Turnover | I18: =A35 -> 10.493673 | J18: =B35 -> 8.4754028 | K18: =C35 -> 12.436288 | L18: =D35 -> 10.095269 | M18: =E35 -> 15.253535 | O18: Current Ratio | P18: 1.3 | Q18: 1.23 | R18: 1.27 | S18: 1.22 | T18: 1.71 | V18: 436417 | W18: 568137 | X18: 594004 | Y18: 674428 | Z18: 1362144 | AB18: 66.34 | AC18: 86.516 | AD18: 102.174 | AE18: 108.546 | AF18: 122.958 | AG18: 133.405
A19: PET | H19: Inventory Turnover | I19: 4.8 | J19: 3.8 | K19: 3.7 | L19: 3.9 | M19: 3.7 | O19: Quick Ratio | P19: 0.33 | Q19: 0.33 | R19: 0.61 | S19: 0.54 | T19: 0.73 | V19: =V17/V18 -> 8.6481095 | W19: =W17/W18 -> 8.8617411 | X19: =X17/X18 -> 9.111942 | Y19: =Y17/Y18 -> 9.586801 | Z19: =Z17/Z18 -> 4.8267246 | AB19: Growth | AC19: =(AC18-AB18)/AB18 -> 0.30413024 | AD19: =(AD18-AC18)/AC18 -> 0.18098386 | AE19: =(AE18-AD18)/AD18 -> 0.062364202 | AF19: =(AF18-AE18)/AE18 -> 0.1327732 | AG19: =(AG18-AF18)/AF18 -> 0.084963971
A20: Gross Margin | B20: 0.06 | C20: 0.061 | D20: 0.05 | E20: 0.053 | F20: 0.055 | H20: Fixed Asset Turnover | I20: 24.6 | J20: 22.64 | K20: 16.88 | L20: 14.43 | M20: 13.74 | O20: A/E | P20: 3.13 | Q20: 3.44 | R20: 2.98 | S20: 3.09 | T20: 2.33
A21: Operating Margin | B21: 0.016 | C21: 0.01 | D21: 0.015 | E21: 0.023 | F21: 0.012 | H21: PET | O21: D/E | P21: 0.78 | Q21: 1.17 | R21: 1.08 | S21: 1.21 | T21: 0.69 | V21: PET
A22: Net Margin | B22: 0.012 | C22: 0.013 | D22: 0.01 | E22: 0.018 | F22: 0.01 | H22: AR Turnover | I22: 5.2 | J22: 5.6 | K22: 8.1 | L22: 8.1 | M22: 7.3 | O22: Interest Coverage Ratio | P22: =V19 -> 8.6481095 | Q22: =W19 -> 8.8617411 | R22: =X19 -> 9.111942 | S22: =Y19 -> 9.586801 | T22: =Z19 -> 4.8267246 | V22: 173211 | W22: 100216 | X22: 198672 | Y22: 391431 | Z22: 212926 | AB22: 2017 | AC22: =P10 -> 2018 | AD22: =Q10 -> 2019 | AE22: =R10 -> 2020 | AF22: =S10 -> 2021 | AG22: =T10 -> 2022
A23: FRT | H23: AP Turnover | I23: =A44 -> 7.7669735 | J23: =B44 -> 7.6643129 | K23: =C44 -> 9.9440231 | L23: =D44 -> 7.852395 | M23: =E44 -> 10.041022 | O23: PET | V23: 93376 | W23: 67681 | X23: 76420 | Y23: 81065 | Z23: 175767 | AB23: 10.703 | AC23: 11.092 | AD23: 10.008 | AE23: 13.453 | AF23: 17.598 | AG23: 17.543
A24: Gross Margin | B24: ='Key financial ratios'!E18 -> 0.13358382 | C24: ='Key financial ratios'!F18 -> 0.12691247 | D24: ='Key financial ratios'!G18 -> 0.13920905 | E24: ='Key financial ratios'!H18 -> 0.14009862 | F24: ='Key financial ratios'!I18 -> 0.15591093 | H24: Inventory Turnover | I24: 11.7 | J24: 8.8 | K24: 13.4 | L24: 14.9 | M24: 8.6 | O24: Current Ratio | P24: 1.22 | Q24: 1.24 | R24: 1.16 | S24: 1.12 | T24: 1.13 | V24: =V22/V23 -> 1.8549842 | W24: =W22/W23 -> 1.480711 | X24: =X22/X23 -> 2.5997383 | Y24: =Y22/Y23 -> 4.8286067 | Z24: =Z22/Z23 -> 1.2114106 | AB24: Growth | AC24: =(AC23-AB23)/AB23 -> 0.03634495 | AD24: =(AD23-AC23)/AC23 -> -0.097728092 | AE24: =(AE23-AD23)/AD23 -> 0.34422462 | AF24: =(AF23-AE23)/AE23 -> 0.30810972 | AG24: =(AG23-AF23)/AF23 -> -0.0031253552
A25: Operating Margin | B25: ='Key financial ratios'!E20 -> 0.026328878 | C25: ='Key financial ratios'!F20 -> 0.016401566 | D25: ='Key financial ratios'!G20 -> 0.00097664503 | E25: ='Key financial ratios'!H20 -> 0.024280816 | F25: ='Key financial ratios'!I20 -> 0.015712097 | H25: Fixed Asset Turnover | I25: 67.23 | J25: 77.62 | K25: 105.6 | L25: 139.58 | M25: 132.04 | O25: Quick Ratio | P25: 0.93 | Q25: 0.86 | R25: 0.98 | S25: 0.9 | T25: 0.78
A26: Net Margin | B26: ='Key financial ratios'!E23 -> 0.023 | C26: ='Key financial ratios'!F23 -> 0.012 | D26: ='Key financial ratios'!G23 -> 0.001 | E26: ='Key financial ratios'!H23 -> 0.02 | F26: ='Key financial ratios'!I23 -> 0.013 | H26: FRT | O26: A/E | P26: 3.77 | Q26: 3.29 | R26: 4.1 | S26: 4.68 | T26: 4.67
A27: Peer Median | H27: AR Turnover | I27: ='Key financial ratios'!E45 -> 14.3 | J27: ='Key financial ratios'!F45 -> 14.3 | K27: ='Key financial ratios'!G45 -> 11.1 | L27: ='Key financial ratios'!H45 -> 13 | M27: ='Key financial ratios'!I45 -> 22.5 | O27: D/E | P27: 1.28 | Q27: 1.01 | R27: 1.76 | S27: 2.01 | T27: 1.91 | V27: Revenue Growth | W27: =AC17 -> 2018 | X27: =AD17 -> 2019 | Y27: =AE17 -> 2020 | Z27: =AF17 -> 2021 | AA27: =AG17 -> 2022
A28: Gross Margin | B28: =MEDIAN(B12,B16,B20,B24) -> 0.097791909 | C28: =MEDIAN(C12,C16,C20,C24) -> 0.095956237 | D28: =MEDIAN(D12,D16,D20,D24) -> 0.10160453 | E28: =MEDIAN(E12,E16,E20,E24) -> 0.10604931 | F28: =MEDIAN(F12,F16,F20,F24) -> 0.11545546 | H28: AP Turnover | I28: ='FPT Digital Retail JSC | Income'!E29/'FPT Digital Retail JSC | BS'!D74 -> 18.77727 | J28: ='FPT Digital Retail JSC | Income'!F29/'FPT Digital Retail JSC | BS'!E74 -> 11.279732 | K28: ='FPT Digital Retail JSC | Income'!G29/'FPT Digital Retail JSC | BS'!F74 -> 10.388968 | L28: ='FPT Digital Retail JSC | Income'!H29/'FPT Digital Retail JSC | BS'!G74 -> 8.2814967 | M28: ='FPT Digital Retail JSC | Income'!I29/'FPT Digital Retail JSC | BS'!H74 -> 11.035412 | O28: Interest Coverage Ratio | P28: =V24 -> 1.8549842 | Q28: =W24 -> 1.480711 | R28: =X24 -> 2.5997383 | S28: =Y24 -> 4.8286067 | T28: =Z24 -> 1.2114106 | V28: FRT | W28: ='Revenue breakdown'!B4 -> 0.16367988 | X28: ='Revenue breakdown'!C4 -> 0.087305252 | Y28: ='Revenue breakdown'!D4 -> -0.11858529 | Z28: ='Revenue breakdown'!E4 -> 0.53429651 | AA28: ='Revenue breakdown'!F4 -> 0.34100259
A29: Operating Margin | B29: =MEDIAN(B13,B17,B21,B25) -> 0.024664439 | C29: =MEDIAN(C13,C17,C21,C25) -> 0.020700783 | D29: =MEDIAN(D13,D17,D21,D25) -> 0.0205 | E29: =MEDIAN(E13,E17,E21,E25) -> 0.031640408 | F29: =MEDIAN(F13,F17,F21,F25) -> 0.027356049 | H29: Inventory Turnover | I29: ='Key financial ratios'!E48 -> 6.3 | J29: ='Key financial ratios'!F48 -> 4.9 | K29: ='Key financial ratios'!G48 -> 4.8 | L29: ='Key financial ratios'!H48 -> 5.7 | M29: ='Key financial ratios'!I48 -> 4.5 | O29: FRT | V29: MWG | W29: =AC19 -> 0.30413024 | X29: =AD19 -> 0.18098386 | Y29: =AE19 -> 0.062364202 | Z29: =AF19 -> 0.1327732 | AA29: =AG19 -> 0.084963971
A30: Net Margin | B30: =MEDIAN(B14,B18,B22,B26) -> 0.0205 | C30: =MEDIAN(C14,C18,C22,C26) -> 0.016 | D30: =MEDIAN(D14,D18,D22,D26) -> 0.0155 | E30: =MEDIAN(E14,E18,E22,E26) -> 0.0255 | F30: =MEDIAN(F14,F18,F22,F26) -> 0.022 | H30: Fixed Asset Turnover | I30: ='Key financial ratios'!E51 -> 2875.09 | J30: ='Key financial ratios'!F51 -> 2826.83 | K30: ='Key financial ratios'!G51 -> 1913.67 | L30: ='Key financial ratios'!H51 -> 1789.13 | M30: ='Key financial ratios'!I51 -> 87.01 | O30: Current Ratio | P30: ='Key financial ratios'!E36 -> 1.2 | Q30: ='Key financial ratios'!F36 -> 1.16 | R30: ='Key financial ratios'!G36 -> 1.19 | S30: ='Key financial ratios'!H36 -> 1.12 | T30: ='Key financial ratios'!I36 -> 1.1 | V30: PET | W30: =AC24 -> 0.03634495 | X30: =AD24 -> -0.097728092 | Y30: =AE24 -> 0.34422462 | Z30: =AF24 -> 0.30810972 | AA30: =AG24 -> -0.0031253552
H31: Peer Median | O31: Quick Ratio | P31: ='Key financial ratios'!E35 -> 0.58 | Q31: ='Key financial ratios'!F35 -> 0.53 | R31: ='Key financial ratios'!G35 -> 0.75 | S31: ='Key financial ratios'!H35 -> 0.58 | T31: ='Key financial ratios'!I35 -> 0.34 | V31: DGW | W31: =AC13 -> 0.55378173 | X31: =AD13 -> 0.42967829 | Y31: =AE13 -> 0.47690858 | Z31: =AF13 -> 0.66903318 | AA31: =AG13 -> 0.052812694
A32: MWG | H32: AR Turnover | I32: =MEDIAN(I12,I17,I22,I27) -> 12.2 | J32: =MEDIAN(J12,J17,J22,J27) -> 13.3 | K32: =MEDIAN(K12,K17,K22,K27) -> 12.45 | L32: =MEDIAN(L12,L17,L22,L27) -> 13.7 | M32: =MEDIAN(M12,M17,M22,M27) -> 17.7 | O32: A/E | P32: ='Key financial ratios'!E40 -> 4.5578995 | Q32: ='Key financial ratios'!F40 -> 5.1767594 | R32: ='Key financial ratios'!G40 -> 4.438875 | S32: ='Key financial ratios'!H40 -> 6.4890008 | T32: ='Key financial ratios'!I40 -> 5.2403319
A33: 86516287 | B33: 102174244 | C33: 108546020 | D33: 122958106 | E33: 133404778 | H33: AP Turnover | I33: =MEDIAN(I13,I18,I23,I28) -> 10.673216 | J33: =MEDIAN(J13,J18,J23,J28) -> 9.8775674 | K33: =MEDIAN(K13,K18,K23,K28) -> 11.412628 | L33: =MEDIAN(L13,L18,L23,L28) -> 8.0669459 | M33: =MEDIAN(M13,M18,M23,M28) -> 13.144473 | O33: D/E | P33: ='Key financial ratios'!E41 -> 2.5995027 | Q33: ='Key financial ratios'!F41 -> 2.9033214 | R33: ='Key financial ratios'!G41 -> 2.0481954 | S33: ='Key financial ratios'!H41 -> 3.6381764 | T33: ='Key financial ratios'!I41 -> 2.6706743
A34: 8244614 | B34: 12055385 | C34: 8728169 | D34: 12179775 | E34: 8745827 | H34: Inventory Turnover | I34: =MEDIAN(I14,I19,I24,I29) -> 5.7 | J34: =MEDIAN(J14,J19,J24,J29) -> 5.3 | K34: =MEDIAN(K14,K19,K24,K29) -> 7.55 | L34: =MEDIAN(L14,L19,L24,L29) -> 8.1 | M34: =MEDIAN(M14,M19,M24,M29) -> 5.55 | O34: Interest Coverage Ratio | P34: ='FPT Digital Retail JSC | Income'!E63/'FPT Digital Retail JSC | Income'!E51 -> 4.2101368 | Q34: ='FPT Digital Retail JSC | Income'!F63/'FPT Digital Retail JSC | Income'!F51 -> 2.0181754 | R34: ='FPT Digital Retail JSC | Income'!G63/'FPT Digital Retail JSC | Income'!G51 -> 0.12595662 | S34: ='FPT Digital Retail JSC | Income'!H63/'FPT Digital Retail JSC | Income'!H51 -> 4.1306824 | T34: ='FPT Digital Retail JSC | Income'!I63/'FPT Digital Retail JSC | Income'!I51 -> 2.0471304
A35: =A33/A34 -> 10.493673 | B35: =B33/B34 -> 8.4754028 | C35: =C33/C34 -> 12.436288 | D35: =D33/D34 -> 10.095269 | E35: =E33/E34 -> 15.253535 | H35: Fixed Asset Turnover | I35: =MEDIAN(I15,I20,I25,I30) -> 154.255 | J35: =MEDIAN(J15,J20,J25,J30) -> 237.985 | K35: =MEDIAN(K15,K20,K25,K30) -> 318.45 | L35: =MEDIAN(L15,L20,L25,L30) -> 408.905 | M35: =MEDIAN(M15,M20,M25,M30) -> 109.525 | O35: Peer Median | V35: Gap current and quick
I36: =I30/I35 -> 18.638553 | J36: =J30/J35 -> 11.878186 | K36: =K30/K35 -> 6.0093264 | L36: =L30/L35 -> 4.3754173 | M36: =M30/M35 -> 0.7944305 | O36: Current Ratio | P36: =MEDIAN(P30,P24,P18,P12) -> 1.26 | Q36: =MEDIAN(Q30,Q24,Q18,Q12) -> 1.235 | R36: =MEDIAN(R30,R24,R18,R12) -> 1.23 | S36: =MEDIAN(S30,S24,S18,S12) -> 1.17 | T36: =MEDIAN(T30,T24,T18,T12) -> 1.31 | V36: =P10 -> 2018 | W36: =Q10 -> 2019 | X36: =R10 -> 2020 | Y36: =S10 -> 2021 | Z36: =T10 -> 2022
A37: DGW | H37: Inventory Turnover | I37: =I29 -> 6.3 | J37: =J29 -> 4.9 | K37: =K29 -> 4.8 | L37: =L29 -> 5.7 | M37: =M29 -> 4.5 | O37: Quick Ratio | P37: =MEDIAN(P31,P25,P19,P13) -> 0.565 | Q37: =MEDIAN(Q31,Q25,Q19,Q13) -> 0.55 | R37: =MEDIAN(R31,R25,R19,R13) -> 0.865 | S37: =MEDIAN(S31,S25,S19,S13) -> 0.645 | T37: =MEDIAN(T31,T25,T19,T13) -> 0.69 | U37: FRT | V37: =P30-P31 -> 0.62 | W37: =Q30-Q31 -> 0.63 | X37: =R30-R31 -> 0.44 | Y37: =S30-S31 -> 0.54 | Z37: =T30-T31 -> 0.76
A38: 5937371 | B38: 8488069 | C38: 12535638 | D38: 20922813 | E38: 22028135 | H38: COGS | I38: ='FPT Digital Retail JSC | Income'!E28 -> 13254725 | J38: ='FPT Digital Retail JSC | Income'!F28 -> 14522903 | K38: ='FPT Digital Retail JSC | Income'!G28 -> 12620415 | L38: ='FPT Digital Retail JSC | Income'!H28 -> 19343448 | M38: ='FPT Digital Retail JSC | Income'!I28 -> 25462623 | O38: A/E | P38: =MEDIAN(P32,P26,P20,P14) -> 3.45 | Q38: =MEDIAN(Q32,Q26,Q20,Q14) -> 3.365 | R38: =MEDIAN(R32,R26,R20,R14) -> 3.54 | S38: =MEDIAN(S32,S26,S20,S14) -> 4.18 | T38: =MEDIAN(T32,T26,T20,T14) -> 3.66 | U38: MWG | V38: =P18-P19 -> 0.97 | W38: =Q18-Q19 -> 0.9 | X38: =R18-R19 -> 0.66 | Y38: =S18-S19 -> 0.68 | Z38: =T18-T19 -> 0.98
A39: 547084 | B39: 700330 | C39: 941370 | D39: 2844456 | E39: 1210401 | I39: =I38/'FPT Digital Retail JSC | BS'!D37 -> 5.2887337 | J39: =J38/'FPT Digital Retail JSC | BS'!E37 -> 4.2922189 | K39: =K38/'FPT Digital Retail JSC | BS'!F37 -> 6.9087922 | L39: =L38/'FPT Digital Retail JSC | BS'!G37 -> 3.9233346 | M39: =M38/'FPT Digital Retail JSC | BS'!H37 -> 3.9270972 | O39: D/E | P39: =MEDIAN(P33,P27,P21,P15) -> 1.185 | Q39: =MEDIAN(Q33,Q27,Q21,Q15) -> 1.09 | R39: =MEDIAN(R33,R27,R21,R15) -> 1.42 | S39: =MEDIAN(S33,S27,S21,S15) -> 1.61 | T39: =MEDIAN(T33,T27,T21,T15) -> 1.365 | U39: DGW | V39: =P12-P13 -> 0.91 | W39: =Q12-Q13 -> 0.98 | X39: =R12-R13 -> 0.43 | Y39: =S12-S13 -> 0.61 | Z39: =T12-T13 -> 0.84
A40: =A38/A39 -> 10.852759 | B40: =B38/B39 -> 12.120099 | C40: =C38/C39 -> 13.316377 | D40: =D38/D39 -> 7.3556466 | E40: =E38/E39 -> 18.199039 | O40: Interest Coverage Ratio | P40: =MEDIAN(P34,P28,P22,P16) -> 3.0325605 | Q40: =MEDIAN(Q34,Q28,Q22,Q16) -> 1.7494432 | R40: =MEDIAN(R34,R28,R22,R16) -> 2.5997383 | S40: =MEDIAN(S34,S28,S22,S16) -> 4.8286067 | T40: =MEDIAN(T34,T28,T22,T16) -> 1.6292705 | U40: PET | V40: =P24-P25 -> 0.29 | W40: =Q24-Q25 -> 0.38 | X40: =R24-R25 -> 0.18 | Y40: =S24-S25 -> 0.22 | Z40: =T24-T25 -> 0.35
A41: PET | U41: Median | V41: =P36-P37 -> 0.695 | W41: =Q36-Q37 -> 0.685 | X41: =R36-R37 -> 0.365 | Y41: =S36-S37 -> 0.525 | Z41: =T36-T37 -> 0.62
A42: 11091976 | B42: 10008489 | C42: 13453249 | D42: 17598238 | E42: 17543323
A43: 1428095 | B43: 1305856 | C43: 1352898 | D43: 2241130 | E43: 1747165
A44: =A42/A43 -> 7.7669735 | B44: =B42/B43 -> 7.6643129 | C44: =C42/C43 -> 9.9440231 | D44: =D42/D43 -> 7.852395 | E44: =E42/E43 -> 10.041022
H61: Inventory Turnover | I61: 6.3 | J61: 4.9 | K61: 4.8 | L61: 5.7 | M61: 4.5
H62: SGA | I62: ='FPT Digital Retail JSC | Income'!E39 -> 1583114 | J62: ='FPT Digital Retail JSC | Income'!F39 -> 1768320 | K62: ='FPT Digital Retail JSC | Income'!G39 -> 1935903 | L62: ='FPT Digital Retail JSC | Income'!H39 -> 2656653 | M62: ='FPT Digital Retail JSC | Income'!I39 -> 4146636
D64: =B10 -> 2018 | E64: =C10 -> 2019 | F64: =D10 -> 2020 | G64: =E10 -> 2021 | H64: =F10 -> 2022
A65: Changes in Operational Cost | D65: 0.16259953 | E65: 0.098391224 | F65: -0.10476283 | G65: 0.49850612 | H65: 0.35277915
A66: Gross Margin | D66: =B24 -> 0.13358382 | E66: =C24 -> 0.12691247 | F66: =D24 -> 0.13920905 | G66: =E24 -> 0.14009862 | H66: =F24 -> 0.15591093
A67: OPM | D67: =B25 -> 0.026328878 | E67: =C25 -> 0.016401566 | F67: =D25 -> 0.00097664503 | G67: =E25 -> 0.024280816 | H67: =F25 -> 0.015712097
