Workbook

Sheet Landscape
A1: EDTECH MARKET SENTIMENTS:
A2: For: | B2: (1) Greater parental contributions and attentions to their children educational attaintment (2) Confidence from capital inflow. Together with rising gov budget/expenditure for education, the industry is shifting towards digital integration. (3) High digital penetration rate: ~78% of Vietnam population (79,9 mn online users); the figure is 68% for rural areas.
A3: Against: | B3: (1) Negative unit economics and unsustainable models: freemium model does not work lead to high burn rate: many edtech startups are encountered cash shortage due to high CAC, low LTV. (2) Immature monetization behaiviour: as the norms of learning has yet shifted to fully online, edtech startups are enforeced to end up with blended mode which leading to higher investment and operational inefficiency (compared to traditional model)

Sheet TAM
E1: Edtech Key Segments: | H1: TAM | I1: RANK
E2: K-12 Learning | G2: $ | H2: =H8 -> 986452284 | I2: =RANK(H2,$H$2:$H$4,0) -> 2
E3: Foreign language/STEAM Learning | G3: $ | H3: =H15 -> 5.1652569e+08 | I3: =RANK(H3,$H$2:$H$4,0) -> 3
E4: Professional Training | G4: $ | H4: =H26 -> 3992147361 | I4: =RANK(H4,$H$2:$H$4,0) -> 1
E5: Management system/LMS | G5: $ | H5: =H34 -> 5.7884951e+08 | I5: >> not be ranked as this segment has high level of pricing variance and distribution B2B/2G is challenging for private players.
E6: Vietnam Edtech Makret | G6: $ | H6: =SUM(H2:H5) -> 6073974847 | I6: =(Growth!H6/TAM!H6)^(1/5)-1 -> 0.11743843 | J6: >> CAGR
E8: K-12 Learning | H8: =H9*H10*H11 -> 986452284
E9: Students (4 - 17 yrs old) | G9: # | H9: =(8.8*97% + 5.1*87%+ 2.4*59%)*10^6*H12 -> 5424653 | J9: https://tradingeconomics.com/vietnam/primary-education-pupils-wb-data.html | K9: https://data.unicef.org/wp-content/uploads/2022/12/Viet-Nam_Factsheet_21-DecFINAL.pdf
E10: Digital penetration rate | G10: % | H10: 0.788 | J10: https://datareportal.com/reports/digital-2025-vietnam
E11: Average educational spending | G11: $ | H11: =(500000*12)/'ARPU Ref'!A2 -> 230.76923 | J11: https://www.vietnam.vn/en/phu-huynh-chi-bao-nhieu-tien-cho-con-di-hoc-them
E12: Urban population of Vietnam | G12: % | H12: 0.377 | J12: https://tiesea.org/vietnam/#:~:text=STATISTICS,East%20Asia%20region%20(2021).
E15: Foreign language/STEAM Learning | H15: =(H17*H20*H21+(H18+H19)*H20*H22)*H12 -> 5.1652569e+08
E16: # students | G16: # | H16: =SUM(H17:H19) -> 3351767.3
E17: K-12 | G17: # | H17: =H9*(11%+10%+7%+6%+3%+7%) -> 2386847.3 | J17: https://www.slideshare.net/slideshow/vietnam-language-learning-behaviors/249514419
E18: Higher Education | G18: # | H18: =1.9*10^6*29% -> 551000 | J18: https://www.educationfair.net/market-reports/asia/vietnam/
E19: Professionals/Post-grad | G19: # | H19: =(4512+6386+7276+7275+6391)*10^3*26%*5% -> 413920 | J19: https://www.nso.gov.vn/en/px-web/?pxid=E0241&theme=Population%20and%20Employment
E20: Digital penetration rate | G20: % | H20: =H10 -> 0.788 | J20: https://datareportal.com/reports/digital-2025-vietnam
E21: Average tuition fee per enrollment | G21: $ | H21: =AVERAGE('ARPU Ref'!E1:E6) -> 708.33333
E22: Average subscription | G22: $ | H22: =AVERAGE('ARPU Ref'!E8:E12)*6 -> 49.760923
E26: Professional Training | H26: =((H27*H28*11%*H29)+(H27*89%*H30))*H12 -> 3992147361 | J26: https://www.crossroadsvn.com/bridging-vietnams-skills-gap-with-abl/#:~:text=A%202023%20World%20Bank%20study,soft%20skills%20as%20major%20gaps.
E27: Professionals/Post-grad | G27: # | H27: =51860*10^3*70% -> 36302000 | J27: Assuming that highly skilled workforce (11% of total labor force) would train via online platform while low-skilled will join program
E28: Digital penetration rate | G28: % | H28: 0.788 | J28: https://impact.economist.com/new-globalisation/bridging-skills-gap-fuelling-careers-and-economy-vietnam
E29: Average educational spending (Subs) | G29: $ | H29: =AVERAGE('ARPU Ref'!E14:E16) -> 47.996667
E30: Average educational spending (Blended Education) | G30: $ | H30: =AVERAGE('ARPU Ref'!E18:E19) -> 323.07692
E34: Management system/LMS/Platform | H34: =(H35*21/183)*H12 -> 5.7884951e+08
E35: World LMS's market TAM | G35: $ | H35: =13.38*10^9 -> 13380000000 | J35: Assume by taking % of Vietnam edtech market to global edtech market
A40: Key assumptions:
A41: 1) Edtech in Vietnam has 4 major segments with # revenue models: (1) Subscriptions - cheaper, (2) tuition fee (traditional)
A42: 2) Despite 78% digital penetration rate, Vietnam Edtech players even major players like Edupia only has 8% conversion rate, indicating the lack of monetization maturity. For that reason, we expect to focus on the urban population reach.
A43: 3) ARPU is subjected to the population size and reference quality, it might be different in real life.

Sheet Growth
E1: Edtech Key Segments: | H1: TAM
E2: K-12 Learning | G2: $ | H2: =H8 -> 1980427920
E3: Foreign language/STEAM Learning | G3: $ | H3: =H15 -> 1363276542
E4: Professional Training | G4: $ | H4: =H26 -> 6471157241
E5: Management system/LMS | G5: $ | H5: =H34 -> 767704918
E6: Vietnam Edtech Makret | G6: $ | H6: =SUM(H2:H5) -> 10582566622 | I6: 2030
E8: K-12 Learning | H8: =H9*H10*H11 -> 1980427920
E9: Students (4 - 17 yrs old) | G9: # | H9: =((8.8*97% + 5.1*87%+ 2.4*59%)*10^6*H12)*(1+2%)^5 -> 7943309.3
E10: Digital penetration rate | G10: % | H10: =78.8% + 10% -> 0.888 | I10: ∆ | J10: https://archive.opengovasia.com/2025/02/15/digital-transformation-vietnams-key-driver-for-growth/
E11: Average educational spending | G11: $ | H11: =((500000*12)/'ARPU Ref'!A2)*(1+4%)^5 -> 280.76605 | I11: ∆ | J11: >> inflation adjusted only
E12: Urban population of Vietnam | G12: % | H12: 0.5 | I12: ∆
E15: Foreign language/STEAM Learning | H15: =(H17*H20*H21+(H18+H19)*H20*H22)*H12 -> 1363276542
E16: # students | G16: # | H16: =SUM(H17:H19) -> 4459976.1
E17: K-12 | G17: # | H17: =H9*(11%+10%+7%+6%+3%+7%) -> 3495056.1
E18: Higher Education | G18: # | H18: =1.9*10^6*29% -> 551000
E19: Professionals/Post-grad | G19: # | H19: =(4512+6386+7276+7275+6391)*10^3*26%*5% -> 413920
E20: Digital penetration rate | G20: % | H20: =H10 -> 0.888 | I20: ∆
E21: Average tuition fee per enrollment | G21: $ | H21: =AVERAGE('ARPU Ref'!E1:E6)*(1+4%)^5 -> 861.79581 | I21: ∆ | J21: >> inflation adjusted only
E22: Average subscription | G22: $ | H22: =AVERAGE('ARPU Ref'!E8:E12)*6*(1+4%)^5 -> 60.541771 | I22: ∆ | J22: >> inflation adjusted only
E26: Professional Training | H26: =((H27*H28*11%*H29)+(H27*89%*H30))*H12 -> 6471157241
E27: Professionals/Post-grad | G27: # | H27: =51860*10^3*70%+100000 -> 36402000
E28: Digital penetration rate | G28: % | H28: =H20 -> 0.888 | I28: ∆
E29: Average educational spending (Subs) | G29: $ | H29: =AVERAGE('ARPU Ref'!E14:E16)*(1+4%)^5 -> 58.395284 | I29: ∆ | J29: >> inflation adjusted only
E30: Average educational spending (Blended Education) | G30: $ | H30: =AVERAGE('ARPU Ref'!E18:E19)*(1+4%)^5 -> 393.07248 | I30: ∆ | J30: >> inflation adjusted only
E34: Management system/LMS | H34: =(H35*21/183)*H12 -> 767704918
E35: World LMS's market TAM | G35: $ | H35: =13.38*10^9 -> 13380000000

Sheet Investment opportunity
A1: INVESTMENT OPPORTUNITY:
A2: Company Name: | B2: REACH Academy (website: https://www.reach-vietnam.org/vi)
A3: Business model: | B3: An end-to-end educational institutions that provide vocational practice to underseved youth with online platform for job-matching and online classes. REACH has 3 entities, 1 of which serves as an NPO while 2 remaining focus on operate for fee-paying students.
A4: Revenue model: | B4: Tuition fee
A5: Investment rationale:
A6: For: | B6: (1) Market sentiment: market pain points in unskilled employees. Expect to earn 100K graduates over 5 years. (2) Downside risk control: As Reach Academy has commercial entities to back their costs and also be able to utilize current resources to minimize burn (high CAC) (3) Strong network effects: Reach Academy graduates could be directly work at Reach Holdings businesses together with online job-matching platform built based on their partnerships -> High value creation/chain.
A7: Against: | B7: (1) Relatively asset-heavy model: this requires major upfront investment but relatively slower ROI (like traditional education/schooling). (2) USP in technology development/utilization: tech layer within the academy together with vocational students require longer time span to really contribute to flywheel effects.
A8: Company deck | B8: https://global-inst.com/projects/2019_VietnamGLP_Upskilling_to_Transform_the_Vietnamese_Economy.pdf

Sheet ARPU Ref
A1: Ref FX | C1: ILA | E1: =20*10^6/$A$2 -> 769.23077 | G1: https://edu2review.com/reviews/so-sanh-hoc-phi-vus-hay-ila-cao-hon-1357.html
A2: 26000 | C2: VUS | E2: =15*10^6/$A$2 -> 576.92308 | G2: https://edu2review.com/reviews/so-sanh-hoc-phi-vus-hay-ila-cao-hon-1357.html
C3: Ocean Edu | E3: =20*10^6/$A$2 -> 769.23077 | G3: https://edu2review.com/reviews/cap-nhat-hoc-phi-khoa-tieng-anh-tre-em-ocean-edu-14016.html
C4: Apollo | E4: =20.5*10^6/$A$2 -> 788.46154 | G4: https://apollo.edu.vn/tin-tuc-va-su-kien/cong-khai-hoc-phi-2024
C5: BC | E5: =25*10^6/$A$2 -> 961.53846 | G5: Real reference
C6: English Ms.Hoa | E6: =10*10^6/$A$2 -> 384.61538 | G6: https://www.anhngumshoa.com/tin-tuc/khoa-hoc-toeic-lo-trinh-khoa-hoc-tai-anh-ngu-ms-hoa-37374.html
C8: Elsa | E8: =429000/A2 -> 16.5 | G8: https://vn.elsaspeak.com/product-detail/elsa-premium-1-thang/?srsltid=AfmBOooqVbBjs6E-y-Zk4rX5Yr8BtuHypVpmz4nTTZOfm4d-Lj29LdTR
C9: Duolingo | E9: =45000/A2 -> 1.7307692 | G9: https://vi.duolingo.com/super
C10: Busuu | E10: =6.08 -> 6.08 | G10: https://www.busuu.com/products/en
C11: Cake | E11: 13.99 | G11: https://apps.apple.com/vn/app/cake-h%E1%BB%8Dc-ti%E1%BA%BFng-anh-h%C3%A0n/id1350420987?l=vi
C12: Eng Breaking | E12: =38/12 -> 3.1666667
C14: Coursera | E14: 79
C15: Udemy | E15: 35
C16: Linkedin Learning | E16: 29.99
C18: Government budget to upskill | E18: =9*10^6/A2 -> 346.15385 | G18: https://vietnamnews.vn/society/1666472/viet-nam-s-low-skilled-workers-hesitate-to-retrain.html#:~:text=Deputy%20Director%20of%20the%20H%C3%A0,support%20and%20extended%20course%20durations.
C19: Reach Academy | E19: 300 | G19: https://global-inst.com/projects/2019_VietnamGLP_Upskilling_to_Transform_the_Vietnamese_Economy.pdf

Sheet Sources - Charts
A1: No. | B1: Reference list:
A2: =AGGREGATE(3,3,$B$2:B2) -> #NAME? | B2: https://tradingeconomics.com/vietnam/primary-education-pupils-wb-data.html
A3: =AGGREGATE(3,3,$B$2:B3) -> #NAME? | B3: https://datareportal.com/reports/digital-2025-vietnam
A4: =AGGREGATE(3,3,$B$2:B4) -> #NAME? | B4: https://www.vietnam.vn/en/phu-huynh-chi-bao-nhieu-tien-cho-con-di-hoc-them
A5: =AGGREGATE(3,3,$B$2:B5) -> #NAME? | B5: https://tiesea.org/vietnam/#:~:text=STATISTICS,East%20Asia%20region%20(2021).
A6: =AGGREGATE(3,3,$B$2:B6) -> #NAME? | B6: https://www.slideshare.net/slideshow/vietnam-language-learning-behaviors/249514419
A7: =AGGREGATE(3,3,$B$2:B7) -> #NAME? | B7: https://www.educationfair.net/market-reports/asia/vietnam/
A8: =AGGREGATE(3,3,$B$2:B8) -> #NAME? | B8: https://www.nso.gov.vn/en/px-web/?pxid=E0241&theme=Population%20and%20Employment
A9: =AGGREGATE(3,3,$B$2:B9) -> #NAME? | B9: https://datareportal.com/reports/digital-2025-vietnam
A10: =AGGREGATE(3,3,$B$2:B10) -> #NAME? | B10: https://impact.economist.com/new-globalisation/bridging-skills-gap-fuelling-careers-and-economy-vietnam
A11: =AGGREGATE(3,3,$B$2:B11) -> #NAME? | B11: https://documents1.worldbank.org/curated/en/261401596433155112/pdf/Vietnam-s-Human-Capital-Education-Success-and-Future-Challenges.pdf
A12: =AGGREGATE(3,3,$B$2:B12) -> #NAME? | B12: https://en.baochinhphu.vn/viet-nam-to-increase-states-expenditure-on-education-to-at-least-20-111250827221440821.htm
